  1           0 LOAD_CONST               0 (0)
              2 LOAD_CONST               1 (None)
              4 IMPORT_NAME              0 (random)
              6 STORE_NAME               0 (random)

  4           8 LOAD_CONST               2 (<code object func1 at 0x0000019D4A0797C0, file "<dis>", line 4>)
             10 LOAD_CONST               3 ('func1')
             12 MAKE_FUNCTION            0
             14 STORE_NAME               1 (func1)

 33          16 LOAD_CONST               4 (<code object abc at 0x0000019D4A079870, file "<dis>", line 33>)
             18 LOAD_CONST               5 ('abc')
             20 MAKE_FUNCTION            0
             22 STORE_NAME               2 (abc)

 48          24 LOAD_CONST               6 (<code object solution at 0x0000019D4A079920, file "<dis>", line 48>)
             26 LOAD_CONST               7 ('solution')
             28 MAKE_FUNCTION            0
             30 STORE_NAME               3 (solution)

 60          32 LOAD_CONST               8 (<code object func2 at 0x0000019D4A0799D0, file "<dis>", line 60>)
             34 LOAD_CONST               9 ('func2')
             36 MAKE_FUNCTION            0
             38 STORE_NAME               4 (func2)

 67          40 LOAD_CONST              10 (<code object calc at 0x0000019D4A079B30, file "<dis>", line 67>)
             42 LOAD_CONST              11 ('calc')
             44 MAKE_FUNCTION            0
             46 STORE_NAME               5 (calc)

 78          48 LOAD_CONST              12 (<code object encode at 0x0000019D4A079BE0, file "<dis>", line 78>)
             50 LOAD_CONST              13 ('encode')
             52 MAKE_FUNCTION            0
             54 STORE_NAME               6 (encode)

 91          56 LOAD_NAME                7 (__name__)
             58 LOAD_CONST              14 ('__main__')
             60 COMPARE_OP               2 (==)
             62 EXTENDED_ARG            31
             64 POP_JUMP_IF_FALSE     7942

103         110 LOAD_NAME                6 (encode)
            112 LOAD_NAME               11 (str1)
            114 CALL_FUNCTION            1
            116 LOAD_CONST              26 (12)
            118 LOAD_CONST              27 (22)
            120 LOAD_CONST              17 (1)
            122 BUILD_LIST               3
            124 COMPARE_OP               2 (==)
            126 POP_JUMP_IF_TRUE       132
            128 LOAD_GLOBAL             19 (AssertionError)
            130 RAISE_VARARGS            1

104     >>  132 LOAD_NAME                6 (encode)
            134 LOAD_NAME               12 (str2)
            136 CALL_FUNCTION            1
            138 LOAD_CONST              26 (12)
            140 LOAD_CONST              28 (14)
            142 LOAD_CONST              29 (2)
            144 BUILD_LIST               3
            146 COMPARE_OP               2 (==)
            148 POP_JUMP_IF_TRUE       154
            150 LOAD_GLOBAL             19 (AssertionError)
            152 RAISE_VARARGS            1

105     >>  154 LOAD_NAME                6 (encode)
            156 LOAD_NAME               13 (str3)
            158 CALL_FUNCTION            1
            160 LOAD_CONST              26 (12)
            162 LOAD_CONST              27 (22)
            164 LOAD_CONST              30 (3)
            166 BUILD_LIST               3
            168 COMPARE_OP               2 (==)
            170 POP_JUMP_IF_TRUE       176
            172 LOAD_GLOBAL             19 (AssertionError)
            174 RAISE_VARARGS            1

106     >>  176 LOAD_NAME                6 (encode)
            178 LOAD_NAME               14 (str4)
            180 CALL_FUNCTION            1
            182 LOAD_CONST              26 (12)
            184 LOAD_CONST              31 (30)
            186 LOAD_CONST              29 (2)
            188 BUILD_LIST               3
            190 COMPARE_OP               2 (==)
            192 POP_JUMP_IF_TRUE       198
            194 LOAD_GLOBAL             19 (AssertionError)
            196 RAISE_VARARGS            1

107     >>  198 LOAD_NAME                6 (encode)
            200 LOAD_NAME               15 (str5)
            202 CALL_FUNCTION            1
            204 LOAD_CONST              26 (12)
            206 LOAD_CONST              27 (22)
            208 LOAD_CONST              32 (4)
            210 LOAD_CONST              26 (12)
            212 LOAD_CONST              31 (30)
            214 LOAD_CONST              17 (1)
            216 BUILD_LIST               6
            218 COMPARE_OP               2 (==)
            220 POP_JUMP_IF_TRUE       226
            222 LOAD_GLOBAL             19 (AssertionError)
            224 RAISE_VARARGS            1

108     >>  226 LOAD_NAME                6 (encode)
            228 LOAD_NAME               16 (str6)
            230 CALL_FUNCTION            1
            232 LOAD_CONST              26 (12)
            234 LOAD_CONST              27 (22)
            236 LOAD_CONST              17 (1)
            238 LOAD_CONST              26 (12)
            240 LOAD_CONST              31 (30)
            242 LOAD_CONST              32 (4)
            244 BUILD_LIST               6
            246 COMPARE_OP               2 (==)
            248 POP_JUMP_IF_TRUE       254
            250 LOAD_GLOBAL             19 (AssertionError)
            252 RAISE_VARARGS            1

109     >>  254 LOAD_NAME                6 (encode)
            256 LOAD_NAME               17 (str7)
            258 CALL_FUNCTION            1
            260 LOAD_CONST              26 (12)
            262 LOAD_CONST              27 (22)
            264 LOAD_CONST              29 (2)
            266 LOAD_CONST              26 (12)
            268 LOAD_CONST              27 (22)
            270 LOAD_CONST              29 (2)
            272 BUILD_LIST               6
            274 COMPARE_OP               2 (==)
            276 EXTENDED_ARG             1
            278 POP_JUMP_IF_TRUE       284
            280 LOAD_GLOBAL             19 (AssertionError)
            282 RAISE_VARARGS            1

110     >>  284 LOAD_NAME                6 (encode)
            286 LOAD_NAME               18 (str8)
            288 CALL_FUNCTION            1
            290 LOAD_CONST              26 (12)
            292 LOAD_CONST              28 (14)
            294 LOAD_CONST              30 (3)
            296 LOAD_CONST              26 (12)
            298 LOAD_CONST              33 (38)
            300 LOAD_CONST              29 (2)
            302 BUILD_LIST               6
            304 COMPARE_OP               2 (==)
            306 EXTENDED_ARG             1
            308 POP_JUMP_IF_TRUE       314
            310 LOAD_GLOBAL             19 (AssertionError)
            312 RAISE_VARARGS            1

111     >>  314 LOAD_NAME                8 (num1)
            316 LOAD_NAME                3 (solution)
            318 LOAD_CONST              34 ('a')
            320 LOAD_NAME               11 (str1)
            322 LOAD_NAME               12 (str2)
            324 LOAD_NAME               13 (str3)
            326 LOAD_NAME               14 (str4)
            328 LOAD_CONST              35 ('bda')
            330 LOAD_NAME               15 (str5)
            332 LOAD_NAME               16 (str6)
            334 LOAD_NAME               17 (str7)
            336 LOAD_NAME               18 (str8)
            338 LOAD_CONST              36 ('bcdef')
            340 LOAD_CONST              37 ('aabcc')
            342 LOAD_CONST              38 ('acbac')
            344 LOAD_CONST              39 ('bdcaa')
            346 LOAD_CONST              40 ('bbbbcc')
            348 LOAD_CONST              41 ('babccc')
            350 LOAD_CONST              42 ('abaccc')
            352 BUILD_LIST              17
            354 CALL_FUNCTION            1
            356 COMPARE_OP               2 (==)
            358 EXTENDED_ARG             1
            360 POP_JUMP_IF_TRUE       366
            362 LOAD_GLOBAL             19 (AssertionError)
            364 RAISE_VARARGS            1

112     >>  366 LOAD_NAME                9 (num2)
            368 LOAD_NAME                3 (solution)
            370 LOAD_CONST              43 ('klmnowx')
            372 LOAD_CONST              44 ('abcdefgiklmno')
            374 LOAD_CONST              45 ('fgij')
            376 LOAD_CONST              46 ('bcfghijklmno')
            378 LOAD_CONST              47 ('fgjpqrst')
            380 LOAD_CONST              48 ('uy')
            382 LOAD_CONST              49 ('abceklmnouvw')
            384 LOAD_CONST              50 ('pqrstuwy')
            386 LOAD_CONST              51 ('fghijlno')
            388 LOAD_CONST              52 ('mnouvwxy')
            390 LOAD_CONST              53 ('klmnopqt')
            392 LOAD_CONST              54 ('klmnopqrstuy')
            394 LOAD_CONST              55 ('aeuvw')
            396 LOAD_CONST              56 ('muvw')
            398 LOAD_CONST              57 ('abcdeklmnow')
            400 LOAD_CONST              58 ('fhijpqrst')
            402 LOAD_CONST              59 ('mpqrst')
            404 LOAD_CONST              60 ('klmnoprt')
            406 LOAD_CONST              61 ('fghijklno')
            408 LOAD_CONST              62 ('abcdelmo')
            410 LOAD_CONST              63 ('klnuvwxy')
            412 LOAD_CONST              64 ('klmnopst')
            414 LOAD_CONST              65 ('abcdeklmnov')
            416 LOAD_CONST              66 ('fghj')
            418 LOAD_CONST              67 ('luvwxy')
            420 LOAD_CONST              68 ('ghklmnopqrst')
            422 LOAD_CONST              69 ('pqrstwx')
            424 LOAD_CONST              70 ('abcdklmno')
            426 LOAD_CONST              71 ('cdefghij')
            428 LOAD_CONST              72 ('pqrs')
            430 LOAD_CONST              73 ('efghijklmno')
            432 LOAD_CONST              74 ('fghjklmno')
            434 LOAD_CONST              75 ('adeklmno')
            436 LOAD_CONST              76 ('rs')
            438 LOAD_CONST              77 ('kuvwxy')
            440 LOAD_CONST              78 ('ghij')
            442 LOAD_CONST              79 ('befghijklmno')
            444 LOAD_CONST              80 ('ln')
            446 LOAD_CONST              81 ('hijklmnopqrst')
            448 LOAD_CONST              82 ('ghpqrst')
            450 LOAD_CONST              83 ('fgiklmnopqrst')
            452 LOAD_CONST              84 ('pqrtuvwxy')
            454 LOAD_CONST              85 ('pqrsty')
            456 LOAD_CONST              86 ('jklmnopqrst')
            458 LOAD_CONST              87 ('lnouvwxy')
            460 LOAD_CONST              88 ('klmnoqsuvwxy')
            462 LOAD_CONST              89 ('abcdeghklmno')
            464 LOAD_CONST              90 ('fi')
            466 LOAD_CONST              91 ('fghijlnpqrst')
            468 LOAD_CONST              92 ('abdklmnouvw')
            470 LOAD_CONST              93 ('uwx')
            472 LOAD_CONST              94 ('abcdekln')
            474 LOAD_CONST              95 ('klmno')
            476 LOAD_CONST              96 ('abcdekn')
            478 LOAD_CONST              97 ('abcdemuvw')
            480 LOAD_CONST              98 ('pqs')
            482 LOAD_CONST              99 ('fghijpqt')
            484 LOAD_CONST             100 ('klmnopqrstuw')
            486 LOAD_CONST             101 ('n')
            488 LOAD_CONST             102 ('nopqrstuvwxy')
            490 LOAD_CONST             103 ('abcdefghj')
            492 LOAD_CONST             104 ('fghiklmnopqrst')
            494 LOAD_CONST             105 ('klmnorst')
            496 LOAD_CONST             106 ('abcdemnouvw')
            498 LOAD_CONST             107 ('fgh')
            500 LOAD_CONST             108 ('pqt')
            502 LOAD_CONST             109 ('abfghij')
            504 LOAD_CONST             110 ('o')
            506 LOAD_CONST             111 ('nouvw')
            508 LOAD_CONST             112 ('abcdklmnouvw')
            510 LOAD_CONST             113 ('abeklmno')
            512 LOAD_CONST             114 ('abcden')
            514 LOAD_CONST             115 ('klmnopqrstwxy')
            516 LOAD_CONST             116 ('q')
            518 LOAD_CONST             117 ('fghijklmnoprt')
            520 LOAD_CONST             118 ('klmnovx')
            522 LOAD_CONST             119 ('abceuvw')
            524 LOAD_CONST             120 ('klmnopsuvwxy')
            526 LOAD_CONST             121 ('hj')
            528 LOAD_CONST             122 ('abcdefgh')
            530 LOAD_CONST             123 ('fhjklmno')
            532 LOAD_CONST             124 ('klmnoquvwxy')
            534 LOAD_CONST             125 ('wxy')
            536 LOAD_CONST             126 ('klmnopqrstuvwy')
            538 LOAD_CONST             127 ('kln')
            540 LOAD_CONST             128 ('abcdegklmno')
            542 LOAD_CONST             129 ('mno')
            544 LOAD_CONST             130 ('gklmno')
            546 LOAD_CONST             131 ('klnouvw')
            548 LOAD_CONST             132 ('fghijklmnoqr')
            550 LOAD_CONST             133 ('fghijpqrst')
            552 LOAD_CONST             134 ('mnuvwxy')
            554 LOAD_CONST             135 ('ghipqrst')
            556 LOAD_CONST             136 ('klmnoqrtuvwxy')
            558 LOAD_CONST             137 ('acdfghij')
            560 LOAD_CONST             138 ('uwy')
            562 LOAD_CONST             139 ('fghjklmnopqrst')
            564 LOAD_CONST             140 ('mnpqrstuvwxy')
            566 LOAD_CONST             141 ('abcdeknouvw')
            568 LOAD_CONST             142 ('abcdefghijklmno')
            570 LOAD_CONST             143 ('klmnorsuvwxy')
            572 LOAD_CONST             144 ('abcdeh')
            574 LOAD_CONST             145 ('klmnost')
            576 LOAD_CONST             146 ('iklmnopqrst')
            578 LOAD_CONST             147 ('abcdegijklmno')
            580 LOAD_CONST             148 ('fghijklmopqrst')
            582 LOAD_CONST             149 ('fghijklmnors')
            584 LOAD_CONST             150 ('pqrstux')
            586 LOAD_CONST             151 ('abcdefghijlm')
            588 LOAD_CONST             152 ('abcdem')
            590 LOAD_CONST             153 ('klmn')
            592 LOAD_CONST             154 ('opqrst')
            594 LOAD_CONST             155 ('ghjklmnopqrst')
            596 LOAD_CONST             156 ('cdfghij')
            598 LOAD_CONST             157 ('kluvwxy')
            600 LOAD_CONST             158 ('ceklmno')
            602 LOAD_CONST             159 ('abcdeghijklmno')
            604 LOAD_CONST             160 ('lmo')
            606 LOAD_CONST             161 ('bklmno')
            608 LOAD_CONST             162 ('fghijs')
            610 LOAD_CONST             163 ('cdeklmnouvw')
            612 LOAD_CONST             164 ('abcdeknuvw')
            614 LOAD_CONST             165 ('cdklmnouvw')
            616 LOAD_CONST             166 ('abcdeklmnovw')
            618 LOAD_CONST             167 ('klmnopr')
            620 LOAD_CONST             168 ('fghijklmnopqrst')
            622 LOAD_CONST             169 ('klmnopqtuvwxy')
            624 LOAD_CONST             170 ('abcdefhijklmno')
            626 LOAD_CONST             171 ('abcdeuv')
            628 LOAD_CONST             172 ('abcdefhklmno')
            630 LOAD_CONST             173 ('x')
            632 LOAD_CONST             174 ('abcdeouvw')
            634 LOAD_CONST             175 ('fjklmno')
            636 LOAD_CONST              34 ('a')
            638 LOAD_CONST             176 ('klmnopqrstuv')
            640 LOAD_CONST             177 ('abdklmno')
            642 LOAD_CONST             178 ('fghijlm')
            644 LOAD_CONST             179 ('bcefghijklmno')
            646 LOAD_CONST             180 ('quvwxy')
            648 LOAD_CONST             181 ('fghi')
            650 LOAD_CONST             182 ('klmnopqrstuwx')
            652 LOAD_CONST             183 ('r')
            654 LOAD_CONST             184 ('klmnuvw')
            656 LOAD_CONST             185 ('kn')
            658 LOAD_CONST             186 ('abcdeklmn')
            660 LOAD_CONST             187 ('abcdeklmno')
            662 LOAD_CONST             188 ('ps')
            664 LOAD_CONST             189 ('klmnoqrt')
            666 LOAD_CONST             190 ('pstuvwxy')
            668 LOAD_CONST             191 ('klmnopqrsty')
            670 LOAD_CONST             192 ('lmn')
            672 LOAD_CONST             193 ('d')
            674 LOAD_CONST             194 ('abcdefghijmo')
            676 LOAD_CONST             195 ('fghijmnopqrst')
            678 LOAD_CONST             196 ('ghiklmno')
            680 LOAD_CONST             197 ('mouvwxy')
            682 LOAD_CONST             198 ('abcdeghj')
            684 LOAD_CONST             199 ('fghijklmnopr')
            686 LOAD_CONST             200 ('kmnouvwxy')
            688 LOAD_CONST             201 ('fghijklmnopqst')
            690 LOAD_CONST             202 ('klmnox')
            692 LOAD_CONST             203 ('nouvwxy')
            694 LOAD_CONST             204 ('adefghijklmno')
            696 LOAD_CONST             205 ('kmo')
            698 LOAD_CONST             206 ('klmnovy')
            700 LOAD_CONST             207 ('klmnopqrstuvwxy')
            702 LOAD_CONST             208 ('cde')
            704 LOAD_CONST             209 ('y')
            706 LOAD_CONST             210 ('klmnouy')
            708 LOAD_CONST             211 ('fgklmnopqrst')
            710 LOAD_CONST             212 ('nuvwxy')
            712 LOAD_CONST             213 ('kluvw')
            714 LOAD_CONST             214 ('abcdefghijkno')
            716 LOAD_CONST             215 ('abcdekl')
            718 LOAD_CONST             216 ('fghijno')
            720 LOAD_CONST             217 ('ceuvw')
            722 LOAD_CONST             218 ('abcdelo')
            724 LOAD_CONST             219 ('bcdklmno')
            726 LOAD_CONST             220 ('gij')
            728 LOAD_CONST             221 ('abcdeijklmno')
            730 LOAD_CONST             222 ('klmnopqrt')
            732 LOAD_CONST             223 ('abcdeklm')
            734 LOAD_CONST             224 ('pqruvwxy')
            736 LOAD_CONST             225 ('klnuvw')
            738 LOAD_CONST             226 ('fijklmno')
            740 LOAD_CONST             227 ('knpqrstuvwxy')
            742 LOAD_CONST             228 ('fghijklmnor')
            744 LOAD_CONST             229 ('ace')
            746 LOAD_CONST             230 ('abcdekluvw')
            748 LOAD_CONST             231 ('deklmnouvw')
            750 LOAD_CONST             232 ('lpqrstuvwxy')
            752 LOAD_CONST             233 ('abcdefhiklmno')
            754 LOAD_CONST             234 ('fijpqrst')
            756 LOAD_CONST             235 ('klmnopqrstvwy')
            758 LOAD_CONST             236 ('mn')
            760 LOAD_CONST             237 ('kmpqrst')
            762 LOAD_CONST             238 ('ipqrst')
            764 LOAD_CONST             239 ('fghijkmnpqrst')
            766 LOAD_CONST             240 ('uvxy')
            768 LOAD_CONST             241 ('bklmnouvw')
            770 LOAD_CONST             242 ('fghijkmnopqrst')
            772 LOAD_CONST             243 ('fghijklnopqrst')
            774 LOAD_CONST             244 ('kopqrstuvwxy')
            776 LOAD_CONST             245 ('pqrstuwxy')
            778 LOAD_CONST             246 ('abdeuvw')
            780 LOAD_CONST             247 ('acefghij')
            782 LOAD_CONST             248 ('jklmno')
            784 LOAD_CONST             249 ('k')
            786 LOAD_CONST             250 ('fghijqs')
            788 LOAD_CONST             251 ('abcdefghijno')
            790 LOAD_CONST             252 ('fghijklmnort')
            792 LOAD_CONST             253 ('adeuvw')
            794 LOAD_CONST             254 ('vwx')
            796 LOAD_CONST             255 ('gjklmno')
            798 EXTENDED_ARG             1
            800 LOAD_CONST             256 ('hi')
            802 EXTENDED_ARG             1
            804 LOAD_CONST             257 ('abcdefghijm')
            806 EXTENDED_ARG             1
            808 LOAD_CONST             258 ('nuvw')
            810 EXTENDED_ARG             1
            812 LOAD_CONST             259 ('fklmnopqrst')
            814 EXTENDED_ARG             1
            816 LOAD_CONST             260 ('abcdehklmno')
            818 EXTENDED_ARG             1
            820 LOAD_CONST             261 ('fghijklmnoqrt')
            822 EXTENDED_ARG             1
            824 LOAD_CONST             262 ('klmnoruvwxy')
            826 EXTENDED_ARG             1
            828 LOAD_CONST             263 ('abcdemnuvw')
            830 EXTENDED_ARG             1
            832 LOAD_CONST             264 ('klmnovw')
            834 EXTENDED_ARG             1
            836 LOAD_CONST             265 ('klmnopqrstvw')
            838 EXTENDED_ARG             1
            840 LOAD_CONST             266 ('klmnoqtuvwxy')
            842 EXTENDED_ARG             1
            844 LOAD_CONST             267 ('klmnoy')
            846 EXTENDED_ARG             1
            848 LOAD_CONST             268 ('wx')
            850 EXTENDED_ARG             1
            852 LOAD_CONST             269 ('ouvwxy')
            854 EXTENDED_ARG             1
            856 LOAD_CONST             270 ('lmopqrst')
            858 EXTENDED_ARG             1
            860 LOAD_CONST             271 ('fghjpqrst')
            862 EXTENDED_ARG             1
            864 LOAD_CONST             272 ('lnuvwxy')
            866 EXTENDED_ARG             1
            868 LOAD_CONST             273 ('vy')
            870 EXTENDED_ARG             1
            872 LOAD_CONST             274 ('abdfghijklmno')
            874 EXTENDED_ARG             1
            876 LOAD_CONST             275 ('kmnouvw')
            878 EXTENDED_ARG             1
            880 LOAD_CONST             276 ('uvy')
            882 EXTENDED_ARG             1
            884 LOAD_CONST             277 ('klmnoqst')
            886 EXTENDED_ARG             1
            888 LOAD_CONST             278 ('klmnort')
            890 EXTENDED_ARG             1
            892 LOAD_CONST             279 ('pqrstuxy')
            894 EXTENDED_ARG             1
            896 LOAD_CONST             280 ('qs')
            898 EXTENDED_ARG             1
            900 LOAD_CONST             281 ('lopqrstuvwxy')
            902 EXTENDED_ARG             1
            904 LOAD_CONST             282 ('mnouvw')
            906 EXTENDED_ARG             1
            908 LOAD_CONST             283 ('abdeklmno')
            910 EXTENDED_ARG             1
            912 LOAD_CONST             284 ('abcdelnouvw')
            914 EXTENDED_ARG             1
            916 LOAD_CONST             285 ('pruvwxy')
            918 EXTENDED_ARG             1
            920 LOAD_CONST             286 ('qrsuvwxy')
            922 EXTENDED_ARG             1
            924 LOAD_CONST             287 ('cklmno')
            926 LOAD_CONST              20 ('bc')
            928 EXTENDED_ARG             1
            930 LOAD_CONST             288 ('acdfghijklmno')
            932 EXTENDED_ARG             1
            934 LOAD_CONST             289 ('j')
            936 EXTENDED_ARG             1
            938 LOAD_CONST             290 ('fghijpqs')
            940 EXTENDED_ARG             1
            942 LOAD_CONST             291 ('fghijknopqrst')
            944 EXTENDED_ARG             1
            946 LOAD_CONST             292 ('fgijklmno')
            948 EXTENDED_ARG             1
            950 LOAD_CONST             293 ('fghijnopqrst')
            952 EXTENDED_ARG             1
            954 LOAD_CONST             294 ('mpqrstuvwxy')
            956 EXTENDED_ARG             1
            958 LOAD_CONST             295 ('knopqrst')
            960 EXTENDED_ARG             1
            962 LOAD_CONST             296 ('acdeuvw')
            964 EXTENDED_ARG             1
            966 LOAD_CONST             297 ('lnouvw')
            968 EXTENDED_ARG             1
            970 LOAD_CONST             298 ('fghijklmn')
            972 EXTENDED_ARG             1
            974 LOAD_CONST             299 ('klmnouvxy')
            976 EXTENDED_ARG             1
            978 LOAD_CONST             300 ('abcdefghiklmno')
            980 EXTENDED_ARG             1
            982 LOAD_CONST             301 ('abcdefghij')
            984 EXTENDED_ARG             1
            986 LOAD_CONST             302 ('hij')
            988 EXTENDED_ARG             1
            990 LOAD_CONST             303 ('abcdekuvw')
            992 EXTENDED_ARG             1
            994 LOAD_CONST             304 ('klmnopqs')
            996 EXTENDED_ARG             1
            998 LOAD_CONST             305 ('aklmnouvw')
           1000 EXTENDED_ARG             1
           1002 LOAD_CONST             306 ('acdefghijklmno')
           1004 EXTENDED_ARG             1
           1006 LOAD_CONST             307 ('cfghij')
           1008 EXTENDED_ARG             1
           1010 LOAD_CONST             308 ('fghijpqst')
           1012 EXTENDED_ARG             1
           1014 LOAD_CONST             309 ('cfghijklmno')
           1016 EXTENDED_ARG             1
           1018 LOAD_CONST             310 ('abcdefhi')
           1020 EXTENDED_ARG             1
           1022 LOAD_CONST             311 ('kmouvwxy')
           1024 EXTENDED_ARG             1
           1026 LOAD_CONST             312 ('pquvwxy')
           1028 EXTENDED_ARG             1
           1030 LOAD_CONST             313 ('pqrstuy')
           1032 EXTENDED_ARG             1
           1034 LOAD_CONST             314 ('pqrstuwx')
           1036 EXTENDED_ARG             1
           1038 LOAD_CONST             315 ('ce')
           1040 EXTENDED_ARG             1
           1042 LOAD_CONST             316 ('klmnopqrstv')
           1044 EXTENDED_ARG             1
           1046 LOAD_CONST             317 ('deklmno')
           1048 EXTENDED_ARG             1
           1050 LOAD_CONST             318 ('klmnouvw')
           1052 EXTENDED_ARG             1
           1054 LOAD_CONST             319 ('abcdeno')
           1056 EXTENDED_ARG             1
           1058 LOAD_CONST             320 ('fghijkmo')
           1060 EXTENDED_ARG             1
           1062 LOAD_CONST             321 ('knouvwxy')
           1064 EXTENDED_ARG             1
           1066 LOAD_CONST             322 ('fpqrst')
           1068 EXTENDED_ARG             1
           1070 LOAD_CONST             323 ('hklmno')
           1072 EXTENDED_ARG             1
           1074 LOAD_CONST             324 ('fghijkmopqrst')
           1076 EXTENDED_ARG             1
           1078 LOAD_CONST             325 ('abcdefghjklmno')
           1080 EXTENDED_ARG             1
           1082 LOAD_CONST             326 ('kmpqrstuvwxy')
           1084 EXTENDED_ARG             1
           1086 LOAD_CONST             327 ('dklmnouvw')
           1088 EXTENDED_ARG             1
           1090 LOAD_CONST             328 ('abcdefghijkmo')
           1092 EXTENDED_ARG             1
           1094 LOAD_CONST             329 ('abcdel')
           1096 EXTENDED_ARG             1
           1098 LOAD_CONST             330 ('giklmnopqrst')
           1100 EXTENDED_ARG             1
           1102 LOAD_CONST             331 ('buvw')
           1104 EXTENDED_ARG             1
           1106 LOAD_CONST             332 ('klmo')
           1108 EXTENDED_ARG             1
           1110 LOAD_CONST             333 ('klmnoqrsuvwxy')
           1112 EXTENDED_ARG             1
           1114 LOAD_CONST             334 ('uvwy')
           1116 EXTENDED_ARG             1
           1118 LOAD_CONST             335 ('abcdeluvw')
           1120 EXTENDED_ARG             1
           1122 LOAD_CONST             336 ('klmnostuvwxy')
           1124 EXTENDED_ARG             1
           1126 LOAD_CONST             337 ('bceklmno')
           1128 EXTENDED_ARG             1
           1130 LOAD_CONST             338 ('fghijm')
           1132 EXTENDED_ARG             1
           1134 LOAD_CONST             339 ('defghijklmno')
           1136 EXTENDED_ARG             1
           1138 LOAD_CONST             340 ('ijklmno')
           1140 EXTENDED_ARG             1
           1142 LOAD_CONST             341 ('pqr')
           1144 EXTENDED_ARG             1
           1146 LOAD_CONST             342 ('abcduvw')
           1148 EXTENDED_ARG             1
           1150 LOAD_CONST             343 ('fghijklmnopqt')
           1152 EXTENDED_ARG             1
           1154 LOAD_CONST             344 ('hijklmno')
           1156 EXTENDED_ARG             1
           1158 LOAD_CONST             345 ('klmnoprsuvwxy')
           1160 EXTENDED_ARG             1
           1162 LOAD_CONST             346 ('aeklmno')
           1164 EXTENDED_ARG             1
           1166 LOAD_CONST             347 ('lo')
           1168 EXTENDED_ARG             1
           1170 LOAD_CONST             348 ('klmnouxy')
           1172 EXTENDED_ARG             1
           1174 LOAD_CONST             349 ('cdklmno')
           1176 EXTENDED_ARG             1
           1178 LOAD_CONST             350 ('fghijpr')
           1180 EXTENDED_ARG             1
           1182 LOAD_CONST             351 ('muvwxy')
           1184 EXTENDED_ARG             1
           1186 LOAD_CONST             352 ('lmnouvwxy')
           1188 EXTENDED_ARG             1
           1190 LOAD_CONST             353 ('abce')
           1192 EXTENDED_ARG             1
           1194 LOAD_CONST             354 ('kmnopqrst')
           1196 EXTENDED_ARG             1
           1198 LOAD_CONST             355 ('pt')
           1200 EXTENDED_ARG             1
           1202 LOAD_CONST             356 ('klmnoptuvwxy')
           1204 EXTENDED_ARG             1
           1206 LOAD_CONST             357 ('abde')
           1208 EXTENDED_ARG             1
           1210 LOAD_CONST             358 ('abcdeghiklmno')
           1212 EXTENDED_ARG             1
           1214 LOAD_CONST             359 ('klmnopqsuvwxy')
           1216 EXTENDED_ARG             1
           1218 LOAD_CONST             360 ('klmnouvx')
           1220 EXTENDED_ARG             1
           1222 LOAD_CONST             361 ('efghij')
           1224 EXTENDED_ARG             1
           1226 LOAD_CONST             362 ('klmnouwy')
           1228 EXTENDED_ARG             1
           1230 LOAD_CONST             363 ('bceklmnouvw')
           1232 EXTENDED_ARG             1
           1234 LOAD_CONST             364 ('klmnuvwxy')
           1236 EXTENDED_ARG             1
           1238 LOAD_CONST             365 ('ad')
           1240 EXTENDED_ARG             1
           1242 LOAD_CONST             366 ('klmnoux')
           1244 EXTENDED_ARG             1
           1246 LOAD_CONST             367 ('gjpqrst')
           1248 EXTENDED_ARG             1
           1250 LOAD_CONST             368 ('abcdegij')
           1252 EXTENDED_ARG             1
           1254 LOAD_CONST             369 ('fghijkpqrst')
           1256 EXTENDED_ARG             1
           1258 LOAD_CONST             370 ('fghijlmnopqrst')
           1260 EXTENDED_ARG             1
           1262 LOAD_CONST             371 ('abcdefj')
           1264 EXTENDED_ARG             1
           1266 LOAD_CONST             372 ('fghijklmnops')
           1268 EXTENDED_ARG             1
           1270 LOAD_CONST             373 ('fghijklmnoqs')
           1272 EXTENDED_ARG             1
           1274 LOAD_CONST             374 ('ghi')
           1276 EXTENDED_ARG             1
           1278 LOAD_CONST             375 ('fghijqst')
           1280 EXTENDED_ARG             1
           1282 LOAD_CONST             376 ('abcdemo')
           1284 EXTENDED_ARG             1
           1286 LOAD_CONST             377 ('abcdefghijkl')
           1288 EXTENDED_ARG             1
           1290 LOAD_CONST             378 ('fghklmnopqrst')
           1292 EXTENDED_ARG             1
           1294 LOAD_CONST             379 ('no')
           1296 EXTENDED_ARG             1
           1298 LOAD_CONST             380 ('klmnopqrstuwxy')
           1300 EXTENDED_ARG             1
           1302 LOAD_CONST             381 ('klmnopqrstvwx')
           1304 EXTENDED_ARG             1
           1306 LOAD_CONST             382 ('abcdeklmnou')
           1308 EXTENDED_ARG             1
           1310 LOAD_CONST             383 ('abdefghijklmno')
           1312 EXTENDED_ARG             1
           1314 LOAD_CONST             384 ('klmnopqrstxy')
           1316 EXTENDED_ARG             1
           1318 LOAD_CONST             385 ('acfghij')
           1320 EXTENDED_ARG             1
           1322 LOAD_CONST             386 ('pqrstuvwy')
           1324 EXTENDED_ARG             1
           1326 LOAD_CONST             387 ('kuvw')
           1328 EXTENDED_ARG             1
           1330 LOAD_CONST             388 ('abcdehi')
           1332 EXTENDED_ARG             1
           1334 LOAD_CONST             389 ('de')
           1336 EXTENDED_ARG             1
           1338 LOAD_CONST             390 ('fghijpq')
           1340 EXTENDED_ARG             1
           1342 LOAD_CONST             391 ('lmuvwxy')
           1344 EXTENDED_ARG             1
           1346 LOAD_CONST             392 ('abcdelmouvw')
           1348 EXTENDED_ARG             1
           1350 LOAD_CONST             393 ('abdfghij')
           1352 EXTENDED_ARG             1
           1354 LOAD_CONST             394 ('knuvwxy')
           1356 EXTENDED_ARG             1
           1358 LOAD_CONST             395 ('acde')
           1360 EXTENDED_ARG             1
           1362 LOAD_CONST             396 ('cuvw')
           1364 EXTENDED_ARG             1
           1366 LOAD_CONST             397 ('uw')
           1368 EXTENDED_ARG             1
           1370 LOAD_CONST             398 ('kmopqrstuvwxy')
           1372 EXTENDED_ARG             1
           1374 LOAD_CONST             399 ('abcfghij')
           1376 EXTENDED_ARG             1
           1378 LOAD_CONST             400 ('fghij')
           1380 EXTENDED_ARG             1
           1382 LOAD_CONST             401 ('abcdeklmo')
           1384 EXTENDED_ARG             1
           1386 LOAD_CONST             402 ('abcdehij')
           1388 EXTENDED_ARG             1
           1390 LOAD_CONST             403 ('abcdek')
           1392 EXTENDED_ARG             1
           1394 LOAD_CONST             404 ('fghijklmnoqrst')
           1396 EXTENDED_ARG             1
           1398 LOAD_CONST             405 ('pqrstvx')
           1400 EXTENDED_ARG             1
           1402 LOAD_CONST             406 ('klmnopqrstvx')
           1404 LOAD_CONST               5 ('abc')
           1406 EXTENDED_ARG             1
           1408 LOAD_CONST             407 ('klmnoqrstuvwxy')
           1410 EXTENDED_ARG             1
           1412 LOAD_CONST             408 ('acklmnouvw')
           1414 EXTENDED_ARG             1
           1416 LOAD_CONST             409 ('afghijklmno')
           1418 EXTENDED_ARG             1
           1420 LOAD_CONST             410 ('abcdeklmnuvw')
           1422 EXTENDED_ARG             1
           1424 LOAD_CONST             411 ('abcdei')
           1426 EXTENDED_ARG             1
           1428 LOAD_CONST             412 ('fgiklmno')
           1430 EXTENDED_ARG             1
           1432 LOAD_CONST             413 ('klmnopqrstuvw')
           1434 EXTENDED_ARG             1
           1436 LOAD_CONST             414 ('abcklmnouvw')
           1438 EXTENDED_ARG             1
           1440 LOAD_CONST             415 ('abcdelmnuvw')
           1442 EXTENDED_ARG             1
           1444 LOAD_CONST             416 ('abcdehj')
           1446 EXTENDED_ARG             1
           1448 LOAD_CONST             417 ('abcdefghijlo')
           1450 EXTENDED_ARG             1
           1452 LOAD_CONST             418 ('fghpqrst')
           1454 EXTENDED_ARG             1
           1456 LOAD_CONST             419 ('acfghijklmno')
           1458 EXTENDED_ARG             1
           1460 LOAD_CONST             420 ('abcdeg')
           1462 EXTENDED_ARG             1
           1464 LOAD_CONST             421 ('klpqrst')
           1466 EXTENDED_ARG             1
           1468 LOAD_CONST             422 ('klmouvw')
           1470 EXTENDED_ARG             1
           1472 LOAD_CONST             423 ('bdfghijklmno')
           1474 EXTENDED_ARG             1
           1476 LOAD_CONST             424 ('aefghijklmno')
           1478 EXTENDED_ARG             1
           1480 LOAD_CONST             425 ('fijklmnopqrst')
           1482 EXTENDED_ARG             1
           1484 LOAD_CONST             426 ('fghijps')
           1486 EXTENDED_ARG             1
           1488 LOAD_CONST             427 ('fghijklnpqrst')
           1490 EXTENDED_ARG             1
           1492 LOAD_CONST             428 ('fghijklmnop')
           1494 EXTENDED_ARG             1
           1496 LOAD_CONST             429 ('fklmno')
           1498 EXTENDED_ARG             1
           1500 LOAD_CONST             430 ('klmnopqrstw')
           1502 EXTENDED_ARG             1
           1504 LOAD_CONST             431 ('abcdfghijklmno')
           1506 EXTENDED_ARG             1
           1508 LOAD_CONST             432 ('fj')
           1510 EXTENDED_ARG             1
           1512 LOAD_CONST             433 ('lnopqrst')
           1514 EXTENDED_ARG             1
           1516 LOAD_CONST             434 ('fghijkmpqrst')
           1518 EXTENDED_ARG             1
           1520 LOAD_CONST             435 ('fghijlnopqrst')
           1522 EXTENDED_ARG             1
           1524 LOAD_CONST             436 ('ux')
           1526 EXTENDED_ARG             1
           1528 LOAD_CONST             437 ('fgjklmno')
           1530 EXTENDED_ARG             1
           1532 LOAD_CONST             438 ('fghijklmnopqr')
           1534 EXTENDED_ARG             1
           1536 LOAD_CONST             439 ('abcdeghjklmno')
           1538 EXTENDED_ARG             1
           1540 LOAD_CONST             440 ('abcdefghijkmn')
           1542 EXTENDED_ARG             1
           1544 LOAD_CONST             441 ('abcdegiklmno')
           1546 EXTENDED_ARG             1
           1548 LOAD_CONST             442 ('abcdefiklmno')
           1550 EXTENDED_ARG             1
           1552 LOAD_CONST             443 ('acdeklmno')
           1554 EXTENDED_ARG             1
           1556 LOAD_CONST             444 ('klmnops')
           1558 EXTENDED_ARG             1
           1560 LOAD_CONST             445 ('fghijklmnopqrt')
           1562 EXTENDED_ARG             1
           1564 LOAD_CONST             446 ('fghijklmnoqt')
           1566 EXTENDED_ARG             1
           1568 LOAD_CONST             447 ('abcdegj')
           1570 EXTENDED_ARG             1
           1572 LOAD_CONST             448 ('acdklmno')
           1574 EXTENDED_ARG             1
           1576 LOAD_CONST             449 ('abcdeghi')
           1578 EXTENDED_ARG             1
           1580 LOAD_CONST             450 ('abcdelmuvw')
           1582 EXTENDED_ARG             1
           1584 LOAD_CONST             451 ('abcdefg')
           1586 EXTENDED_ARG             1
           1588 LOAD_CONST             452 ('fghijkl')
           1590 EXTENDED_ARG             1
           1592 LOAD_CONST             453 ('gjklmnopqrst')
           1594 EXTENDED_ARG             1
           1596 LOAD_CONST             454 ('hipqrst')
           1598 EXTENDED_ARG             1
           1600 LOAD_CONST             455 ('klmnopqstuvwxy')
           1602 EXTENDED_ARG             1
           1604 LOAD_CONST             456 ('lnuvw')
           1606 EXTENDED_ARG             1
           1608 LOAD_CONST             457 ('ghijpqrst')
           1610 EXTENDED_ARG             1
           1612 LOAD_CONST             458 ('pqrstuvwxy')
           1614 EXTENDED_ARG             1
           1616 LOAD_CONST             459 ('klmnovwx')
           1618 EXTENDED_ARG             1
           1620 LOAD_CONST             460 ('klmnoqstuvwxy')
           1622 EXTENDED_ARG             1
           1624 LOAD_CONST             461 ('bcklmnouvw')
           1626 EXTENDED_ARG             1
           1628 LOAD_CONST             462 ('abdeklmnouvw')
           1630 EXTENDED_ARG             1
           1632 LOAD_CONST             463 ('fghijklmnopq')
           1634 EXTENDED_ARG             1
           1636 LOAD_CONST             464 ('abcdefghijk')
           1638 EXTENDED_ARG             1
           1640 LOAD_CONST             465 ('abcdefghijklno')
           1642 EXTENDED_ARG             1
           1644 LOAD_CONST             466 ('fiklmnopqrst')
           1646 EXTENDED_ARG             1
           1648 LOAD_CONST             467 ('klmnopq')
           1650 EXTENDED_ARG             1
           1652 LOAD_CONST             468 ('npqrstuvwxy')
           1654 EXTENDED_ARG             1
           1656 LOAD_CONST             469 ('klmnopqrstwx')
           1658 EXTENDED_ARG             1
           1660 LOAD_CONST             470 ('abcdefi')
           1662 EXTENDED_ARG             1
           1664 LOAD_CONST             471 ('lpqrst')
           1666 EXTENDED_ARG             1
           1668 LOAD_CONST             472 ('ghijklmnopqrst')
           1670 EXTENDED_ARG             1
           1672 LOAD_CONST             473 ('bd')
           1674 EXTENDED_ARG             1
           1676 LOAD_CONST             474 ('bcuvw')
           1678 EXTENDED_ARG             1
           1680 LOAD_CONST             475 ('hjklmnopqrst')
           1682 EXTENDED_ARG             1
           1684 LOAD_CONST             476 ('adfghijklmno')
           1686 EXTENDED_ARG             1
           1688 LOAD_CONST             477 ('klmnosuvwxy')
           1690 EXTENDED_ARG             1
           1692 LOAD_CONST             478 ('louvwxy')
           1694 EXTENDED_ARG             1
           1696 LOAD_CONST             479 ('bce')
           1698 EXTENDED_ARG             1
           1700 LOAD_CONST             480 ('gpqrst')
           1702 EXTENDED_ARG             1
           1704 LOAD_CONST             481 ('fghijklmnot')
           1706 EXTENDED_ARG             1
           1708 LOAD_CONST             482 ('wy')
           1710 EXTENDED_ARG             1
           1712 LOAD_CONST             483 ('pqrstvwxy')
           1714 EXTENDED_ARG             1
           1716 LOAD_CONST             484 ('fghijkln')
           1718 EXTENDED_ARG             1
           1720 LOAD_CONST             485 ('lmouvw')
           1722 EXTENDED_ARG             1
           1724 LOAD_CONST             486 ('gi')
           1726 EXTENDED_ARG             1
           1728 LOAD_CONST             487 ('fghijn')
           1730 EXTENDED_ARG             1
           1732 LOAD_CONST             488 ('fhklmnopqrst')
           1734 EXTENDED_ARG             1
           1736 LOAD_CONST             489 ('ghj')
           1738 EXTENDED_ARG             1
           1740 LOAD_CONST             490 ('klpqrstuvwxy')
           1742 EXTENDED_ARG             1
           1744 LOAD_CONST             491 ('abcdefgklmno')
           1746 EXTENDED_ARG             1
           1748 LOAD_CONST             492 ('fghijlmo')
           1750 EXTENDED_ARG             1
           1752 LOAD_CONST             493 ('fghijo')
           1754 EXTENDED_ARG             1
           1756 LOAD_CONST             494 ('fhpqrst')
           1758 EXTENDED_ARG             1
           1760 LOAD_CONST             495 ('klmnoprs')
           1762 EXTENDED_ARG             1
           1764 LOAD_CONST             496 ('abcefghij')
           1766 EXTENDED_ARG             1
           1768 LOAD_CONST             497 ('abcdeklno')
           1770 EXTENDED_ARG             1
           1772 LOAD_CONST             498 ('abcdefghijlmno')
           1774 EXTENDED_ARG             1
           1776 LOAD_CONST             499 ('kmnpqrst')
           1778 EXTENDED_ARG             1
           1780 LOAD_CONST             500 ('fghijklmnoq')
           1782 EXTENDED_ARG             1
           1784 LOAD_CONST             501 ('abcdefhij')
           1786 EXTENDED_ARG             1
           1788 LOAD_CONST             502 ('fghijklmnopt')
           1790 EXTENDED_ARG             1
           1792 LOAD_CONST             503 ('klmnopt')
           1794 EXTENDED_ARG             1
           1796 LOAD_CONST             504 ('abcdefklmno')
           1798 EXTENDED_ARG             1
           1800 LOAD_CONST             505 ('abcdelno')
           1802 EXTENDED_ARG             1
           1804 LOAD_CONST             506 ('pqrstw')
           1806 EXTENDED_ARG             1
           1808 LOAD_CONST             507 ('fghijlopqrst')
           1810 EXTENDED_ARG             1
           1812 LOAD_CONST             508 ('bfghij')
           1814 EXTENDED_ARG             1
           1816 LOAD_CONST             509 ('abuvw')
           1818 EXTENDED_ARG             1
           1820 LOAD_CONST             510 ('abcdefghijln')
           1822 EXTENDED_ARG             1
           1824 LOAD_CONST             511 ('ac')
           1826 EXTENDED_ARG             2
           1828 LOAD_CONST             512 ('aefghij')
           1830 EXTENDED_ARG             2
           1832 LOAD_CONST             513 ('prs')
           1834 EXTENDED_ARG             2
           1836 LOAD_CONST             514 ('lmnopqrstuvwxy')
           1838 EXTENDED_ARG             2
           1840 LOAD_CONST             515 ('abcdefghijn')
           1842 EXTENDED_ARG             2
           1844 LOAD_CONST             516 ('klmnopqrstux')
           1846 EXTENDED_ARG             2
           1848 LOAD_CONST             517 ('luvw')
           1850 EXTENDED_ARG             2
           1852 LOAD_CONST             518 ('giklmno')
           1854 EXTENDED_ARG             2
           1856 LOAD_CONST             519 ('kpqrst')
           1858 EXTENDED_ARG             2
           1860 LOAD_CONST             520 ('jpqrst')
           1862 EXTENDED_ARG             2
           1864 LOAD_CONST             521 ('fghijrt')
           1866 EXTENDED_ARG             2
           1868 LOAD_CONST             522 ('fghijlo')
           1870 EXTENDED_ARG             2
           1872 LOAD_CONST             523 ('abcdefij')
           1874 EXTENDED_ARG             2
           1876 LOAD_CONST             524 ('fghijklmnorst')
           1878 EXTENDED_ARG             2
           1880 LOAD_CONST             525 ('fghijqrst')
           1882 EXTENDED_ARG             2
           1884 LOAD_CONST             526 ('tuvwxy')
           1886 EXTENDED_ARG             2
           1888 LOAD_CONST             527 ('fghijlmopqrst')
           1890 EXTENDED_ARG             2
           1892 LOAD_CONST             528 ('klmnouwxy')
           1894 EXTENDED_ARG             2
           1896 LOAD_CONST             529 ('bdeuvw')
           1898 EXTENDED_ARG             2
           1900 LOAD_CONST             530 ('fghijprt')
           1902 EXTENDED_ARG             2
           1904 LOAD_CONST             531 ('klmnoprst')
           1906 EXTENDED_ARG             2
           1908 LOAD_CONST             532 ('pqrstuvy')
           1910 EXTENDED_ARG             2
           1912 LOAD_CONST             533 ('fghijpqrt')
           1914 EXTENDED_ARG             2
           1916 LOAD_CONST             534 ('fgj')
           1918 EXTENDED_ARG             2
           1920 LOAD_CONST             535 ('pqrstvxy')
           1922 EXTENDED_ARG             2
           1924 LOAD_CONST             536 ('abdefghij')
           1926 EXTENDED_ARG             2
           1928 LOAD_CONST             537 ('abcdegh')
           1930 EXTENDED_ARG             2
           1932 LOAD_CONST             538 ('abefghij')
           1934 EXTENDED_ARG             2
           1936 LOAD_CONST             539 ('lno')
           1938 EXTENDED_ARG             2
           1940 LOAD_CONST             540 ('klmnopuvwxy')
           1942 EXTENDED_ARG             2
           1944 LOAD_CONST             541 ('klmnouvwxy')
           1946 EXTENDED_ARG             2
           1948 LOAD_CONST             542 ('fghijrst')
           1950 EXTENDED_ARG             2
           1952 LOAD_CONST             543 ('cd')
           1954 EXTENDED_ARG             2
           1956 LOAD_CONST             544 ('euvw')
           1958 EXTENDED_ARG             2
           1960 LOAD_CONST             545 ('hijpqrst')
           1962 EXTENDED_ARG             2
           1964 LOAD_CONST             546 ('pqrst')
           1966 EXTENDED_ARG             2
           1968 LOAD_CONST             547 ('klopqrst')
           1970 EXTENDED_ARG             2
           1972 LOAD_CONST             548 ('gijpqrst')
           1974 EXTENDED_ARG             2
           1976 LOAD_CONST             549 ('klmnopqrs')
           1978 EXTENDED_ARG             2
           1980 LOAD_CONST             550 ('fghijk')
           1982 EXTENDED_ARG             2
           1984 LOAD_CONST             551 ('klopqrstuvwxy')
           1986 EXTENDED_ARG             2
           1988 LOAD_CONST             552 ('rtuvwxy')
           1990 EXTENDED_ARG             2
           1992 LOAD_CONST             553 ('klmnorstuvwxy')
           1994 EXTENDED_ARG             2
           1996 LOAD_CONST             554 ('stuvwxy')
           1998 EXTENDED_ARG             2
           2000 LOAD_CONST             555 ('abcdevw')
           2002 EXTENDED_ARG             2
           2004 LOAD_CONST             556 ('cdefghijklmno')
           2006 EXTENDED_ARG             2
           2008 LOAD_CONST             557 ('bdeklmno')
           2010 EXTENDED_ARG             2
           2012 LOAD_CONST             558 ('pqstuvwxy')
           2014 EXTENDED_ARG             2
           2016 LOAD_CONST             559 ('fghipqrst')
           2018 EXTENDED_ARG             2
           2020 LOAD_CONST             560 ('fghijpst')
           2022 EXTENDED_ARG             2
           2024 LOAD_CONST             561 ('kmn')
           2026 EXTENDED_ARG             2
           2028 LOAD_CONST             562 ('mo')
           2030 EXTENDED_ARG             2
           2032 LOAD_CONST             563 ('abcdeuw')
           2034 EXTENDED_ARG             2
           2036 LOAD_CONST             564 ('qst')
           2038 EXTENDED_ARG             2
           2040 LOAD_CONST             565 ('fghijklmnost')
           2042 EXTENDED_ARG             2
           2044 LOAD_CONST             566 ('klnopqrst')
           2046 EXTENDED_ARG             2
           2048 LOAD_CONST             567 ('abcdekm')
           2050 EXTENDED_ARG             2
           2052 LOAD_CONST             568 ('abcdefgj')
           2054 EXTENDED_ARG             2
           2056 LOAD_CONST             569 ('klmnopqrstuvy')
           2058 EXTENDED_ARG             2
           2060 LOAD_CONST             570 ('kouvw')
           2062 EXTENDED_ARG             2
           2064 LOAD_CONST             571 ('abcdelmnouvw')
           2066 EXTENDED_ARG             2
           2068 LOAD_CONST             572 ('abefghijklmno')
           2070 EXTENDED_ARG             2
           2072 LOAD_CONST             573 ('fgipqrst')
           2074 EXTENDED_ARG             2
           2076 LOAD_CONST             574 ('klm')
           2078 EXTENDED_ARG             2
           2080 LOAD_CONST             575 ('klmnopstuvwxy')
           2082 EXTENDED_ARG             2
           2084 LOAD_CONST             576 ('abcdekmno')
           2086 EXTENDED_ARG             2
           2088 LOAD_CONST             577 ('fghijmno')
           2090 EXTENDED_ARG             2
           2092 LOAD_CONST             578 ('pqrstvw')
           2094 EXTENDED_ARG             2
           2096 LOAD_CONST             579 ('kmouvw')
           2098 EXTENDED_ARG             2
           2100 LOAD_CONST             580 ('cdeklmno')
           2102 EXTENDED_ARG             2
           2104 LOAD_CONST             581 ('st')
           2106 EXTENDED_ARG             2
           2108 LOAD_CONST             582 ('fij')
           2110 EXTENDED_ARG             2
           2112 LOAD_CONST             583 ('fhiklmno')
           2114 EXTENDED_ARG             2
           2116 LOAD_CONST             584 ('abcdefghklmno')
           2118 EXTENDED_ARG             2
           2120 LOAD_CONST             585 ('lmnuvwxy')
           2122 EXTENDED_ARG             2
           2124 LOAD_CONST             586 ('klmnovwy')
           2126 EXTENDED_ARG             2
           2128 LOAD_CONST             587 ('klmnow')
           2130 EXTENDED_ARG             2
           2132 LOAD_CONST             588 ('mnuvw')
           2134 EXTENDED_ARG             2
           2136 LOAD_CONST             589 ('fghijklmnpqrst')
           2138 EXTENDED_ARG             2
           2140 LOAD_CONST             590 ('klmnoxy')
           2142 EXTENDED_ARG             2
           2144 LOAD_CONST             591 ('fghklmno')
           2146 EXTENDED_ARG             2
           2148 LOAD_CONST             592 ('b')
           2150 EXTENDED_ARG             2
           2152 LOAD_CONST             593 ('lopqrst')
           2154 EXTENDED_ARG             2
           2156 LOAD_CONST             594 ('pqrstuvw')
           2158 EXTENDED_ARG             2
           2160 LOAD_CONST             595 ('abcdekmouvw')
           2162 EXTENDED_ARG             2
           2164 LOAD_CONST             596 ('abcdeklmnouw')
           2166 EXTENDED_ARG             2
           2168 LOAD_CONST             597 ('acduvw')
           2170 EXTENDED_ARG             2
           2172 LOAD_CONST             598 ('klmnoq')
           2174 EXTENDED_ARG             2
           2176 LOAD_CONST             599 ('bde')
           2178 EXTENDED_ARG             2
           2180 LOAD_CONST             600 ('pqrstxy')
           2182 EXTENDED_ARG             2
           2184 LOAD_CONST             601 ('qrs')
           2186 EXTENDED_ARG             2
           2188 LOAD_CONST             602 ('bcdeklmnouvw')
           2190 EXTENDED_ARG             2
           2192 LOAD_CONST             603 ('abcdekmo')
           2194 EXTENDED_ARG             2
           2196 LOAD_CONST             604 ('abcdefghijkn')
           2198 EXTENDED_ARG             2
           2200 LOAD_CONST             605 ('kno')
           2202 EXTENDED_ARG             2
           2204 LOAD_CONST             606 ('abcdefghijklm')
           2206 EXTENDED_ARG             2
           2208 LOAD_CONST             607 ('abcdefgij')
           2210 EXTENDED_ARG             2
           2212 LOAD_CONST             608 ('kmopqrst')
           2214 EXTENDED_ARG             2
           2216 LOAD_CONST             609 ('kmnuvwxy')
           2218 EXTENDED_ARG             2
           2220 LOAD_CONST             610 ('pqrstuvwx')
           2222 EXTENDED_ARG             2
           2224 LOAD_CONST             611 ('fghijkmn')
           2226 EXTENDED_ARG             2
           2228 LOAD_CONST             612 ('acdefghij')
           2230 EXTENDED_ARG             2
           2232 LOAD_CONST             613 ('fghijmn')
           2234 EXTENDED_ARG             2
           2236 LOAD_CONST             614 ('qr')
           2238 EXTENDED_ARG             2
           2240 LOAD_CONST             615 ('l')
           2242 EXTENDED_ARG             2
           2244 LOAD_CONST             616 ('kmnopqrstuvwxy')
           2246 EXTENDED_ARG             2
           2248 LOAD_CONST             617 ('abcdefghijl')
           2250 EXTENDED_ARG             2
           2252 LOAD_CONST             618 ('afghij')
           2254 EXTENDED_ARG             2
           2256 LOAD_CONST             619 ('auvw')
           2258 EXTENDED_ARG             2
           2260 LOAD_CONST             620 ('abcdew')
           2262 EXTENDED_ARG             2
           2264 LOAD_CONST             621 ('klmnopqrstwy')
           2266 EXTENDED_ARG             2
           2268 LOAD_CONST             622 ('adfghij')
           2270 EXTENDED_ARG             2
           2272 LOAD_CONST             623 ('abcdeghij')
           2274 EXTENDED_ARG             2
           2276 LOAD_CONST             624 ('lmopqrstuvwxy')
           2278 EXTENDED_ARG             2
           2280 LOAD_CONST             625 ('abcdefghijklmn')
           2282 EXTENDED_ARG             2
           2284 LOAD_CONST             626 ('uvx')
           2286 EXTENDED_ARG             2
           2288 LOAD_CONST             627 ('km')
           2290 EXTENDED_ARG             2
           2292 LOAD_CONST             628 ('abcdefijklmno')
           2294 EXTENDED_ARG             2
           2296 LOAD_CONST             629 ('abcdeij')
           2298 EXTENDED_ARG             2
           2300 LOAD_CONST             630 ('pq')
           2302 EXTENDED_ARG             2
           2304 LOAD_CONST             631 ('lnpqrst')
           2306 EXTENDED_ARG             2
           2308 LOAD_CONST             632 ('bdfghij')
           2310 EXTENDED_ARG             2
           2312 LOAD_CONST             633 ('abcdefhj')
           2314 EXTENDED_ARG             2
           2316 LOAD_CONST             634 ('mopqrstuvwxy')
           2318 EXTENDED_ARG             2
           2320 LOAD_CONST             635 ('fghijklmnopqs')
           2322 EXTENDED_ARG             2
           2324 LOAD_CONST             636 ('fghijqt')
           2326 EXTENDED_ARG             2
           2328 LOAD_CONST             637 ('ade')
           2330 EXTENDED_ARG             2
           2332 LOAD_CONST             638 ('abcdejklmno')
           2334 EXTENDED_ARG             2
           2336 LOAD_CONST             639 ('fghijklmpqrst')
           2338 EXTENDED_ARG             2
           2340 LOAD_CONST             640 ('pqrstuvxy')
           2342 EXTENDED_ARG             2
           2344 LOAD_CONST             641 ('mouvw')
           2346 EXTENDED_ARG             2
           2348 LOAD_CONST             642 ('mopqrst')
           2350 EXTENDED_ARG             2
           2352 LOAD_CONST             643 ('lmnopqrst')
           2354 EXTENDED_ARG             2
           2356 LOAD_CONST             644 ('abcdefhjklmno')
           2358 EXTENDED_ARG             2
           2360 LOAD_CONST             645 ('acdklmnouvw')
           2362 EXTENDED_ARG             2
           2364 LOAD_CONST             646 ('bcklmno')
           2366 EXTENDED_ARG             2
           2368 LOAD_CONST             647 ('nopqrst')
           2370 EXTENDED_ARG             2
           2372 LOAD_CONST             648 ('qrt')
           2374 EXTENDED_ARG             2
           2376 LOAD_CONST             649 ('fghijlmnpqrst')
           2378 EXTENDED_ARG             2
           2380 LOAD_CONST             650 ('pqrstuv')
           2382 EXTENDED_ARG             2
           2384 LOAD_CONST             651 ('klmnos')
           2386 EXTENDED_ARG             2
           2388 LOAD_CONST             652 ('pqrstwxy')
           2390 EXTENDED_ARG             2
           2392 LOAD_CONST             653 ('fgjklmnopqrst')
           2394 EXTENDED_ARG             2
           2396 LOAD_CONST             654 ('pqrstuw')
           2398 EXTENDED_ARG             2
           2400 LOAD_CONST             655 ('klmnopqrstuvxy')
           2402 EXTENDED_ARG             2
           2404 LOAD_CONST             656 ('fhijklmno')
           2406 EXTENDED_ARG             2
           2408 LOAD_CONST             657 ('abcdekmnuvw')
           2410 EXTENDED_ARG             2
           2412 LOAD_CONST             658 ('ghjklmno')
           2414 EXTENDED_ARG             2
           2416 LOAD_CONST             659 ('klmnoprtuvwxy')
           2418 EXTENDED_ARG             2
           2420 LOAD_CONST             660 ('abcdefghijlmn')
           2422 EXTENDED_ARG             2
           2424 LOAD_CONST             661 ('klmouvwxy')
           2426 EXTENDED_ARG             2
           2428 LOAD_CONST             662 ('abcdegjklmno')
           2430 EXTENDED_ARG             2
           2432 LOAD_CONST             663 ('p')
           2434 EXTENDED_ARG             2
           2436 LOAD_CONST             664 ('hiklmnopqrst')
           2438 EXTENDED_ARG             2
           2440 LOAD_CONST             665 ('rstuvwxy')
           2442 EXTENDED_ARG             2
           2444 LOAD_CONST             666 ('gh')
           2446 EXTENDED_ARG             2
           2448 LOAD_CONST             667 ('cdfghijklmno')
           2450 EXTENDED_ARG             2
           2452 LOAD_CONST             668 ('klmnou')
           2454 EXTENDED_ARG             2
           2456 LOAD_CONST             669 ('iklmno')
           2458 EXTENDED_ARG             2
           2460 LOAD_CONST             670 ('klmnopqrstvxy')
           2462 EXTENDED_ARG             2
           2464 LOAD_CONST             671 ('lmpqrstuvwxy')
           2466 EXTENDED_ARG             2
           2468 LOAD_CONST             672 ('prtuvwxy')
           2470 EXTENDED_ARG             2
           2472 LOAD_CONST             673 ('klmnovwxy')
           2474 EXTENDED_ARG             2
           2476 LOAD_CONST             674 ('pqst')
           2478 EXTENDED_ARG             2
           2480 LOAD_CONST             675 ('klmnortuvwxy')
           2482 EXTENDED_ARG             2
           2484 LOAD_CONST             676 ('lmnpqrstuvwxy')
           2486 EXTENDED_ARG             2
           2488 LOAD_CONST             677 ('fghijmpqrst')
           2490 EXTENDED_ARG             2
           2492 LOAD_CONST             678 ('ghiklmnopqrst')
           2494 EXTENDED_ARG             2
           2496 LOAD_CONST             679 ('klmpqrst')
           2498 EXTENDED_ARG             2
           2500 LOAD_CONST             680 ('klmnoprstuvwxy')
           2502 EXTENDED_ARG             2
           2504 LOAD_CONST             681 ('ghklmno')
           2506 EXTENDED_ARG             2
           2508 LOAD_CONST             682 ('fghijopqrst')
           2510 EXTENDED_ARG             2
           2512 LOAD_CONST             683 ('klmnoqruvwxy')
           2514 EXTENDED_ARG             2
           2516 LOAD_CONST             684 ('abcdeklmouvw')
           2518 EXTENDED_ARG             2
           2520 LOAD_CONST             685 ('ae')
           2522 EXTENDED_ARG             2
           2524 LOAD_CONST             686 ('abcfghijklmno')
           2526 EXTENDED_ARG             2
           2528 LOAD_CONST             687 ('vw')
           2530 EXTENDED_ARG             2
           2532 LOAD_CONST             688 ('fghijr')
           2534 EXTENDED_ARG             2
           2536 LOAD_CONST             689 ('kmnpqrstuvwxy')
           2538 EXTENDED_ARG             2
           2540 LOAD_CONST             690 ('fghijklpqrst')
           2542 EXTENDED_ARG             2
           2544 LOAD_CONST             691 ('vwxy')
           2546 EXTENDED_ARG             2
           2548 LOAD_CONST             692 ('uxy')
           2550 EXTENDED_ARG             2
           2552 LOAD_CONST             693 ('cklmnouvw')
           2554 EXTENDED_ARG             2
           2556 LOAD_CONST             694 ('abcdefghijkm')
           2558 EXTENDED_ARG             2
           2560 LOAD_CONST             695 ('uvw')
           2562 EXTENDED_ARG             2
           2564 LOAD_CONST             696 ('bcd')
           2566 EXTENDED_ARG             2
           2568 LOAD_CONST             697 ('bcefghij')
           2570 EXTENDED_ARG             2
           2572 LOAD_CONST             698 ('abcdeiklmno')
           2574 EXTENDED_ARG             2
           2576 LOAD_CONST             699 ('klmnot')
           2578 EXTENDED_ARG             2
           2580 LOAD_CONST             700 ('cduvw')
           2582 EXTENDED_ARG             2
           2584 LOAD_CONST             701 ('fghijmo')
           2586 EXTENDED_ARG             2
           2588 LOAD_CONST             702 ('eklmnouvw')
           2590 EXTENDED_ARG             2
           2592 LOAD_CONST             703 ('klmnopqrstuwy')
           2594 EXTENDED_ARG             2
           2596 LOAD_CONST             704 ('kmnuvw')
           2598 EXTENDED_ARG             2
           2600 LOAD_CONST             705 ('lmouvwxy')
           2602 EXTENDED_ARG             2
           2604 LOAD_CONST             706 ('abcdefghijlmo')
           2606 EXTENDED_ARG             2
           2608 LOAD_CONST             707 ('cefghij')
           2610 EXTENDED_ARG             2
           2612 LOAD_CONST             708 ('klmnoqs')
           2614 EXTENDED_ARG             2
           2616 LOAD_CONST             709 ('klmnouwx')
           2618 EXTENDED_ARG             2
           2620 LOAD_CONST             710 ('kmuvwxy')
           2622 EXTENDED_ARG             2
           2624 LOAD_CONST             711 ('ceklmnouvw')
           2626 EXTENDED_ARG             2
           2628 LOAD_CONST             712 ('fghijklmnoqrs')
           2630 EXTENDED_ARG             2
           2632 LOAD_CONST             713 ('abduvw')
           2634 EXTENDED_ARG             2
           2636 LOAD_CONST             714 ('abceklmno')
           2638 EXTENDED_ARG             2
           2640 LOAD_CONST             715 ('ghijklmno')
           2642 EXTENDED_ARG             2
           2644 LOAD_CONST             716 ('abcdefghijmn')
           2646 EXTENDED_ARG             2
           2648 LOAD_CONST             717 ('bcdfghij')
           2650 EXTENDED_ARG             2
           2652 LOAD_CONST             718 ('pqrstvwx')
           2654 EXTENDED_ARG             2
           2656 LOAD_CONST             719 ('fghijlpqrst')
           2658 EXTENDED_ARG             2
           2660 LOAD_CONST             720 ('gijklmnopqrst')
           2662 EXTENDED_ARG             2
           2664 LOAD_CONST             721 ('abcdelnuvw')
           2666 EXTENDED_ARG             2
           2668 LOAD_CONST             722 ('pqrstvwy')
           2670 EXTENDED_ARG             2
           2672 LOAD_CONST             723 ('pr')
           2674 EXTENDED_ARG             2
           2676 LOAD_CONST             724 ('fghijklmnos')
           2678 EXTENDED_ARG             2
           2680 LOAD_CONST             725 ('c')
           2682 EXTENDED_ARG             2
           2684 LOAD_CONST             726 ('fghijklmno')
           2686 EXTENDED_ARG             2
           2688 LOAD_CONST             727 ('abcdefghijkmno')
           2690 EXTENDED_ARG             2
           2692 LOAD_CONST             728 ('abcuvw')
           2694 EXTENDED_ARG             2
           2696 LOAD_CONST             729 ('abcdev')
           2698 EXTENDED_ARG             2
           2700 LOAD_CONST             730 ('abeuvw')
           2702 EXTENDED_ARG             2
           2704 LOAD_CONST             731 ('pqrstuvx')
           2706 EXTENDED_ARG             2
           2708 LOAD_CONST             732 ('klo')
           2710 EXTENDED_ARG             2
           2712 LOAD_CONST             733 ('fghijln')
           2714 EXTENDED_ARG             2
           2716 LOAD_CONST             734 ('klmnpqrstuvwxy')
           2718 EXTENDED_ARG             2
           2720 LOAD_CONST             735 ('abcdefghijlno')
           2722 EXTENDED_ARG             2
           2724 LOAD_CONST             736 ('fghijklmnopst')
           2726 EXTENDED_ARG             2
           2728 LOAD_CONST             737 ('acd')
           2730 EXTENDED_ARG             2
           2732 LOAD_CONST             738 ('gipqrst')
           2734 EXTENDED_ARG             2
           2736 LOAD_CONST             739 ('w')
           2738 EXTENDED_ARG             2
           2740 LOAD_CONST             740 ('abcdenuvw')
           2742 EXTENDED_ARG             2
           2744 LOAD_CONST             741 ('deuvw')
           2746 EXTENDED_ARG             2
           2748 LOAD_CONST             742 ('abcdeklmnouvw')
           2750 EXTENDED_ARG             2
           2752 LOAD_CONST             743 ('fg')
           2754 EXTENDED_ARG             2
           2756 LOAD_CONST             744 ('cdeuvw')
           2758 EXTENDED_ARG             2
           2760 LOAD_CONST             745 ('lmnuvw')
           2762 EXTENDED_ARG             2
           2764 LOAD_CONST             746 ('abcdenouvw')
           2766 EXTENDED_ARG             2
           2768 LOAD_CONST             747 ('klmnoqt')
           2770 EXTENDED_ARG             2
           2772 LOAD_CONST             748 ('hklmnopqrst')
           2774 EXTENDED_ARG             2
           2776 LOAD_CONST             749 ('klmnouvwy')
           2778 EXTENDED_ARG             2
           2780 LOAD_CONST             750 ('gijklmno')
           2782 EXTENDED_ARG             2
           2784 LOAD_CONST             751 ('klmnopqrst')
           2786 EXTENDED_ARG             2
           2788 LOAD_CONST             752 ('fghijmopqrst')
           2790 EXTENDED_ARG             2
           2792 LOAD_CONST             753 ('kmno')
           2794 EXTENDED_ARG             2
           2796 LOAD_CONST             754 ('f')
           2798 EXTENDED_ARG             2
           2800 LOAD_CONST             755 ('uv')
           2802 EXTENDED_ARG             2
           2804 LOAD_CONST             756 ('fhij')
           2806 EXTENDED_ARG             2
           2808 LOAD_CONST             757 ('knuvw')
           2810 EXTENDED_ARG             2
           2812 LOAD_CONST             758 ('klmnor')
           2814 EXTENDED_ARG             2
           2816 LOAD_CONST             759 ('klnouvwxy')
           2818 EXTENDED_ARG             2
           2820 LOAD_CONST             760 ('bcdeuvw')
           2822 EXTENDED_ARG             2
           2824 LOAD_CONST             761 ('bdklmno')
           2826 EXTENDED_ARG             2
           2828 LOAD_CONST             762 ('abklmnouvw')
           2830 EXTENDED_ARG             2
           2832 LOAD_CONST             763 ('abcdehjklmno')
           2834 EXTENDED_ARG             2
           2836 LOAD_CONST             764 ('bcde')
           2838 EXTENDED_ARG             2
           2840 LOAD_CONST             765 ('fghijklmo')
           2842 EXTENDED_ARG             2
           2844 LOAD_CONST             766 ('abcdefghijklmo')
           2846 EXTENDED_ARG             2
           2848 LOAD_CONST             767 ('ko')
           2850 EXTENDED_ARG             3
           2852 LOAD_CONST             768 ('abcdeklmuvw')
           2854 EXTENDED_ARG             3
           2856 LOAD_CONST             769 ('bcdefghijklmno')
           2858 EXTENDED_ARG             3
           2860 LOAD_CONST             770 ('beuvw')
           2862 EXTENDED_ARG             3
           2864 LOAD_CONST             771 ('qstuvwxy')
           2866 EXTENDED_ARG             3
           2868 LOAD_CONST             772 ('aeklmnouvw')
           2870 EXTENDED_ARG             3
           2872 LOAD_CONST             773 ('h')
           2874 EXTENDED_ARG             3
           2876 LOAD_CONST             774 ('t')
           2878 EXTENDED_ARG             3
           2880 LOAD_CONST             775 ('kmuvw')
           2882 EXTENDED_ARG             3
           2884 LOAD_CONST             776 ('fhi')
           2886 EXTENDED_ARG             3
           2888 LOAD_CONST             777 ('fjklmnopqrst')
           2890 EXTENDED_ARG             3
           2892 LOAD_CONST             778 ('hiklmno')
           2894 EXTENDED_ARG             3
           2896 LOAD_CONST             779 ('fhipqrst')
           2898 EXTENDED_ARG             3
           2900 LOAD_CONST             780 ('qrtuvwxy')
           2902 EXTENDED_ARG             3
           2904 LOAD_CONST             781 ('abcdeklnuvw')
           2906 EXTENDED_ARG             3
           2908 LOAD_CONST             782 ('fghijqrt')
           2910 EXTENDED_ARG             3
           2912 LOAD_CONST             783 ('pqrstx')
           2914 EXTENDED_ARG             3
           2916 LOAD_CONST             784 ('bdefghijklmno')
           2918 EXTENDED_ARG             3
           2920 LOAD_CONST             785 ('gj')
           2922 EXTENDED_ARG             3
           2924 LOAD_CONST             786 ('abcdelmno')
           2926 EXTENDED_ARG             3
           2928 LOAD_CONST             787 ('abcdefjklmno')
           2930 EXTENDED_ARG             3
           2932 LOAD_CONST             788 ('fhjpqrst')
           2934 EXTENDED_ARG             3
           2936 LOAD_CONST             789 ('klnpqrst')
           2938 EXTENDED_ARG             3
           2940 LOAD_CONST             790 ('fgijklmnopqrst')
           2942 EXTENDED_ARG             3
           2944 LOAD_CONST             791 ('abcdelm')
           2946 EXTENDED_ARG             3
           2948 LOAD_CONST             792 ('fghijrs')
           2950 EXTENDED_ARG             3
           2952 LOAD_CONST             793 ('klmnouw')
           2954 EXTENDED_ARG             3
           2956 LOAD_CONST             794 ('fhklmno')
           2958 EXTENDED_ARG             3
           2960 LOAD_CONST             795 ('abcdeln')
           2962 EXTENDED_ARG             3
           2964 LOAD_CONST             796 ('fgijpqrst')
           2966 EXTENDED_ARG             3
           2968 LOAD_CONST             797 ('fghijklmnoqst')
           2970 EXTENDED_ARG             3
           2972 LOAD_CONST             798 ('abeklmnouvw')
           2974 EXTENDED_ARG             3
           2976 LOAD_CONST             799 ('klmuvw')
           2978 EXTENDED_ARG             3
           2980 LOAD_CONST             800 ('i')
           2982 EXTENDED_ARG             3
           2984 LOAD_CONST             801 ('lmno')
           2986 EXTENDED_ARG             3
           2988 LOAD_CONST             802 ('fghijklo')
           2990 EXTENDED_ARG             3
           2992 LOAD_CONST             803 ('fghijkm')
           2994 EXTENDED_ARG             3
           2996 LOAD_CONST             804 ('g')
           2998 EXTENDED_ARG             3
           3000 LOAD_CONST             805 ('adklmnouvw')
           3002 EXTENDED_ARG             3
           3004 LOAD_CONST             806 ('be')
           3006 EXTENDED_ARG             3
           3008 LOAD_CONST             807 ('abcdefgjklmno')
           3010 EXTENDED_ARG             3
           3012 LOAD_CONST             808 ('prst')
           3014 EXTENDED_ARG             3
           3016 LOAD_CONST             809 ('puvwxy')
           3018 EXTENDED_ARG             3
           3020 LOAD_CONST             810 ('qrstuvwxy')
           3022 EXTENDED_ARG             3
           3024 LOAD_CONST             811 ('klmnov')
           3026 EXTENDED_ARG             3
           3028 LOAD_CONST             812 ('klmnopqrstuvwx')
           3030 EXTENDED_ARG             3
           3032 LOAD_CONST             813 ('acefghijklmno')
           3034 EXTENDED_ARG             3
           3036 LOAD_CONST             814 ('fghijpqrs')
           3038 EXTENDED_ARG             3
           3040 LOAD_CONST             815 ('fhj')
           3042 EXTENDED_ARG             3
           3044 LOAD_CONST             816 ('abklmno')
           3046 EXTENDED_ARG             3
           3048 LOAD_CONST             817 ('abcd')
           3050 EXTENDED_ARG             3
           3052 LOAD_CONST             818 ('fiklmno')
           3054 EXTENDED_ARG             3
           3056 LOAD_CONST             819 ('ijpqrst')
           3058 EXTENDED_ARG             3
           3060 LOAD_CONST             820 ('fghijnpqrst')
           3062 EXTENDED_ARG             3
           3064 LOAD_CONST             821 ('lmnouvw')
           3066 EXTENDED_ARG             3
           3068 LOAD_CONST             822 ('suvwxy')
           3070 EXTENDED_ARG             3
           3072 LOAD_CONST             823 ('knouvw')
           3074 EXTENDED_ARG             3
           3076 LOAD_CONST             824 ('duvw')
           3078 EXTENDED_ARG             3
           3080 LOAD_CONST             825 ('fghijkmno')
           3082 EXTENDED_ARG             3
           3084 LOAD_CONST             826 ('bdefghij')
           3086 EXTENDED_ARG             3
           3088 LOAD_CONST             827 ('aceklmno')
           3090 EXTENDED_ARG             3
           3092 LOAD_CONST             828 ('fgklmno')
           3094 EXTENDED_ARG             3
           3096 LOAD_CONST             829 ('fghijst')
           3098 EXTENDED_ARG             3
           3100 LOAD_CONST             830 ('adefghij')
           3102 EXTENDED_ARG             3
           3104 LOAD_CONST             831 ('fghijklmnopqrs')
           3106 EXTENDED_ARG             3
           3108 LOAD_CONST             832 ('bcdefghij')
           3110 EXTENDED_ARG             3
           3112 LOAD_CONST             833 ('abcdefghijko')
           3114 EXTENDED_ARG             3
           3116 LOAD_CONST             834 ('klmnotuvwxy')
           3118 EXTENDED_ARG             3
           3120 LOAD_CONST             835 ('klmnopruvwxy')
           3122 EXTENDED_ARG             3
           3124 LOAD_CONST             836 ('klmnovxy')
           3126 EXTENDED_ARG             3
           3128 LOAD_CONST             837 ('qtuvwxy')
           3130 EXTENDED_ARG             3
           3132 LOAD_CONST             838 ('fhjklmnopqrst')
           3134 EXTENDED_ARG             3
           3136 LOAD_CONST             839 ('klmnoqrst')
           3138 EXTENDED_ARG             3
           3140 LOAD_CONST             840 ('prt')
           3142 EXTENDED_ARG             3
           3144 LOAD_CONST             841 ('fghijt')
           3146 EXTENDED_ARG             3
           3148 LOAD_CONST             842 ('uvwx')
           3150 EXTENDED_ARG             3
           3152 LOAD_CONST             843 ('abcdekmnouvw')
           3154 EXTENDED_ARG             3
           3156 LOAD_CONST             844 ('dfghij')
           3158 EXTENDED_ARG             3
           3160 LOAD_CONST             845 ('abcdehiklmno')
           3162 EXTENDED_ARG             3
           3164 LOAD_CONST             846 ('klmnopqrstu')
           3166 EXTENDED_ARG             3
           3168 LOAD_CONST             847 ('adeklmnouvw')
           3170 EXTENDED_ARG             3
           3172 LOAD_CONST             848 ('abcdefghijmno')
           3174 EXTENDED_ARG             3
           3176 LOAD_CONST             849 ('klmnopquvwxy')
           3178 EXTENDED_ARG             3
           3180 LOAD_CONST             850 ('abcdefghijkln')
           3182 EXTENDED_ARG             3
           3184 LOAD_CONST             851 ('mnpqrst')
           3186 EXTENDED_ARG             3
           3188 LOAD_CONST             852 ('fghijlmn')
           3190 EXTENDED_ARG             3
           3192 LOAD_CONST             853 ('lnopqrstuvwxy')
           3194 EXTENDED_ARG             3
           3196 LOAD_CONST             854 ('pqrt')
           3198 EXTENDED_ARG             3
           3200 LOAD_CONST             855 ('fghijpt')
           3202 EXTENDED_ARG             3
           3204 LOAD_CONST             856 ('abcde')
           3206 EXTENDED_ARG             3
           3208 LOAD_CONST             857 ('ij')
           3210 EXTENDED_ARG             3
           3212 LOAD_CONST             858 ('bcdklmnouvw')
           3214 EXTENDED_ARG             3
           3216 LOAD_CONST             859 ('fghijkn')
           3218 EXTENDED_ARG             3
           3220 LOAD_CONST             860 ('pst')
           3222 EXTENDED_ARG             3
           3224 LOAD_CONST             861 ('bdklmnouvw')
           3226 EXTENDED_ARG             3
           3228 LOAD_CONST             862 ('abcdeko')
           3230 EXTENDED_ARG             3
           3232 LOAD_CONST             863 ('fh')
           3234 EXTENDED_ARG             3
           3236 LOAD_CONST             864 ('fjpqrst')
           3238 EXTENDED_ARG             3
           3240 LOAD_CONST             865 ('fghijqr')
           3242 EXTENDED_ARG             3
           3244 LOAD_CONST             866 ('beklmno')
           3246 EXTENDED_ARG             3
           3248 LOAD_CONST             867 ('fghijklopqrst')
           3250 EXTENDED_ARG             3
           3252 LOAD_CONST             868 ('lmuvw')
           3254 EXTENDED_ARG             3
           3256 LOAD_CONST             869 ('klouvw')
           3258 EXTENDED_ARG             3
           3260 LOAD_CONST             870 ('fghijpqr')
           3262 EXTENDED_ARG             3
           3264 LOAD_CONST             871 ('abcdegi')
           3266 EXTENDED_ARG             3
           3268 LOAD_CONST             872 ('psuvwxy')
           3270 EXTENDED_ARG             3
           3272 LOAD_CONST             873 ('klnopqrstuvwxy')
           3274 EXTENDED_ARG             3
           3276 LOAD_CONST             874 ('abcdelmn')
           3278 EXTENDED_ARG             3
           3280 LOAD_CONST             875 ('fhiklmnopqrst')
           3282 EXTENDED_ARG             3
           3284 LOAD_CONST             876 ('fghijprst')
           3286 EXTENDED_ARG             3
           3288 LOAD_CONST             877 ('lnpqrstuvwxy')
           3290 EXTENDED_ARG             3
           3292 LOAD_CONST             878 ('qruvwxy')
           3294 EXTENDED_ARG             3
           3296 LOAD_CONST             879 ('aduvw')
           3298 EXTENDED_ARG             3
           3300 LOAD_CONST             880 ('abcdekmuvw')
           3302 EXTENDED_ARG             3
           3304 LOAD_CONST             881 ('adklmno')
           3306 EXTENDED_ARG             3
           3308 LOAD_CONST             882 ('abcdeu')
           3310 EXTENDED_ARG             3
           3312 LOAD_CONST             883 ('cefghijklmno')
           3314 EXTENDED_ARG             3
           3316 LOAD_CONST             884 ('lm')
           3318 EXTENDED_ARG             3
           3320 LOAD_CONST             885 ('hjklmno')
           3322 EXTENDED_ARG             3
           3324 LOAD_CONST             886 ('abcdefghijklo')
           3326 EXTENDED_ARG             3
           3328 LOAD_CONST             887 ('klmnoqrs')
           3330 EXTENDED_ARG             3
           3332 LOAD_CONST             888 ('fghijko')
           3334 EXTENDED_ARG             3
           3336 LOAD_CONST             889 ('ouvw')
           3338 EXTENDED_ARG             3
           3340 LOAD_CONST             890 ('pqrstu')
           3342 EXTENDED_ARG             3
           3344 LOAD_CONST             891 ('mnopqrst')
           3346 EXTENDED_ARG             3
           3348 LOAD_CONST             892 ('louvw')
           3350 EXTENDED_ARG             3
           3352 LOAD_CONST             893 ('prsuvwxy')
           3354 EXTENDED_ARG             3
           3356 LOAD_CONST             894 ('abcdekno')
           3358 EXTENDED_ARG             3
           3360 LOAD_CONST             895 ('klmnopqruvwxy')
           3362 EXTENDED_ARG             3
           3364 LOAD_CONST             896 ('kpqrstuvwxy')
           3366 EXTENDED_ARG             3
           3368 LOAD_CONST             897 ('abcdefgijklmno')
           3370 EXTENDED_ARG             3
           3372 LOAD_CONST             898 ('klmnors')
           3374 EXTENDED_ARG             3
           3376 LOAD_CONST             899 ('abcdefghijo')
           3378 EXTENDED_ARG             3
           3380 LOAD_CONST             900 ('npqrst')
           3382 EXTENDED_ARG             3
           3384 LOAD_CONST             901 ('knopqrstuvwxy')
           3386 EXTENDED_ARG             3
           3388 LOAD_CONST             902 ('vx')
           3390 EXTENDED_ARG             3
           3392 LOAD_CONST             903 ('fghijqrs')
           3394 EXTENDED_ARG             3
           3396 LOAD_CONST             904 ('klmnopqrstuxy')
           3398 EXTENDED_ARG             3
           3400 LOAD_CONST             905 ('u')
           3402 EXTENDED_ARG             3
           3404 LOAD_CONST             906 ('aceuvw')
           3406 EXTENDED_ARG             3
           3408 LOAD_CONST             907 ('klmnopqrtuvwxy')
           3410 EXTENDED_ARG             3
           3412 LOAD_CONST             908 ('uvwxy')
           3414 EXTENDED_ARG             3
           3416 LOAD_CONST             909 ('fipqrst')
           3418 EXTENDED_ARG             3
           3420 LOAD_CONST             910 ('klmnowxy')
           3422 EXTENDED_ARG             3
           3424 LOAD_CONST             911 ('befghij')
           3426 EXTENDED_ARG             3
           3428 LOAD_CONST             912 ('gklmnopqrst')
           3430 EXTENDED_ARG             3
           3432 LOAD_CONST             913 ('abe')
           3434 EXTENDED_ARG             3
           3436 LOAD_CONST             914 ('mnopqrstuvwxy')
           3438 EXTENDED_ARG             3
           3440 LOAD_CONST             915 ('fghijklmnoprs')
           3442 EXTENDED_ARG             3
           3444 LOAD_CONST             916 ('abcdeo')
           3446 EXTENDED_ARG             3
           3448 LOAD_CONST             917 ('eklmno')
           3450 EXTENDED_ARG             3
           3452 LOAD_CONST             918 ('fgi')
           3454 EXTENDED_ARG             3
           3456 LOAD_CONST             919 ('fghijlmpqrst')
           3458 EXTENDED_ARG             3
           3460 LOAD_CONST             920 ('qt')
           3462 EXTENDED_ARG             3
           3464 LOAD_CONST             921 ('abcdefghi')
           3466 EXTENDED_ARG             3
           3468 LOAD_CONST             922 ('bcduvw')
           3470 EXTENDED_ARG             3
           3472 LOAD_CONST             923 ('bduvw')
           3474 EXTENDED_ARG             3
           3476 LOAD_CONST             924 ('klouvwxy')
           3478 EXTENDED_ARG             3
           3480 LOAD_CONST             925 ('kouvwxy')
           3482 EXTENDED_ARG             3
           3484 LOAD_CONST             926 ('fghiklmno')
           3486 EXTENDED_ARG             3
           3488 LOAD_CONST             927 ('abcdemno')
           3490 EXTENDED_ARG             3
           3492 LOAD_CONST             928 ('pqsuvwxy')
           3494 LOAD_CONST              19 ('ab')
           3496 EXTENDED_ARG             3
           3498 LOAD_CONST             929 ('klmnopqrstvwxy')
           3500 EXTENDED_ARG             3
           3502 LOAD_CONST             930 ('pqrstv')
           3504 EXTENDED_ARG             3
           3506 LOAD_CONST             931 ('abfghijklmno')
           3508 EXTENDED_ARG             3
           3510 LOAD_CONST             932 ('beklmnouvw')
           3512 EXTENDED_ARG             3
           3514 LOAD_CONST             933 ('fghijklm')
           3516 EXTENDED_ARG             3
           3518 LOAD_CONST             934 ('pqrsuvwxy')
           3520 EXTENDED_ARG             3
           3522 LOAD_CONST             935 ('acdeklmnouvw')
           3524 EXTENDED_ARG             3
           3526 LOAD_CONST             936 ('vwy')
           3528 EXTENDED_ARG             3
           3530 LOAD_CONST             937 ('ghjpqrst')
           3532 EXTENDED_ARG             3
           3534 LOAD_CONST             938 ('fghijl')
           3536 EXTENDED_ARG             3
           3538 LOAD_CONST             939 ('klmnopqrstvy')
           3540 EXTENDED_ARG             3
           3542 LOAD_CONST             940 ('abcdelouvw')
           3544 EXTENDED_ARG             3
           3546 LOAD_CONST             941 ('fhijklmnopqrst')
           3548 EXTENDED_ARG             3
           3550 LOAD_CONST             942 ('klmpqrstuvwxy')
           3552 EXTENDED_ARG             3
           3554 LOAD_CONST             943 ('abcdef')
           3556 EXTENDED_ARG             3
           3558 LOAD_CONST             944 ('bcfghij')
           3560 EXTENDED_ARG             3
           3562 LOAD_CONST             945 ('fghijkno')
           3564 EXTENDED_ARG             3
           3566 LOAD_CONST             946 ('kopqrst')
           3568 EXTENDED_ARG             3
           3570 LOAD_CONST             947 ('rsuvwxy')
           3572 EXTENDED_ARG             3
           3574 LOAD_CONST             948 ('abcdekmn')
           3576 EXTENDED_ARG             3
           3578 LOAD_CONST             949 ('aklmno')
           3580 EXTENDED_ARG             3
           3582 LOAD_CONST             950 ('dfghijklmno')
           3584 EXTENDED_ARG             3
           3586 LOAD_CONST             951 ('abcdeklouvw')
           3588 EXTENDED_ARG             3
           3590 LOAD_CONST             952 ('klmnpqrst')
           3592 EXTENDED_ARG             3
           3594 LOAD_CONST             953 ('abcdeklmnouv')
           3596 EXTENDED_ARG             3
           3598 LOAD_CONST             954 ('knpqrst')
           3600 EXTENDED_ARG             3
           3602 LOAD_CONST             955 ('aceklmnouvw')
           3604 EXTENDED_ARG             3
           3606 LOAD_CONST             956 ('kl')
           3608 EXTENDED_ARG             3
           3610 LOAD_CONST             957 ('fghijprs')
           3612 EXTENDED_ARG             3
           3614 LOAD_CONST             958 ('rt')
           3616 EXTENDED_ARG             3
           3618 LOAD_CONST             959 ('klmnopqrsuvwxy')
           3620 EXTENDED_ARG             3
           3622 LOAD_CONST             960 ('bfghijklmno')
           3624 EXTENDED_ARG             3
           3626 LOAD_CONST             961 ('klmnouv')
           3628 EXTENDED_ARG             3
           3630 LOAD_CONST             962 ('abcdefh')
           3632 EXTENDED_ARG             3
           3634 LOAD_CONST             963 ('s')
           3636 EXTENDED_ARG             3
           3638 LOAD_CONST             964 ('klmnouvwx')
           3640 EXTENDED_ARG             3
           3642 LOAD_CONST             965 ('fghijp')
           3644 EXTENDED_ARG             3
           3646 LOAD_CONST             966 ('uwxy')
           3648 EXTENDED_ARG             3
           3650 LOAD_CONST             967 ('fghijq')
           3652 EXTENDED_ARG             3
           3654 LOAD_CONST             968 ('klmnoqr')
           3656 EXTENDED_ARG             3
           3658 LOAD_CONST             969 ('vxy')
           3660 EXTENDED_ARG             3
           3662 LOAD_CONST             970 ('fgpqrst')
           3664 EXTENDED_ARG             3
           3666 LOAD_CONST             971 ('fghijlmno')
           3668 EXTENDED_ARG             3
           3670 LOAD_CONST             972 ('defghij')
           3672 EXTENDED_ARG             3
           3674 LOAD_CONST             973 ('pqtuvwxy')
           3676 EXTENDED_ARG             3
           3678 LOAD_CONST             974 ('dklmno')
           3680 EXTENDED_ARG             3
           3682 LOAD_CONST             975 ('klno')
           3684 EXTENDED_ARG             3
           3686 LOAD_CONST             976 ('klmnowy')
           3688 EXTENDED_ARG             3
           3690 LOAD_CONST             977 ('abcdemn')
           3692 EXTENDED_ARG             3
           3694 LOAD_CONST             978 ('abcdeklnouvw')
           3696 EXTENDED_ARG             3
           3698 LOAD_CONST             979 ('ptuvwxy')
           3700 EXTENDED_ARG             3
           3702 LOAD_CONST             980 ('abcdehijklmno')
           3704 EXTENDED_ARG             3
           3706 LOAD_CONST             981 ('acuvw')
           3708 EXTENDED_ARG             3
           3710 LOAD_CONST             982 ('bcdfghijklmno')
           3712 EXTENDED_ARG             3
           3714 LOAD_CONST             983 ('abcdemouvw')
           3716 EXTENDED_ARG             3
           3718 LOAD_CONST             984 ('abcdefgi')
           3720 EXTENDED_ARG             3
           3722 LOAD_CONST             985 ('opqrstuvwxy')
           3724 EXTENDED_ARG             3
           3726 LOAD_CONST             986 ('v')
           3728 EXTENDED_ARG             3
           3730 LOAD_CONST             987 ('lmpqrst')
           3732 EXTENDED_ARG             3
           3734 LOAD_CONST             988 ('abcdeuvw')
           3736 EXTENDED_ARG             3
           3738 LOAD_CONST             989 ('abcdekouvw')
           3740 EXTENDED_ARG             3
           3742 LOAD_CONST             990 ('qrst')
           3744 EXTENDED_ARG             3
           3746 LOAD_CONST             991 ('klmopqrstuvwxy')
           3748 EXTENDED_ARG             3
           3750 LOAD_CONST             992 ('prstuvwxy')
           3752 EXTENDED_ARG             3
           3754 LOAD_CONST             993 ('lmnpqrst')
           3756 EXTENDED_ARG             3
           3758 LOAD_CONST             994 ('pqrstvy')
           3760 EXTENDED_ARG             3
           3762 LOAD_CONST             995 ('abcdfghij')
           3764 EXTENDED_ARG             3
           3766 LOAD_CONST             996 ('klmnop')
           3768 EXTENDED_ARG             3
           3770 LOAD_CONST             997 ('ijklmnopqrst')
           3772 EXTENDED_ARG             3
           3774 LOAD_CONST             998 ('klnpqrstuvwxy')
           3776 EXTENDED_ARG             3
           3778 LOAD_CONST             999 ('klmnopqr')
           3780 EXTENDED_ARG             3
           3782 LOAD_CONST            1000 ('xy')
           3784 EXTENDED_ARG             3
           3786 LOAD_CONST            1001 ('abcdeklo')
           3788 EXTENDED_ARG             3
           3790 LOAD_CONST            1002 ('abd')
           3792 EXTENDED_ARG             3
           3794 LOAD_CONST            1003 ('klmnouvy')
           3796 EXTENDED_ARG             3
           3798 LOAD_CONST            1004 ('klmuvwxy')
           3800 EXTENDED_ARG             3
           3802 LOAD_CONST            1005 ('abcefghijklmno')
           3804 EXTENDED_ARG             3
           3806 LOAD_CONST            1006 ('fghijkopqrst')
           3808 EXTENDED_ARG             3
           3810 LOAD_CONST            1007 ('fghijklmnoprst')
           3812 EXTENDED_ARG             3
           3814 LOAD_CONST            1008 ('ruvwxy')
           3816 EXTENDED_ARG             3
           3818 LOAD_CONST            1009 ('m')
           3820 EXTENDED_ARG             3
           3822 LOAD_CONST            1010 ('e')
           3824 EXTENDED_ARG             3
           3826 LOAD_CONST            1011 ('abcdej')
           3828 EXTENDED_ARG             3
           3830 LOAD_CONST            1012 ('hpqrst')
           3832 EXTENDED_ARG             3
           3834 LOAD_CONST            1013 ('bceuvw')
           3836 EXTENDED_ARG             3
           3838 LOAD_CONST            1014 ('fghijmnpqrst')
           3840 EXTENDED_ARG             3
           3842 LOAD_CONST            1015 ('pqrstwy')
           3844 EXTENDED_ARG             3
           3846 LOAD_CONST            1016 ('klmnopqrstx')
           3848 EXTENDED_ARG             3
           3850 LOAD_CONST            1017 ('qsuvwxy')
           3852 EXTENDED_ARG             3
           3854 LOAD_CONST            1018 ('fghijknpqrst')
           3856 EXTENDED_ARG             3
           3858 LOAD_CONST            1019 ('bcdeklmno')
           3860 EXTENDED_ARG             3
           3862 LOAD_CONST            1020 ('klmopqrst')
           3864 EXTENDED_ARG             3
           3866 LOAD_CONST            1021 ('bdeklmnouvw')
           3868 EXTENDED_ARG             3
           3870 LOAD_CONST            1022 ('klmnopqst')
           3872 EXTENDED_ARG             3
           3874 LOAD_CONST            1023 ('klmnopqrstuvx')
           3876 EXTENDED_ARG             4
           3878 LOAD_CONST            1024 ('acklmno')
           3880 EXTENDED_ARG             4
           3882 LOAD_CONST            1025 ('hjpqrst')
           3884 EXTENDED_ARG             4
           3886 LOAD_CONST            1026 ('abcklmno')
           3888 EXTENDED_ARG             4
           3890 LOAD_CONST            1027 ('rst')
           3892 EXTENDED_ARG             3
           3894 BUILD_LIST             989
           3896 CALL_FUNCTION            1
           3898 COMPARE_OP               2 (==)
           3900 EXTENDED_ARG            15
           3902 POP_JUMP_IF_TRUE      3908
           3904 LOAD_GLOBAL             19 (AssertionError)
           3906 RAISE_VARARGS            1

113     >> 3908 LOAD_NAME               10 (num3)
           3910 LOAD_NAME                3 (solution)
           3912 EXTENDED_ARG             4
           3914 LOAD_CONST            1028 ('ysvydhncudvxqgub')
           3916 EXTENDED_ARG             4
           3918 LOAD_CONST            1029 ('jxomzgqmpccovmyy')
           3920 EXTENDED_ARG             4
           3922 LOAD_CONST            1030 ('hxiwwqdowwbdzrql')
           3924 EXTENDED_ARG             4
           3926 LOAD_CONST            1031 ('zqfykhyqgxpuedhx')
           3928 EXTENDED_ARG             4
           3930 LOAD_CONST            1032 ('vhszanyizlocrcta')
           3932 EXTENDED_ARG             4
           3934 LOAD_CONST            1033 ('dthywqimclejyrxf')
           3936 EXTENDED_ARG             4
           3938 LOAD_CONST            1034 ('pxvnsacefcaeqwpn')
           3940 EXTENDED_ARG             4
           3942 LOAD_CONST            1035 ('eibroystpzgkhwkt')
           3944 EXTENDED_ARG             4
           3946 LOAD_CONST            1036 ('efioczniyhzlkgxx')
           3948 EXTENDED_ARG             4
           3950 LOAD_CONST            1037 ('jbafyifjrdsevjlt')
           3952 EXTENDED_ARG             4
           3954 LOAD_CONST            1038 ('noggsbrxuzxxxpnv')
           3956 EXTENDED_ARG             4
           3958 LOAD_CONST            1039 ('usxugdobkxyvebgp')
           3960 EXTENDED_ARG             4
           3962 LOAD_CONST            1040 ('omppygjbdzvfncoh')
           3964 EXTENDED_ARG             4
           3966 LOAD_CONST            1041 ('lszhxcyfyhbezqpl')
           3968 EXTENDED_ARG             4
           3970 LOAD_CONST            1042 ('sywbjmfmigsrdhbe')
           3972 EXTENDED_ARG             4
           3974 LOAD_CONST            1043 ('kmitesfpzturedvn')
           3976 EXTENDED_ARG             4
           3978 LOAD_CONST            1044 ('fhccayoplynamcmf')
           3980 EXTENDED_ARG             4
           3982 LOAD_CONST            1045 ('xwkxxvmngwdkktcq')
           3984 EXTENDED_ARG             4
           3986 LOAD_CONST            1046 ('bkdetlrdtrvxtwnm')
           3988 EXTENDED_ARG             4
           3990 LOAD_CONST            1047 ('otbqjkibazuiuzjc')
           3992 EXTENDED_ARG             4
           3994 LOAD_CONST            1048 ('bvdlpsuozpxykhso')
           3996 EXTENDED_ARG             4
           3998 LOAD_CONST            1049 ('sfkdemywenvutigi')
           4000 EXTENDED_ARG             4
           4002 LOAD_CONST            1050 ('zlsgexavkjlbniyz')
           4004 EXTENDED_ARG             4
           4006 LOAD_CONST            1051 ('omvmljrelegkrnly')
           4008 EXTENDED_ARG             4
           4010 LOAD_CONST            1052 ('ncfqxwbgspmmxequ')
           4012 EXTENDED_ARG             4
           4014 LOAD_CONST            1053 ('nsnusovrqfyjqcmi')
           4016 EXTENDED_ARG             4
           4018 LOAD_CONST            1054 ('xmfltlmbucykoygu')
           4020 EXTENDED_ARG             4
           4022 LOAD_CONST            1055 ('znevkwdmcjkxazvx')
           4024 EXTENDED_ARG             4
           4026 LOAD_CONST            1056 ('qmmlumphgweyuqll')
           4028 EXTENDED_ARG             4
           4030 LOAD_CONST            1057 ('vvwllhnjjilkkfbr')
           4032 EXTENDED_ARG             4
           4034 LOAD_CONST            1058 ('tfczebbrmcwkijpy')
           4036 EXTENDED_ARG             4
           4038 LOAD_CONST            1059 ('dyqudxtooxmzaivg')
           4040 EXTENDED_ARG             4
           4042 LOAD_CONST            1060 ('qabmbvkkacpipzwv')
           4044 EXTENDED_ARG             4
           4046 LOAD_CONST            1061 ('ousivmwzqkzowbsf')
           4048 EXTENDED_ARG             4
           4050 LOAD_CONST            1062 ('wiajbnzcyczvdkme')
           4052 EXTENDED_ARG             4
           4054 LOAD_CONST            1063 ('jtvkqglawuiitvne')
           4056 EXTENDED_ARG             4
           4058 LOAD_CONST            1064 ('hynkguvzlahiaweu')
           4060 EXTENDED_ARG             4
           4062 LOAD_CONST            1065 ('dcdhzutcxsrwhtiu')
           4064 EXTENDED_ARG             4
           4066 LOAD_CONST            1066 ('sjkbkfbzcltyhkzc')
           4068 EXTENDED_ARG             4
           4070 LOAD_CONST            1067 ('vmtoulenvyzgmzph')
           4072 EXTENDED_ARG             4
           4074 LOAD_CONST            1068 ('hhpjlqospgyrpjnr')
           4076 EXTENDED_ARG             4
           4078 LOAD_CONST            1069 ('trxsiqvzjdsumnbx')
           4080 EXTENDED_ARG             4
           4082 LOAD_CONST            1070 ('ifmzrmfjlfbxrspp')
           4084 EXTENDED_ARG             4
           4086 LOAD_CONST            1071 ('zuybbnxweoodzrcp')
           4088 EXTENDED_ARG             4
           4090 LOAD_CONST            1072 ('dqselcmauqpdbvji')
           4092 EXTENDED_ARG             4
           4094 LOAD_CONST            1073 ('ucdmjxlnodsqbtpf')
           4096 EXTENDED_ARG             4
           4098 LOAD_CONST            1074 ('yxqxoqyqsuxbvvwh')
           4100 EXTENDED_ARG             4
           4102 LOAD_CONST            1075 ('jifmvnffunc2jlgdux')
           4104 EXTENDED_ARG             4
           4106 LOAD_CONST            1076 ('fttypgxftlzhrjhu')
           4108 EXTENDED_ARG             4
           4110 LOAD_CONST            1077 ('rzmkqtaejgzrwvht')
           4112 EXTENDED_ARG             4
           4114 LOAD_CONST            1078 ('fylzmnvoslrjeuhu')
           4116 EXTENDED_ARG             4
           4118 LOAD_CONST            1079 ('xxhmsywcfchxybtz')
           4120 EXTENDED_ARG             4
           4122 LOAD_CONST            1080 ('nivviopjjkilmfnt')
           4124 EXTENDED_ARG             4
           4126 LOAD_CONST            1081 ('vlvtonhigprfttuk')
           4128 EXTENDED_ARG             4
           4130 LOAD_CONST            1082 ('cwgnurrfabcfotdmj')
           4132 EXTENDED_ARG             4
           4134 LOAD_CONST            1083 ('erjxfseyzaygaujp')
           4136 EXTENDED_ARG             4
           4138 LOAD_CONST            1084 ('nrcqdwczglmcvinq')
           4140 EXTENDED_ARG             4
           4142 LOAD_CONST            1085 ('dqbyglmywihtexid')
           4144 EXTENDED_ARG             4
           4146 LOAD_CONST            1086 ('vqggccuiimjqqpuz')
           4148 EXTENDED_ARG             4
           4150 LOAD_CONST            1087 ('wbvvklwhouxxcbzg')
           4152 EXTENDED_ARG             4
           4154 LOAD_CONST            1088 ('jxstdmcbouqvysje')
           4156 EXTENDED_ARG             4
           4158 LOAD_CONST            1089 ('envdnanmuewgheqr')
           4160 EXTENDED_ARG             4
           4162 LOAD_CONST            1090 ('oxjeneckyoxdypwq')
           4164 EXTENDED_ARG             4
           4166 LOAD_CONST            1091 ('ityoxogkfmlasgfq')
           4168 EXTENDED_ARG             4
           4170 LOAD_CONST            1092 ('tgpkcweywtqopjnc')
           4172 EXTENDED_ARG             4
           4174 LOAD_CONST            1093 ('hepoijpjgvckkqzc')
           4176 EXTENDED_ARG             4
           4178 LOAD_CONST            1094 ('ubppuzmagmjgmjnf')
           4180 EXTENDED_ARG             4
           4182 LOAD_CONST            1095 ('snvaiqinphtkbxtc')
           4184 EXTENDED_ARG             4
           4186 LOAD_CONST            1096 ('wvdwymqejrygisbn')
           4188 EXTENDED_ARG             4
           4190 LOAD_CONST            1097 ('kmbwjynfbwyablvs')
           4192 EXTENDED_ARG             4
           4194 LOAD_CONST            1098 ('rsscpinfcegvnulj')
           4196 EXTENDED_ARG             4
           4198 LOAD_CONST            1099 ('oplzudhvjaumtavx')
           4200 EXTENDED_ARG             4
           4202 LOAD_CONST            1100 ('oionhndcrjvfexir')
           4204 EXTENDED_ARG             4
           4206 LOAD_CONST            1101 ('cxxlrudrixtmjsgw')
           4208 EXTENDED_ARG             4
           4210 LOAD_CONST            1102 ('sfngfbrksewwbwuo')
           4212 EXTENDED_ARG             4
           4214 LOAD_CONST            1103 ('wngezcjkxlftmure')
           4216 EXTENDED_ARG             4
           4218 LOAD_CONST            1104 ('xgkmmsvjjvtlwyko')
           4220 EXTENDED_ARG             4
           4222 LOAD_CONST            1105 ('dfaihamfjrwobkai')
           4224 EXTENDED_ARG             4
           4226 LOAD_CONST            1106 ('ybzlbmtejcbhkbqn')
           4228 EXTENDED_ARG             4
           4230 LOAD_CONST            1107 ('yvgttkpmodjrdjaj')
           4232 EXTENDED_ARG             4
           4234 LOAD_CONST            1108 ('wsfkdifjxsisyazp')
           4236 EXTENDED_ARG             4
           4238 LOAD_CONST            1109 ('btdahuinzvvmyuti')
           4240 EXTENDED_ARG             4
           4242 LOAD_CONST            1110 ('sppdjjphoadtnxqz')
           4244 EXTENDED_ARG             4
           4246 LOAD_CONST            1111 ('idikaxmkupaaeyvd')
           4248 EXTENDED_ARG             4
           4250 LOAD_CONST            1112 ('bxmusrwhsuglelsa')
           4252 EXTENDED_ARG             4
           4254 LOAD_CONST            1113 ('wllftkyuyjwumzfz')
           4256 EXTENDED_ARG             4
           4258 LOAD_CONST            1114 ('lsrfakcruqfghhqr')
           4260 EXTENDED_ARG             4
           4262 LOAD_CONST            1115 ('oitbsfztaayzgttw')
           4264 EXTENDED_ARG             4
           4266 LOAD_CONST            1116 ('qvdaclqbkxzxtvji')
           4268 EXTENDED_ARG             4
           4270 LOAD_CONST            1117 ('hqtnylqopcuyitvv')
           4272 EXTENDED_ARG             4
           4274 LOAD_CONST            1118 ('dovrsivynjuycgob')
           4276 EXTENDED_ARG             4
           4278 LOAD_CONST            1119 ('zbeexmgffbvgyukt')
           4280 EXTENDED_ARG             4
           4282 LOAD_CONST            1120 ('jnyrkwuketocbnlp')
           4284 EXTENDED_ARG             4
           4286 LOAD_CONST            1121 ('kesivzsfimkupknz')
           4288 EXTENDED_ARG             4
           4290 LOAD_CONST            1122 ('fvctuhkhcsxgpnlc')
           4292 EXTENDED_ARG             4
           4294 LOAD_CONST            1123 ('geyiflxobsqqgysp')
           4296 EXTENDED_ARG             4
           4298 LOAD_CONST            1124 ('vdhnckkljiwiylkc')
           4300 EXTENDED_ARG             4
           4302 LOAD_CONST            1125 ('jxixmpjvkuisogjx')
           4304 EXTENDED_ARG             4
           4306 LOAD_CONST            1126 ('ggmgthlqqfjzvsiv')
           4308 EXTENDED_ARG             4
           4310 LOAD_CONST            1127 ('nkdbbqswrytidodb')
           4312 EXTENDED_ARG             4
           4314 LOAD_CONST            1128 ('cvnxasfxcyyprwky')
           4316 EXTENDED_ARG             4
           4318 LOAD_CONST            1129 ('msptawajcgigotxx')
           4320 EXTENDED_ARG             4
           4322 LOAD_CONST            1130 ('lggqfreicrrzgqug')
           4324 EXTENDED_ARG             4
           4326 LOAD_CONST            1131 ('pywexuvmpapzhhmk')
           4328 EXTENDED_ARG             4
           4330 LOAD_CONST            1132 ('yjfzlaazckdxqhpk')
           4332 EXTENDED_ARG             4
           4334 LOAD_CONST            1133 ('gxopiqnejwahizvy')
           4336 EXTENDED_ARG             4
           4338 LOAD_CONST            1134 ('rwptjuqhjshtosim')
           4340 EXTENDED_ARG             4
           4342 LOAD_CONST            1135 ('zhszbxltmwjfbcnn')
           4344 EXTENDED_ARG             4
           4346 LOAD_CONST            1136 ('hznbmqrhucjlhtev')
           4348 EXTENDED_ARG             4
           4350 LOAD_CONST            1137 ('repwvulbjzulzqlm')
           4352 EXTENDED_ARG             4
           4354 LOAD_CONST            1138 ('juemhyiaujdhjwda')
           4356 EXTENDED_ARG             4
           4358 LOAD_CONST            1139 ('iphegtklhgyiabcof')
           4360 EXTENDED_ARG             4
           4362 LOAD_CONST            1140 ('tpqxoalgjntzhxph')
           4364 EXTENDED_ARG             4
           4366 LOAD_CONST            1141 ('ahnrxtoyzqrqrxce')
           4368 EXTENDED_ARG             4
           4370 LOAD_CONST            1142 ('ljsunmfpleczezfi')
           4372 EXTENDED_ARG             4
           4374 LOAD_CONST            1143 ('flqbbwjpvmpiagkm')
           4376 EXTENDED_ARG             4
           4378 LOAD_CONST            1144 ('enxrdnasgsrczncm')
           4380 EXTENDED_ARG             4
           4382 LOAD_CONST            1145 ('setirvmdopdbgqqi')
           4384 EXTENDED_ARG             4
           4386 LOAD_CONST            1146 ('uuyoeqtcgvygmlbd')
           4388 EXTENDED_ARG             4
           4390 LOAD_CONST            1147 ('gznmxhdzpgclmmce')
           4392 EXTENDED_ARG             4
           4394 LOAD_CONST            1148 ('wrqmvtilsmjrfruj')
           4396 EXTENDED_ARG             4
           4398 LOAD_CONST            1149 ('nzbqahmftsbygrje')
           4400 EXTENDED_ARG             4
           4402 LOAD_CONST            1150 ('nodxqfwosevxikai')
           4404 EXTENDED_ARG             4
           4406 LOAD_CONST            1151 ('ynzmckxtfampkdcb')
           4408 EXTENDED_ARG             4
           4410 LOAD_CONST            1152 ('ishsysxcjavxukfq')
           4412 EXTENDED_ARG             4
           4414 LOAD_CONST            1153 ('mbwcnmktksqoptdx')
           4416 EXTENDED_ARG             4
           4418 LOAD_CONST            1154 ('ybpgwitxuarhyuud')
           4420 EXTENDED_ARG             4
           4422 LOAD_CONST            1155 ('odkhmislpnpjltvc')
           4424 EXTENDED_ARG             4
           4426 LOAD_CONST            1156 ('imlknoihasmgbjle')
           4428 EXTENDED_ARG             4
           4430 LOAD_CONST            1157 ('autoweexfbmsnamc')
           4432 EXTENDED_ARG             4
           4434 LOAD_CONST            1158 ('pzddxvvmnmujzovy')
           4436 EXTENDED_ARG             4
           4438 LOAD_CONST            1159 ('zbklmwsqltyiqjaq')
           4440 EXTENDED_ARG             4
           4442 LOAD_CONST            1160 ('wsfezmwlwnovzfnq')
           4444 EXTENDED_ARG             4
           4446 LOAD_CONST            1161 ('ipvtflaxlabczbjwg')
           4448 EXTENDED_ARG             4
           4450 LOAD_CONST            1162 ('xmeypiupgboeikma')
           4452 EXTENDED_ARG             4
           4454 LOAD_CONST            1163 ('qmhxpnusoafktsrp')
           4456 EXTENDED_ARG             4
           4458 LOAD_CONST            1164 ('akbzwaoevusmqhjy')
           4460 EXTENDED_ARG             4
           4462 LOAD_CONST            1165 ('ptnrluxfiaoedirs')
           4464 EXTENDED_ARG             4
           4466 LOAD_CONST            1166 ('fkkujjetvujaffev')
           4468 EXTENDED_ARG             4
           4470 LOAD_CONST            1167 ('iqlaebkqlabcuugvd')
           4472 EXTENDED_ARG             4
           4474 LOAD_CONST            1168 ('tvfazupnodyxyegj')
           4476 EXTENDED_ARG             4
           4478 LOAD_CONST            1169 ('cxxbmckkoocwwmkv')
           4480 EXTENDED_ARG             4
           4482 LOAD_CONST            1170 ('eiinwggrnufbuefm')
           4484 EXTENDED_ARG             4
           4486 LOAD_CONST            1171 ('jbajzgyvabcjrpirb')
           4488 EXTENDED_ARG             4
           4490 LOAD_CONST            1172 ('anotitqeflusqkmx')
           4492 EXTENDED_ARG             4
           4494 LOAD_CONST            1173 ('kkyyjfyqfwuyphvs')
           4496 EXTENDED_ARG             4
           4498 LOAD_CONST            1174 ('mkxxxgmewnnfmtgw')
           4500 EXTENDED_ARG             4
           4502 LOAD_CONST            1175 ('rfzfkowvhlbuptnn')
           4504 EXTENDED_ARG             4
           4506 LOAD_CONST            1176 ('yihacnrktjrrbupi')
           4508 EXTENDED_ARG             4
           4510 LOAD_CONST            1177 ('ljbfbmrxivbqhvgn')
           4512 EXTENDED_ARG             4
           4514 LOAD_CONST            1178 ('kelkifhcummieqec')
           4516 EXTENDED_ARG             4
           4518 LOAD_CONST            1179 ('qwglfqmlgtufeggt')
           4520 EXTENDED_ARG             4
           4522 LOAD_CONST            1180 ('ztdsjupiobdswepc')
           4524 EXTENDED_ARG             4
           4526 LOAD_CONST            1181 ('nxxrjnqebfrtztab')
           4528 EXTENDED_ARG             4
           4530 LOAD_CONST            1182 ('zwuijitgzkamuohu')
           4532 EXTENDED_ARG             4
           4534 LOAD_CONST            1183 ('skctyqbrtdlybrad')
           4536 EXTENDED_ARG             4
           4538 LOAD_CONST            1184 ('ftvbzzqisluhwvoj')
           4540 EXTENDED_ARG             4
           4542 LOAD_CONST            1185 ('tkyzlbdwikxwxtfm')
           4544 EXTENDED_ARG             4
           4546 LOAD_CONST            1186 ('yqzbwtibgyhezefc')
           4548 EXTENDED_ARG             4
           4550 LOAD_CONST            1187 ('ugmtditxujqhzdjk')
           4552 EXTENDED_ARG             4
           4554 LOAD_CONST            1188 ('pzqfxlcsbyiayoqn')
           4556 EXTENDED_ARG             4
           4558 LOAD_CONST            1189 ('mvuvmubzxoapqlwq')
           4560 EXTENDED_ARG             4
           4562 LOAD_CONST            1190 ('wxydvrxojyifgild')
           4564 EXTENDED_ARG             4
           4566 LOAD_CONST            1191 ('gaubuvvoncoahhqs')
           4568 EXTENDED_ARG             4
           4570 LOAD_CONST            1192 ('arrqgidasqpyozqo')
           4572 EXTENDED_ARG             4
           4574 LOAD_CONST            1193 ('hlktmcpfqmqunsiw')
           4576 EXTENDED_ARG             4
           4578 LOAD_CONST            1194 ('hpshspcjtkvjtyfc')
           4580 EXTENDED_ARG             4
           4582 LOAD_CONST            1195 ('xwdjpdyqbgkvbbto')
           4584 EXTENDED_ARG             4
           4586 LOAD_CONST            1196 ('dnipqamvliabetfk')
           4588 EXTENDED_ARG             4
           4590 LOAD_CONST            1197 ('zrptncovohuprjfj')
           4592 EXTENDED_ARG             4
           4594 LOAD_CONST            1198 ('zykerhdnpwqnklnp')
           4596 EXTENDED_ARG             4
           4598 LOAD_CONST            1199 ('wehvwpjsjmlhbxme')
           4600 EXTENDED_ARG             4
           4602 LOAD_CONST            1200 ('qhabvcixedhtacnm')
           4604 EXTENDED_ARG             4
           4606 LOAD_CONST            1201 ('nzbonhjtiragsjxu')
           4608 EXTENDED_ARG             4
           4610 LOAD_CONST            1202 ('piktfsxlejzjpmxa')
           4612 EXTENDED_ARG             4
           4614 LOAD_CONST            1203 ('kpgluxplomivhups')
           4616 EXTENDED_ARG             4
           4618 LOAD_CONST            1204 ('utbqkkbmdakmajvb')
           4620 EXTENDED_ARG             4
           4622 LOAD_CONST            1205 ('pbosjdvammowabof')
           4624 EXTENDED_ARG             4
           4626 LOAD_CONST            1206 ('hwwpavjyghyogxiz')
           4628 EXTENDED_ARG             4
           4630 LOAD_CONST            1207 ('qixjbuehpllqwbir')
           4632 EXTENDED_ARG             4
           4634 LOAD_CONST            1208 ('watokwdhqrlthmyt')
           4636 EXTENDED_ARG             4
           4638 LOAD_CONST            1209 ('fiuvnmucwsfhvirt')
           4640 EXTENDED_ARG             4
           4642 LOAD_CONST            1210 ('efjbktqktzylkzym')
           4644 EXTENDED_ARG             4
           4646 LOAD_CONST            1211 ('eyagoufvrlrbukvi')
           4648 EXTENDED_ARG             4
           4650 LOAD_CONST            1212 ('dbebcdxywrceoioj')
           4652 EXTENDED_ARG             4
           4654 LOAD_CONST            1213 ('dmejkiuqtpzkvtil')
           4656 EXTENDED_ARG             4
           4658 LOAD_CONST            1214 ('irxxxrbxjvvisefx')
           4660 EXTENDED_ARG             4
           4662 LOAD_CONST            1215 ('ezacasyffovrewri')
           4664 EXTENDED_ARG             4
           4666 LOAD_CONST            1216 ('zfoernjrzvxkzqjn')
           4668 EXTENDED_ARG             4
           4670 LOAD_CONST            1217 ('krrmkfftxdxqxrjf')
           4672 EXTENDED_ARG             4
           4674 LOAD_CONST            1218 ('xexiopshwbkipjdw')
           4676 EXTENDED_ARG             4
           4678 LOAD_CONST            1219 ('cnuiizhcocljycvu')
           4680 EXTENDED_ARG             4
           4682 LOAD_CONST            1220 ('idsxihqjacgtwiuu')
           4684 EXTENDED_ARG             4
           4686 LOAD_CONST            1221 ('nwjjtbiketrqdvxb')
           4688 EXTENDED_ARG             4
           4690 LOAD_CONST            1222 ('avmxhxabcxhflzcbs')
           4692 EXTENDED_ARG             4
           4694 LOAD_CONST            1223 ('uqxjgosfyjcbxshz')
           4696 EXTENDED_ARG             4
           4698 LOAD_CONST            1224 ('gwybdcsgvjjacjoq')
           4700 EXTENDED_ARG             4
           4702 LOAD_CONST            1225 ('zokabcujdqyhfvvve')
           4704 EXTENDED_ARG             4
           4706 LOAD_CONST            1226 ('dudqkxdyvnmzxbal')
           4708 EXTENDED_ARG             4
           4710 LOAD_CONST            1227 ('duurelhvlvlwtisc')
           4712 EXTENDED_ARG             4
           4714 LOAD_CONST            1228 ('vvduznkfxsydjjsu')
           4716 EXTENDED_ARG             4
           4718 LOAD_CONST            1229 ('jvohyxbezkxdybjk')
           4720 EXTENDED_ARG             4
           4722 LOAD_CONST            1230 ('tecmjpqvbqdfgbch')
           4724 EXTENDED_ARG             4
           4726 LOAD_CONST            1231 ('wmiwtqmxlipobteb')
           4728 EXTENDED_ARG             4
           4730 LOAD_CONST            1232 ('bzhfoutsommbeahv')
           4732 EXTENDED_ARG             4
           4734 LOAD_CONST            1233 ('pzxilyvfyokfmsmr')
           4736 EXTENDED_ARG             4
           4738 LOAD_CONST            1234 ('fvptnoujoahvjljv')
           4740 EXTENDED_ARG             4
           4742 LOAD_CONST            1235 ('nntjwlzvtlwjijtq')
           4744 EXTENDED_ARG             4
           4746 LOAD_CONST            1236 ('iiahigptxppvjwwh')
           4748 EXTENDED_ARG             4
           4750 LOAD_CONST            1237 ('fiwxrfkvznhngctp')
           4752 EXTENDED_ARG             4
           4754 LOAD_CONST            1238 ('hljuecxsqwhfhooj')
           4756 EXTENDED_ARG             4
           4758 LOAD_CONST            1239 ('kpgylifngxbybkwm')
           4760 EXTENDED_ARG             4
           4762 LOAD_CONST            1240 ('ckxgbjjygzkystat')
           4764 EXTENDED_ARG             4
           4766 LOAD_CONST            1241 ('anxjpmmadenhxunx')
           4768 EXTENDED_ARG             4
           4770 LOAD_CONST            1242 ('kztzbysfhebhkxhw')
           4772 EXTENDED_ARG             4
           4774 LOAD_CONST            1243 ('qeywqntlveiebhos')
           4776 EXTENDED_ARG             4
           4778 LOAD_CONST            1244 ('jlbvhtvumiyxwqlo')
           4780 EXTENDED_ARG             4
           4782 LOAD_CONST            1245 ('ubsttmdcjigfizes')
           4784 EXTENDED_ARG             4
           4786 LOAD_CONST            1246 ('tifeodqhusljfhxl')
           4788 EXTENDED_ARG             4
           4790 LOAD_CONST            1247 ('xhtrvehthwvsxkmj')
           4792 EXTENDED_ARG             4
           4794 LOAD_CONST            1248 ('slytykltdhwruorn')
           4796 EXTENDED_ARG             4
           4798 LOAD_CONST            1249 ('ettsedvbbxttpkwg')
           4800 EXTENDED_ARG             4
           4802 LOAD_CONST            1250 ('znlstbcrbxxyauvt')
           4804 EXTENDED_ARG             4
           4806 LOAD_CONST            1251 ('zvxkminzbadeyxpn')
           4808 EXTENDED_ARG             4
           4810 LOAD_CONST            1252 ('vkeqpqwrdrzvrdkg')
           4812 EXTENDED_ARG             4
           4814 LOAD_CONST            1253 ('lmgvnrmbwermpsxx')
           4816 EXTENDED_ARG             4
           4818 LOAD_CONST            1254 ('wpcihvumyumoljws')
           4820 EXTENDED_ARG             4
           4822 LOAD_CONST            1255 ('sqqleapevuisjovs')
           4824 EXTENDED_ARG             4
           4826 LOAD_CONST            1256 ('xrtefpneewlrlvwd')
           4828 EXTENDED_ARG             4
           4830 LOAD_CONST            1257 ('mmbabccilwfyvvjak')
           4832 EXTENDED_ARG             4
           4834 LOAD_CONST            1258 ('mqebclxzlkierkjf')
           4836 EXTENDED_ARG             4
           4838 LOAD_CONST            1259 ('cuytrwygyntgajgm')
           4840 EXTENDED_ARG             4
           4842 LOAD_CONST            1260 ('fhodjnmtmzrqzszj')
           4844 EXTENDED_ARG             4
           4846 LOAD_CONST            1261 ('kmgwmlnfykcuvqnl')
           4848 EXTENDED_ARG             4
           4850 LOAD_CONST            1262 ('aopjewaqievtqdct')
           4852 EXTENDED_ARG             4
           4854 LOAD_CONST            1263 ('tjouxksorchkworv')
           4856 EXTENDED_ARG             4
           4858 LOAD_CONST            1264 ('ncirabcozpldzewjz')
           4860 EXTENDED_ARG             4
           4862 LOAD_CONST            1265 ('sucivpgmovkfqxpn')
           4864 EXTENDED_ARG             4
           4866 LOAD_CONST            1266 ('akhusibommljkvfb')
           4868 EXTENDED_ARG             4
           4870 LOAD_CONST            1267 ('cdxrtkejlxftegjn')
           4872 EXTENDED_ARG             4
           4874 LOAD_CONST            1268 ('pcykwqocqfjcpygs')
           4876 EXTENDED_ARG             4
           4878 LOAD_CONST            1269 ('ddgipyltjxtthplq')
           4880 EXTENDED_ARG             4
           4882 LOAD_CONST            1270 ('uqtqauyppkzzztxr')
           4884 EXTENDED_ARG             4
           4886 LOAD_CONST            1271 ('byziilqifrkefnmx')
           4888 EXTENDED_ARG             4
           4890 LOAD_CONST            1272 ('pihmqvosbrmfwvgj')
           4892 EXTENDED_ARG             4
           4894 LOAD_CONST            1273 ('zcrokjgwuujlsqzk')
           4896 EXTENDED_ARG             4
           4898 LOAD_CONST            1274 ('midiigvhwxuuxdoj')
           4900 EXTENDED_ARG             4
           4902 LOAD_CONST            1275 ('quzizelifvrqgiqy')
           4904 EXTENDED_ARG             4
           4906 LOAD_CONST            1276 ('qoizxtjfeiykktbh')
           4908 EXTENDED_ARG             4
           4910 LOAD_CONST            1277 ('kopvmoiueozhbxfe')
           4912 EXTENDED_ARG             4
           4914 LOAD_CONST            1278 ('rabczignulcwpsobz')
           4916 EXTENDED_ARG             4
           4918 LOAD_CONST            1279 ('esmkumjwclulmmlg')
           4920 EXTENDED_ARG             5
           4922 LOAD_CONST            1280 ('cwknucjbjropshgm')
           4924 EXTENDED_ARG             5
           4926 LOAD_CONST            1281 ('xrkvscqbnuofxbbd')
           4928 EXTENDED_ARG             5
           4930 LOAD_CONST            1282 ('lfhexistfbnypjxb')
           4932 EXTENDED_ARG             5
           4934 LOAD_CONST            1283 ('qtvceoxufqerkgcd')
           4936 EXTENDED_ARG             5
           4938 LOAD_CONST            1284 ('nvqnrbzmizbmenoj')
           4940 EXTENDED_ARG             5
           4942 LOAD_CONST            1285 ('vaxeseydjahzmeqv')
           4944 EXTENDED_ARG             5
           4946 LOAD_CONST            1286 ('kkhvyzvdlupbekot')
           4948 EXTENDED_ARG             5
           4950 LOAD_CONST            1287 ('ghkdrqrrufndvlab')
           4952 EXTENDED_ARG             5
           4954 LOAD_CONST            1288 ('puuorkmgkyjrrfzm')
           4956 EXTENDED_ARG             5
           4958 LOAD_CONST            1289 ('qdojlkfsajazdbtr')
           4960 EXTENDED_ARG             5
           4962 LOAD_CONST            1290 ('trunvamzxxtruqqk')
           4964 EXTENDED_ARG             5
           4966 LOAD_CONST            1291 ('wyfqiycmuaxnwdmj')
           4968 EXTENDED_ARG             5
           4970 LOAD_CONST            1292 ('tehftxcnimfcgulv')
           4972 EXTENDED_ARG             5
           4974 LOAD_CONST            1293 ('xideohbursltsyaw')
           4976 EXTENDED_ARG             5
           4978 LOAD_CONST            1294 ('zukuxtscehugrlwz')
           4980 EXTENDED_ARG             5
           4982 LOAD_CONST            1295 ('tqyowyifdxmlekmi')
           4984 EXTENDED_ARG             5
           4986 LOAD_CONST            1296 ('gktvxxotbobtzjhz')
           4988 EXTENDED_ARG             5
           4990 LOAD_CONST            1297 ('sbrdswxuitwshrql')
           4992 EXTENDED_ARG             5
           4994 LOAD_CONST            1298 ('vjxkqyvipqlevbhk')
           4996 EXTENDED_ARG             5
           4998 LOAD_CONST            1299 ('xupvseicxsjlvprl')
           5000 EXTENDED_ARG             5
           5002 LOAD_CONST            1300 ('zzvgmaspjzobbbai')
           5004 EXTENDED_ARG             5
           5006 LOAD_CONST            1301 ('umqxughwbhxrbgnv')
           5008 EXTENDED_ARG             5
           5010 LOAD_CONST            1302 ('necgnedkdtsxllws')
           5012 EXTENDED_ARG             5
           5014 LOAD_CONST            1303 ('kfzhgtbffdkcmemk')
           5016 EXTENDED_ARG             5
           5018 LOAD_CONST            1304 ('jygmwohqgxytdabcc')
           5020 EXTENDED_ARG             5
           5022 LOAD_CONST            1305 ('xubntcuzhakycmhb')
           5024 EXTENDED_ARG             5
           5026 LOAD_CONST            1306 ('nykkvobihcvcbsom')
           5028 EXTENDED_ARG             5
           5030 LOAD_CONST            1307 ('jmpfjbgethlvegac')
           5032 EXTENDED_ARG             5
           5034 LOAD_CONST            1308 ('rcrkrqlqszizkuwn')
           5036 EXTENDED_ARG             5
           5038 LOAD_CONST            1309 ('mkvtjvezpqntwsor')
           5040 EXTENDED_ARG             5
           5042 LOAD_CONST            1310 ('vavxnwabzsvbxrta')
           5044 EXTENDED_ARG             5
           5046 LOAD_CONST            1311 ('wxjtawscbrqldboj')
           5048 EXTENDED_ARG             5
           5050 LOAD_CONST            1312 ('ukqyxnzmmregydtj')
           5052 EXTENDED_ARG             5
           5054 LOAD_CONST            1313 ('bzdoqdhyfxjhrtca')
           5056 EXTENDED_ARG             5
           5058 LOAD_CONST            1314 ('zwwifjejxilnlncq')
           5060 EXTENDED_ARG             5
           5062 LOAD_CONST            1315 ('zbhinfwhbsewmmnj')
           5064 EXTENDED_ARG             5
           5066 LOAD_CONST            1316 ('wpatetlrcetrwygn')
           5068 EXTENDED_ARG             5
           5070 LOAD_CONST            1317 ('qijjqtjtkjldjzpv')
           5072 EXTENDED_ARG             5
           5074 LOAD_CONST            1318 ('wizlmxgtbqokdive')
           5076 EXTENDED_ARG             5
           5078 LOAD_CONST            1319 ('gjowgwgtfyoyvakj')
           5080 EXTENDED_ARG             5
           5082 LOAD_CONST            1320 ('dutziyzhjwwdwbmh')
           5084 EXTENDED_ARG             5
           5086 LOAD_CONST            1321 ('hhxlvaslalqnjfez')
           5088 EXTENDED_ARG             5
           5090 LOAD_CONST            1322 ('nftbzbqrrdhpbvel')
           5092 EXTENDED_ARG             5
           5094 LOAD_CONST            1323 ('rawgbwriyffuvwea')
           5096 EXTENDED_ARG             5
           5098 LOAD_CONST            1324 ('qelvbxvcmyipiyux')
           5100 EXTENDED_ARG             5
           5102 LOAD_CONST            1325 ('gpvbmgzpjpvmfjou')
           5104 EXTENDED_ARG             5
           5106 LOAD_CONST            1326 ('edysbthmpzewjmhq')
           5108 EXTENDED_ARG             5
           5110 LOAD_CONST            1327 ('gimdgabewrjfmouq')
           5112 EXTENDED_ARG             5
           5114 LOAD_CONST            1328 ('kabamudmytcvskgz')
           5116 EXTENDED_ARG             5
           5118 LOAD_CONST            1329 ('jnbqnbtzepeettut')
           5120 EXTENDED_ARG             5
           5122 LOAD_CONST            1330 ('ubycgxbczobyuvty')
           5124 EXTENDED_ARG             5
           5126 LOAD_CONST            1331 ('ncqlwqzzlurrfurm')
           5128 EXTENDED_ARG             5
           5130 LOAD_CONST            1332 ('mqdliidaptajnque')
           5132 EXTENDED_ARG             5
           5134 LOAD_CONST            1333 ('aqkislhbhutlmskx')
           5136 EXTENDED_ARG             5
           5138 LOAD_CONST            1334 ('kqgowgleasjmgjro')
           5140 EXTENDED_ARG             5
           5142 LOAD_CONST            1335 ('anzasevxbinscrwy')
           5144 EXTENDED_ARG             5
           5146 LOAD_CONST            1336 ('mligzlmekbqjtlkz')
           5148 EXTENDED_ARG             5
           5150 LOAD_CONST            1337 ('acjwzeaariolohth')
           5152 EXTENDED_ARG             5
           5154 LOAD_CONST            1338 ('lewbaeswgtsegzgf')
           5156 EXTENDED_ARG             5
           5158 LOAD_CONST            1339 ('bkaleiidkzgtyukg')
           5160 EXTENDED_ARG             5
           5162 LOAD_CONST            1340 ('griqeggfgygajdxr')
           5164 EXTENDED_ARG             5
           5166 LOAD_CONST            1341 ('tiqtuoakcxhsppug')
           5168 EXTENDED_ARG             5
           5170 LOAD_CONST            1342 ('djwebkqgutgcqjkq')
           5172 EXTENDED_ARG             5
           5174 LOAD_CONST            1343 ('mtdquygxxpcnmxvg')
           5176 EXTENDED_ARG             5
           5178 LOAD_CONST            1344 ('lzbitojuuxxhrcms')
           5180 EXTENDED_ARG             5
           5182 LOAD_CONST            1345 ('wkqdzfkdeoxlrrrv')
           5184 EXTENDED_ARG             5
           5186 LOAD_CONST            1346 ('qdkvpynqxmqizxfh')
           5188 EXTENDED_ARG             5
           5190 LOAD_CONST            1347 ('rsypvochupieijuw')
           5192 EXTENDED_ARG             5
           5194 LOAD_CONST            1348 ('zhjqkrovsdewbwrg')
           5196 EXTENDED_ARG             5
           5198 LOAD_CONST            1349 ('cojrovhotitqglxf')
           5200 EXTENDED_ARG             5
           5202 LOAD_CONST            1350 ('vupizqllrxepdyej')
           5204 EXTENDED_ARG             5
           5206 LOAD_CONST            1351 ('rrcescgfpodyqgqj')
           5208 EXTENDED_ARG             5
           5210 LOAD_CONST            1352 ('enyhpwibqizxzxlf')
           5212 EXTENDED_ARG             5
           5214 LOAD_CONST            1353 ('ysgpfnkxewxpunmc')
           5216 EXTENDED_ARG             5
           5218 LOAD_CONST            1354 ('qqayjdiwesfhjqdj')
           5220 EXTENDED_ARG             5
           5222 LOAD_CONST            1355 ('vvxsqmsxkwlowkaz')
           5224 EXTENDED_ARG             5
           5226 LOAD_CONST            1356 ('vhbgvteemnjcjzjn')
           5228 EXTENDED_ARG             5
           5230 LOAD_CONST            1357 ('pjvysfsrgpzeefgi')
           5232 EXTENDED_ARG             5
           5234 LOAD_CONST            1358 ('hjpqwdkuxpvojlrb')
           5236 EXTENDED_ARG             5
           5238 LOAD_CONST            1359 ('qdviqqkpfpmusqku')
           5240 EXTENDED_ARG             5
           5242 LOAD_CONST            1360 ('zekclapatdchkkuu')
           5244 EXTENDED_ARG             5
           5246 LOAD_CONST            1361 ('ushhsykosapkwfvn')
           5248 EXTENDED_ARG             5
           5250 LOAD_CONST            1362 ('qlwhigtykfafzwkf')
           5252 EXTENDED_ARG             5
           5254 LOAD_CONST            1363 ('ueeemzyxxionuzvh')
           5256 EXTENDED_ARG             5
           5258 LOAD_CONST            1364 ('uxidcslniryrlkfr')
           5260 EXTENDED_ARG             5
           5262 LOAD_CONST            1365 ('wjrqpxvnjwnzvhaw')
           5264 EXTENDED_ARG             5
           5266 LOAD_CONST            1366 ('sfufkmlseobjehmb')
           5268 EXTENDED_ARG             5
           5270 LOAD_CONST            1367 ('viqcfxqgzfgjlwyn')
           5272 EXTENDED_ARG             5
           5274 LOAD_CONST            1368 ('vfffdaynlllgflud')
           5276 EXTENDED_ARG             5
           5278 LOAD_CONST            1369 ('xgbzqwuziammugee')
           5280 EXTENDED_ARG             5
           5282 LOAD_CONST            1370 ('juwviucofrqykbph')
           5284 EXTENDED_ARG             5
           5286 LOAD_CONST            1371 ('nfhofnyrvpgnrncr')
           5288 EXTENDED_ARG             5
           5290 LOAD_CONST            1372 ('xwnrmtztbduhaxzm')
           5292 EXTENDED_ARG             5
           5294 LOAD_CONST            1373 ('qwjuwencytcviddt')
           5296 EXTENDED_ARG             5
           5298 LOAD_CONST            1374 ('zgtzokhuophlklax')
           5300 EXTENDED_ARG             5
           5302 LOAD_CONST            1375 ('yhhhyqbivjulhxzz')
           5304 EXTENDED_ARG             5
           5306 LOAD_CONST            1376 ('qjlrmtnkpezzxbip')
           5308 EXTENDED_ARG             5
           5310 LOAD_CONST            1377 ('csjtxagscqzcyxgw')
           5312 EXTENDED_ARG             5
           5314 LOAD_CONST            1378 ('gibiwnkxfwmdypdb')
           5316 EXTENDED_ARG             5
           5318 LOAD_CONST            1379 ('zwuqefypxjswiqnr')
           5320 EXTENDED_ARG             5
           5322 LOAD_CONST            1380 ('rvwoomgislxnjiku')
           5324 EXTENDED_ARG             5
           5326 LOAD_CONST            1381 ('avtzjpgdqkrswwil')
           5328 EXTENDED_ARG             5
           5330 LOAD_CONST            1382 ('tybnjxlyeppveuln')
           5332 EXTENDED_ARG             5
           5334 LOAD_CONST            1383 ('hvjlkwgdbzjuthio')
           5336 EXTENDED_ARG             5
           5338 LOAD_CONST            1384 ('uwmvnynpvcrtjaoi')
           5340 EXTENDED_ARG             5
           5342 LOAD_CONST            1385 ('tazibajxbbektuny')
           5344 EXTENDED_ARG             5
           5346 LOAD_CONST            1386 ('eydtgcsqrjeudusa')
           5348 EXTENDED_ARG             5
           5350 LOAD_CONST            1387 ('cjvzwcgypecfudux')
           5352 EXTENDED_ARG             5
           5354 LOAD_CONST            1388 ('oovnezznsbbuzage')
           5356 EXTENDED_ARG             5
           5358 LOAD_CONST            1389 ('jjeciyognokzoavb')
           5360 EXTENDED_ARG             5
           5362 LOAD_CONST            1390 ('ewwzxbjfxgyrwdnz')
           5364 EXTENDED_ARG             5
           5366 LOAD_CONST            1391 ('mqtotsnaejvwsfxv')
           5368 EXTENDED_ARG             5
           5370 LOAD_CONST            1392 ('hewhemklxufjlxds')
           5372 EXTENDED_ARG             5
           5374 LOAD_CONST            1393 ('qfgrjckxuvxppffa')
           5376 EXTENDED_ARG             5
           5378 LOAD_CONST            1394 ('xrkanxmmdhjnrpms')
           5380 EXTENDED_ARG             5
           5382 LOAD_CONST            1395 ('ugszqiazpribuhin')
           5384 EXTENDED_ARG             5
           5386 LOAD_CONST            1396 ('hhtlbstnuebaovan')
           5388 EXTENDED_ARG             5
           5390 LOAD_CONST            1397 ('wmerwupitfwffwjq')
           5392 EXTENDED_ARG             5
           5394 LOAD_CONST            1398 ('cfhlftbplljrdnmt')
           5396 EXTENDED_ARG             5
           5398 LOAD_CONST            1399 ('iwgvszqjzoutyofq')
           5400 EXTENDED_ARG             5
           5402 LOAD_CONST            1400 ('rfddyjwanuajwfms')
           5404 EXTENDED_ARG             5
           5406 LOAD_CONST            1401 ('glcpwdgghxjjlbhl')
           5408 EXTENDED_ARG             5
           5410 LOAD_CONST            1402 ('opyabchjxtqeaqluw')
           5412 EXTENDED_ARG             5
           5414 LOAD_CONST            1403 ('zqrzsgsurxcablbp')
           5416 EXTENDED_ARG             5
           5418 LOAD_CONST            1404 ('tlzsuhpazrgyftra')
           5420 EXTENDED_ARG             5
           5422 LOAD_CONST            1405 ('hfbywjxrjvfyfjor')
           5424 EXTENDED_ARG             5
           5426 LOAD_CONST            1406 ('xfuisoaqkhitaneo')
           5428 EXTENDED_ARG             5
           5430 LOAD_CONST            1407 ('jbmpkilwrfevuabc')
           5432 EXTENDED_ARG             5
           5434 LOAD_CONST            1408 ('riftearjllxbsrpg')
           5436 EXTENDED_ARG             5
           5438 LOAD_CONST            1409 ('visatalbyphvpcqn')
           5440 EXTENDED_ARG             5
           5442 LOAD_CONST            1410 ('tezwyeuynxiqceny')
           5444 EXTENDED_ARG             5
           5446 LOAD_CONST            1411 ('gmllnngsknyuqfyg')
           5448 EXTENDED_ARG             5
           5450 LOAD_CONST            1412 ('jcptptnztjtczgin')
           5452 EXTENDED_ARG             5
           5454 LOAD_CONST            1413 ('sfslwzsttdrouqmi')
           5456 EXTENDED_ARG             5
           5458 LOAD_CONST            1414 ('oprcoelsndlnehzv')
           5460 EXTENDED_ARG             5
           5462 LOAD_CONST            1415 ('cfmhxjwgozohudcf')
           5464 EXTENDED_ARG             5
           5466 LOAD_CONST            1416 ('mhxzekxwbbccbumx')
           5468 EXTENDED_ARG             5
           5470 LOAD_CONST            1417 ('qeqyvhpujfgrmiop')
           5472 EXTENDED_ARG             5
           5474 LOAD_CONST            1418 ('gtqtcpovarcorjrf')
           5476 EXTENDED_ARG             5
           5478 LOAD_CONST            1419 ('aloszdzbbywgchfd')
           5480 EXTENDED_ARG             5
           5482 LOAD_CONST            1420 ('dknbhpmmjnuehczn')
           5484 EXTENDED_ARG             5
           5486 LOAD_CONST            1421 ('ebkeuntykvvfywib')
           5488 EXTENDED_ARG             5
           5490 LOAD_CONST            1422 ('nlgiglojmpbxhafl')
           5492 EXTENDED_ARG             5
           5494 LOAD_CONST            1423 ('uswobtqjlbukbjdo')
           5496 EXTENDED_ARG             5
           5498 LOAD_CONST            1424 ('deinrxindafjewms')
           5500 EXTENDED_ARG             5
           5502 LOAD_CONST            1425 ('bgkkntzoayoycmii')
           5504 EXTENDED_ARG             5
           5506 LOAD_CONST            1426 ('ibgusyotlezfhixr')
           5508 EXTENDED_ARG             5
           5510 LOAD_CONST            1427 ('jhduofjmetuvulfv')
           5512 EXTENDED_ARG             5
           5514 LOAD_CONST            1428 ('ncomoknshtsctgif')
           5516 EXTENDED_ARG             5
           5518 LOAD_CONST            1429 ('oeqgwqzgiuxzwnbo')
           5520 EXTENDED_ARG             5
           5522 LOAD_CONST            1430 ('kfqhheuvmfwtbokw')
           5524 EXTENDED_ARG             5
           5526 LOAD_CONST            1431 ('iqsoqygphhfktibu')
           5528 EXTENDED_ARG             5
           5530 LOAD_CONST            1432 ('bobacxbmnfzanumt')
           5532 EXTENDED_ARG             5
           5534 LOAD_CONST            1433 ('knnwtzpjwzujuuxw')
           5536 EXTENDED_ARG             5
           5538 LOAD_CONST            1434 ('vfnlobdgwymhcgun')
           5540 EXTENDED_ARG             5
           5542 LOAD_CONST            1435 ('gsvqncqugmzlvkcc')
           5544 EXTENDED_ARG             5
           5546 LOAD_CONST            1436 ('fqnfjzhlmmsjzvxx')
           5548 EXTENDED_ARG             5
           5550 LOAD_CONST            1437 ('isynioqvlkzdhldw')
           5552 EXTENDED_ARG             5
           5554 LOAD_CONST            1438 ('ysyenabcioynjgrzo')
           5556 EXTENDED_ARG             5
           5558 LOAD_CONST            1439 ('mgarisubmmtmxaqu')
           5560 EXTENDED_ARG             5
           5562 LOAD_CONST            1440 ('tlkplxdwjvivozqu')
           5564 EXTENDED_ARG             5
           5566 LOAD_CONST            1441 ('uumvkpkfqckauzpy')
           5568 EXTENDED_ARG             5
           5570 LOAD_CONST            1442 ('jqzzndmsdwuznmii')
           5572 EXTENDED_ARG             5
           5574 LOAD_CONST            1443 ('cqqaephdukcklkkh')
           5576 EXTENDED_ARG             5
           5578 LOAD_CONST            1444 ('arqsbqajtlzbxspv')
           5580 EXTENDED_ARG             5
           5582 LOAD_CONST            1445 ('fpwnogjkszhusmqn')
           5584 EXTENDED_ARG             5
           5586 LOAD_CONST            1446 ('arkauhwcnzyhgzgp')
           5588 EXTENDED_ARG             5
           5590 LOAD_CONST            1447 ('mmlbhlqmmpxdsjpr')
           5592 EXTENDED_ARG             5
           5594 LOAD_CONST            1448 ('hxsyiwgylwvfxvqf')
           5596 EXTENDED_ARG             5
           5598 LOAD_CONST            1449 ('fmgsmcxhczkblvrr')
           5600 EXTENDED_ARG             5
           5602 LOAD_CONST            1450 ('jfsbaiqqmrcqziyh')
           5604 EXTENDED_ARG             5
           5606 LOAD_CONST            1451 ('yonriirnykgcqqoa')
           5608 EXTENDED_ARG             5
           5610 LOAD_CONST            1452 ('loqnbxhvnqhefnzc')
           5612 EXTENDED_ARG             5
           5614 LOAD_CONST            1453 ('vnrwfrtawnjzmzpr')
           5616 EXTENDED_ARG             5
           5618 LOAD_CONST            1454 ('nwvmixbdevbawgcb')
           5620 EXTENDED_ARG             5
           5622 LOAD_CONST            1455 ('ssoscjougdkdgwzy')
           5624 EXTENDED_ARG             5
           5626 LOAD_CONST            1456 ('tdotnfxymskkechy')
           5628 EXTENDED_ARG             5
           5630 LOAD_CONST            1457 ('gdqyqjahcohateim')
           5632 EXTENDED_ARG             5
           5634 LOAD_CONST            1458 ('nmpingpzculglnzq')
           5636 EXTENDED_ARG             5
           5638 LOAD_CONST            1459 ('oshxfncaghkzfflo')
           5640 EXTENDED_ARG             5
           5642 LOAD_CONST            1460 ('brqucwymtbtbpkmg')
           5644 EXTENDED_ARG             5
           5646 LOAD_CONST            1461 ('dlbolallmawftyne')
           5648 EXTENDED_ARG             5
           5650 LOAD_CONST            1462 ('zaygaqdomkdndypz')
           5652 EXTENDED_ARG             5
           5654 LOAD_CONST            1463 ('frynwfgjeyczjiyj')
           5656 EXTENDED_ARG             5
           5658 LOAD_CONST            1464 ('fkrmnqytsxookgtf')
           5660 EXTENDED_ARG             5
           5662 LOAD_CONST            1465 ('ztsuspdffprgefji')
           5664 EXTENDED_ARG             5
           5666 LOAD_CONST            1466 ('urmvtcqxbzqlfenp')
           5668 EXTENDED_ARG             5
           5670 LOAD_CONST            1467 ('jtqnervrgeqgltma')
           5672 EXTENDED_ARG             5
           5674 LOAD_CONST            1468 ('mxazffkgorgqvasd')
           5676 EXTENDED_ARG             5
           5678 LOAD_CONST            1469 ('ohxmmsvrbcbakvtz')
           5680 EXTENDED_ARG             5
           5682 LOAD_CONST            1470 ('gvgbadnzvabrkajj')
           5684 EXTENDED_ARG             5
           5686 LOAD_CONST            1471 ('ytxszlngumxdrxgs')
           5688 EXTENDED_ARG             5
           5690 LOAD_CONST            1472 ('uyrufyweypbkrbcg')
           5692 EXTENDED_ARG             5
           5694 LOAD_CONST            1473 ('ylelxbcmvwdqlsst')
           5696 EXTENDED_ARG             5
           5698 LOAD_CONST            1474 ('fnqgyqxovwwitolz')
           5700 EXTENDED_ARG             5
           5702 LOAD_CONST            1475 ('nmrqcgovdmaregoh')
           5704 EXTENDED_ARG             5
           5706 LOAD_CONST            1476 ('jabcyxscsxpdwhduv')
           5708 EXTENDED_ARG             5
           5710 LOAD_CONST            1477 ('agyjbfjdrxsdxcbz')
           5712 EXTENDED_ARG             5
           5714 LOAD_CONST            1478 ('rsxthmvbbfsbapza')
           5716 EXTENDED_ARG             5
           5718 LOAD_CONST            1479 ('bnulsywwhvtckkmm')
           5720 EXTENDED_ARG             5
           5722 LOAD_CONST            1480 ('oetgshifgdhknjen')
           5724 EXTENDED_ARG             5
           5726 LOAD_CONST            1481 ('fdacdxgrjnfqhbgl')
           5728 EXTENDED_ARG             5
           5730 LOAD_CONST            1482 ('ltrpuqvqvaaijmix')
           5732 EXTENDED_ARG             5
           5734 LOAD_CONST            1483 ('aalhlxvddlhxsyev')
           5736 EXTENDED_ARG             5
           5738 LOAD_CONST            1484 ('qubggjexevkjzapf')
           5740 EXTENDED_ARG             5
           5742 LOAD_CONST            1485 ('qffkqkgvbxyrncum')
           5744 EXTENDED_ARG             5
           5746 LOAD_CONST            1486 ('ouebeyqrrbwluaiu')
           5748 EXTENDED_ARG             5
           5750 LOAD_CONST            1487 ('bsmvockhhfxdvwnn')
           5752 EXTENDED_ARG             5
           5754 LOAD_CONST            1488 ('wzyrusboriskzetg')
           5756 EXTENDED_ARG             5
           5758 LOAD_CONST            1489 ('qtkohvlnoxldzkhe')
           5760 EXTENDED_ARG             5
           5762 LOAD_CONST            1490 ('sknqielwtnmdozdk')
           5764 EXTENDED_ARG             5
           5766 LOAD_CONST            1491 ('hueabhcqpsziqofs')
           5768 EXTENDED_ARG             5
           5770 LOAD_CONST            1492 ('qvdcptldvpyzwbwt')
           5772 EXTENDED_ARG             5
           5774 LOAD_CONST            1493 ('gmcsgkgfgdzvdywo')
           5776 EXTENDED_ARG             5
           5778 LOAD_CONST            1494 ('whcybgsdsunkkpqd')
           5780 EXTENDED_ARG             5
           5782 LOAD_CONST            1495 ('zouenychsloywadi')
           5784 EXTENDED_ARG             5
           5786 LOAD_CONST            1496 ('ofnixothejurjqwx')
           5788 EXTENDED_ARG             5
           5790 LOAD_CONST            1497 ('baurihhbpsuzaxdz')
           5792 EXTENDED_ARG             5
           5794 LOAD_CONST            1498 ('odnxgsawwegaqqsk')
           5796 EXTENDED_ARG             5
           5798 LOAD_CONST            1499 ('avnvjxfrofflpnfl')
           5800 EXTENDED_ARG             5
           5802 LOAD_CONST            1500 ('fpeejbcasyuuirri')
           5804 EXTENDED_ARG             5
           5806 LOAD_CONST            1501 ('lnqcckixeovoabad')
           5808 EXTENDED_ARG             5
           5810 LOAD_CONST            1502 ('ogzfwbnpmoqzdxqb')
           5812 EXTENDED_ARG             5
           5814 LOAD_CONST            1503 ('lsfpkmktczfkgase')
           5816 EXTENDED_ARG             5
           5818 LOAD_CONST            1504 ('ckfkwbmenshnuzrk')
           5820 EXTENDED_ARG             5
           5822 LOAD_CONST            1505 ('puuxkxfbbtdttkec')
           5824 EXTENDED_ARG             5
           5826 LOAD_CONST            1506 ('oxplgbgxocgwayuc')
           5828 EXTENDED_ARG             5
           5830 LOAD_CONST            1507 ('tgxfplgbhcjubdtg')
           5832 EXTENDED_ARG             5
           5834 LOAD_CONST            1508 ('cpcwhsckcdfhbwmp')
           5836 EXTENDED_ARG             5
           5838 LOAD_CONST            1509 ('huaukdwwqenjsnbr')
           5840 EXTENDED_ARG             5
           5842 LOAD_CONST            1510 ('hvofxghsjlfhswhp')
           5844 EXTENDED_ARG             5
           5846 LOAD_CONST            1511 ('vnwbsvtnpfpwatiw')
           5848 EXTENDED_ARG             5
           5850 LOAD_CONST            1512 ('mcbkpsbgywhqxsix')
           5852 EXTENDED_ARG             5
           5854 LOAD_CONST            1513 ('zksceqawvnemisil')
           5856 EXTENDED_ARG             5
           5858 LOAD_CONST            1514 ('ojpmvjelrldcqflk')
           5860 EXTENDED_ARG             5
           5862 LOAD_CONST            1515 ('ppfxcvjrjywbkaci')
           5864 EXTENDED_ARG             5
           5866 LOAD_CONST            1516 ('vkkkabrzumejtwdr')
           5868 EXTENDED_ARG             5
           5870 LOAD_CONST            1517 ('jzzvegddqgtogyel')
           5872 EXTENDED_ARG             5
           5874 LOAD_CONST            1518 ('fvwxxwbukfrbazxg')
           5876 EXTENDED_ARG             5
           5878 LOAD_CONST            1519 ('rpvgsjrcsunopqja')
           5880 EXTENDED_ARG             5
           5882 LOAD_CONST            1520 ('ngjxvxsqxcboieeo')
           5884 EXTENDED_ARG             5
           5886 LOAD_CONST            1521 ('xgrdakguxugvngjr')
           5888 EXTENDED_ARG             5
           5890 LOAD_CONST            1522 ('zlixckrlsfjnvwiw')
           5892 EXTENDED_ARG             5
           5894 LOAD_CONST            1523 ('kqqahdzvaovwrarw')
           5896 EXTENDED_ARG             5
           5898 LOAD_CONST            1524 ('zeqmlrqvcymohkfc')
           5900 EXTENDED_ARG             5
           5902 LOAD_CONST            1525 ('fkdmammoniaqeaei')
           5904 EXTENDED_ARG             5
           5906 LOAD_CONST            1526 ('ktrvrgxstgvttftq')
           5908 EXTENDED_ARG             5
           5910 LOAD_CONST            1527 ('skujpfmasgqboljm')
           5912 EXTENDED_ARG             5
           5914 LOAD_CONST            1528 ('ydenwjcdlcdtodqp')
           5916 EXTENDED_ARG             5
           5918 LOAD_CONST            1529 ('hgsuqywmnwmyfotr')
           5920 EXTENDED_ARG             5
           5922 LOAD_CONST            1530 ('waufauuijgxaqceu')
           5924 EXTENDED_ARG             5
           5926 LOAD_CONST            1531 ('gbudfydfhbvoamth')
           5928 EXTENDED_ARG             5
           5930 LOAD_CONST            1532 ('afskwqlszmvafeqm')
           5932 EXTENDED_ARG             5
           5934 LOAD_CONST            1533 ('nbsjuuyfqbhqajok')
           5936 EXTENDED_ARG             5
           5938 LOAD_CONST            1534 ('iiawyxcdikosbwsx')
           5940 EXTENDED_ARG             5
           5942 LOAD_CONST            1535 ('kgqvvxhnmswfngde')
           5944 EXTENDED_ARG             6
           5946 LOAD_CONST            1536 ('icqcdxpedlxpvgms')
           5948 EXTENDED_ARG             6
           5950 LOAD_CONST            1537 ('wpxzbdlhhvarycks')
           5952 EXTENDED_ARG             6
           5954 LOAD_CONST            1538 ('wkwdjgkzzrmuhuol')
           5956 EXTENDED_ARG             6
           5958 LOAD_CONST            1539 ('swsgbdcrbhqhfcci')
           5960 EXTENDED_ARG             6
           5962 LOAD_CONST            1540 ('kgmkgeiryynvhwah')
           5964 EXTENDED_ARG             6
           5966 LOAD_CONST            1541 ('cmpvksdyjvmbdfhj')
           5968 EXTENDED_ARG             6
           5970 LOAD_CONST            1542 ('uglxrzjgijfcvhbx')
           5972 EXTENDED_ARG             6
           5974 LOAD_CONST            1543 ('bgevfvpmocxgausz')
           5976 EXTENDED_ARG             6
           5978 LOAD_CONST            1544 ('uqojyggipoyuwkby')
           5980 EXTENDED_ARG             6
           5982 LOAD_CONST            1545 ('avlnovzpuzubuuss')
           5984 EXTENDED_ARG             6
           5986 LOAD_CONST            1546 ('eyghurrorndubcsm')
           5988 EXTENDED_ARG             6
           5990 LOAD_CONST            1547 ('zdnntbwcugnykdti')
           5992 EXTENDED_ARG             6
           5994 LOAD_CONST            1548 ('lchrlndexvovoznd')
           5996 EXTENDED_ARG             6
           5998 LOAD_CONST            1549 ('cpnizzfmpzinymlk')
           6000 EXTENDED_ARG             6
           6002 LOAD_CONST            1550 ('hskvkurwexwqasxt')
           6004 EXTENDED_ARG             6
           6006 LOAD_CONST            1551 ('xprysdqnfmvifwjy')
           6008 EXTENDED_ARG             6
           6010 LOAD_CONST            1552 ('ngzdbejzpatoixnp')
           6012 EXTENDED_ARG             6
           6014 LOAD_CONST            1553 ('zxomsbqlfuhemazl')
           6016 EXTENDED_ARG             6
           6018 LOAD_CONST            1554 ('iqvuegauwclhvqma')
           6020 EXTENDED_ARG             6
           6022 LOAD_CONST            1555 ('tzdgvyptuayjvktt')
           6024 EXTENDED_ARG             6
           6026 LOAD_CONST            1556 ('zvhbvljserqbcbir')
           6028 EXTENDED_ARG             6
           6030 LOAD_CONST            1557 ('mukwzypdxlegwipe')
           6032 EXTENDED_ARG             6
           6034 LOAD_CONST            1558 ('uslhhogibvwqzhyz')
           6036 EXTENDED_ARG             6
           6038 LOAD_CONST            1559 ('rylrlapnfsdogovl')
           6040 EXTENDED_ARG             6
           6042 LOAD_CONST            1560 ('impmhoqumkogchoq')
           6044 EXTENDED_ARG             6
           6046 LOAD_CONST            1561 ('zarlqxhzfwhqjsms')
           6048 EXTENDED_ARG             6
           6050 LOAD_CONST            1562 ('ymxpexvboiwzkomy')
           6052 EXTENDED_ARG             6
           6054 LOAD_CONST            1563 ('nhgexfzvunjnosgb')
           6056 EXTENDED_ARG             6
           6058 LOAD_CONST            1564 ('wslojqmvusvumclp')
           6060 EXTENDED_ARG             6
           6062 LOAD_CONST            1565 ('uufkkyrchehmokjr')
           6064 EXTENDED_ARG             6
           6066 LOAD_CONST            1566 ('uadbebqfwaewmzdk')
           6068 EXTENDED_ARG             6
           6070 LOAD_CONST            1567 ('wwzazyhamqhdwjzc')
           6072 EXTENDED_ARG             6
           6074 LOAD_CONST            1568 ('yrwrqxhvmzfeiqpa')
           6076 EXTENDED_ARG             6
           6078 LOAD_CONST            1569 ('gycblakmiqqoioke')
           6080 EXTENDED_ARG             6
           6082 LOAD_CONST            1570 ('gpyfmbzhhhtuysyf')
           6084 EXTENDED_ARG             6
           6086 LOAD_CONST            1571 ('agtyhlalmwzmpnes')
           6088 EXTENDED_ARG             6
           6090 LOAD_CONST            1572 ('jhbfquwnkzzmmrqg')
           6092 EXTENDED_ARG             6
           6094 LOAD_CONST            1573 ('xahekbixkfaidgkb')
           6096 EXTENDED_ARG             6
           6098 LOAD_CONST            1574 ('njiajqrymsbxsfyj')
           6100 EXTENDED_ARG             6
           6102 LOAD_CONST            1575 ('xrhkzoerfwjjjvyv')
           6104 EXTENDED_ARG             6
           6106 LOAD_CONST            1576 ('mojaewgjwmmxmmcj')
           6108 EXTENDED_ARG             6
           6110 LOAD_CONST            1577 ('mcimexhcqqptnotx')
           6112 EXTENDED_ARG             6
           6114 LOAD_CONST            1578 ('lshefqasobmbuxdd')
           6116 EXTENDED_ARG             6
           6118 LOAD_CONST            1579 ('srgglcluxgheudmy')
           6120 EXTENDED_ARG             6
           6122 LOAD_CONST            1580 ('cgxocmkqzjagwgmm')
           6124 EXTENDED_ARG             6
           6126 LOAD_CONST            1581 ('iyreabcwxbnkpsjoa')
           6128 EXTENDED_ARG             6
           6130 LOAD_CONST            1582 ('zaljaqjvfvvqdays')
           6132 EXTENDED_ARG             6
           6134 LOAD_CONST            1583 ('gskeygtjgbijvkjn')
           6136 EXTENDED_ARG             6
           6138 LOAD_CONST            1584 ('smpslnyxjvbhjyvh')
           6140 EXTENDED_ARG             6
           6142 LOAD_CONST            1585 ('raeaxhedueaayvlp')
           6144 EXTENDED_ARG             6
           6146 LOAD_CONST            1586 ('vbzqcqhzdaptsdts')
           6148 EXTENDED_ARG             6
           6150 LOAD_CONST            1587 ('enurfjqxyapakpyu')
           6152 EXTENDED_ARG             6
           6154 LOAD_CONST            1588 ('xesnqtvzlkjudkgx')
           6156 EXTENDED_ARG             6
           6158 LOAD_CONST            1589 ('kjwfyrasqtafiyri')
           6160 EXTENDED_ARG             6
           6162 LOAD_CONST            1590 ('bsbavcxzjuaksbld')
           6164 EXTENDED_ARG             6
           6166 LOAD_CONST            1591 ('hstmbonbgsleppae')
           6168 EXTENDED_ARG             6
           6170 LOAD_CONST            1592 ('exyhezlohmqkhxlr')
           6172 EXTENDED_ARG             6
           6174 LOAD_CONST            1593 ('rqmhckbvtfyqwsxh')
           6176 EXTENDED_ARG             6
           6178 LOAD_CONST            1594 ('wfnvwsffbdliqsll')
           6180 EXTENDED_ARG             6
           6182 LOAD_CONST            1595 ('eaqnrvadjaojgfsm')
           6184 EXTENDED_ARG             6
           6186 LOAD_CONST            1596 ('rhocxroqdqrervjn')
           6188 EXTENDED_ARG             6
           6190 LOAD_CONST            1597 ('mzdczcvbrhjwcdve')
           6192 EXTENDED_ARG             6
           6194 LOAD_CONST            1598 ('yxlrftymqxqtbvso')
           6196 EXTENDED_ARG             6
           6198 LOAD_CONST            1599 ('baunrbrfzrapqzit')
           6200 EXTENDED_ARG             6
           6202 LOAD_CONST            1600 ('oipmrdynelruxvry')
           6204 EXTENDED_ARG             6
           6206 LOAD_CONST            1601 ('khppolojdkojxwqv')
           6208 EXTENDED_ARG             6
           6210 LOAD_CONST            1602 ('umwgrzharatzdqjb')
           6212 EXTENDED_ARG             6
           6214 LOAD_CONST            1603 ('jbabfxajhdducgsw')
           6216 EXTENDED_ARG             6
           6218 LOAD_CONST            1604 ('ohtxxfqthypvhbca')
           6220 EXTENDED_ARG             6
           6222 LOAD_CONST            1605 ('knwjiwadhywkwlsz')
           6224 EXTENDED_ARG             6
           6226 LOAD_CONST            1606 ('qteikhwuuasdyvpn')
           6228 EXTENDED_ARG             6
           6230 LOAD_CONST            1607 ('ytdeibtvnlysssfj')
           6232 EXTENDED_ARG             6
           6234 LOAD_CONST            1608 ('bdcflvlghfonjfik')
           6236 EXTENDED_ARG             6
           6238 LOAD_CONST            1609 ('eactaiaqtgrhwkbn')
           6240 EXTENDED_ARG             6
           6242 LOAD_CONST            1610 ('evfodntmumnmpltz')
           6244 EXTENDED_ARG             6
           6246 LOAD_CONST            1611 ('zklhlzjiueabafnz')
           6248 EXTENDED_ARG             6
           6250 LOAD_CONST            1612 ('zrsbbgkjcseqeang')
           6252 EXTENDED_ARG             6
           6254 LOAD_CONST            1613 ('cbvthkbgywxvjkhh')
           6256 EXTENDED_ARG             6
           6258 LOAD_CONST            1614 ('gykehthvmdzklzmm')
           6260 EXTENDED_ARG             6
           6262 LOAD_CONST            1615 ('bhrydwsdwtqaxyhu')
           6264 EXTENDED_ARG             6
           6266 LOAD_CONST            1616 ('abchczaihcevacgzx')
           6268 EXTENDED_ARG             6
           6270 LOAD_CONST            1617 ('yonhiezjoqwosrwx')
           6272 EXTENDED_ARG             6
           6274 LOAD_CONST            1618 ('lpwsvvjbtimkqkaz')
           6276 EXTENDED_ARG             6
           6278 LOAD_CONST            1619 ('tibcufriphwxwzhj')
           6280 EXTENDED_ARG             6
           6282 LOAD_CONST            1620 ('kqxnnvmxdyubsyma')
           6284 EXTENDED_ARG             6
           6286 LOAD_CONST            1621 ('jdjdalrfdvtzjzzf')
           6288 EXTENDED_ARG             6
           6290 LOAD_CONST            1622 ('qzijzvthlydyayby')
           6292 EXTENDED_ARG             6
           6294 LOAD_CONST            1623 ('xsmhbxalbihmkgmr')
           6296 EXTENDED_ARG             6
           6298 LOAD_CONST            1624 ('ickheeqdhkhfvagy')
           6300 EXTENDED_ARG             6
           6302 LOAD_CONST            1625 ('zgancfyzdspdikye')
           6304 EXTENDED_ARG             6
           6306 LOAD_CONST            1626 ('rglysjgxdhtlirpe')
           6308 EXTENDED_ARG             6
           6310 LOAD_CONST            1627 ('xwmvbwnbknuynzms')
           6312 EXTENDED_ARG             6
           6314 LOAD_CONST            1628 ('rtggytyubuthyvdu')
           6316 EXTENDED_ARG             6
           6318 LOAD_CONST            1629 ('hjfqzmmiqdopyduc')
           6320 EXTENDED_ARG             6
           6322 LOAD_CONST            1630 ('yyeixxunfkstmdly')
           6324 EXTENDED_ARG             6
           6326 LOAD_CONST            1631 ('stccdhodaeauqskv')
           6328 EXTENDED_ARG             6
           6330 LOAD_CONST            1632 ('bsemgaskpcgvmcgd')
           6332 EXTENDED_ARG             6
           6334 LOAD_CONST            1633 ('todqxrxzpksoowqy')
           6336 EXTENDED_ARG             6
           6338 LOAD_CONST            1634 ('wqpfgvkppuehavdx')
           6340 EXTENDED_ARG             6
           6342 LOAD_CONST            1635 ('oecawvidnbencfzv')
           6344 EXTENDED_ARG             6
           6346 LOAD_CONST            1636 ('ocpbksbgdutggshn')
           6348 EXTENDED_ARG             6
           6350 LOAD_CONST            1637 ('hvfvfvhuwftqdtys')
           6352 EXTENDED_ARG             6
           6354 LOAD_CONST            1638 ('raqymywkbzpjsomo')
           6356 EXTENDED_ARG             6
           6358 LOAD_CONST            1639 ('mnsgyltrdguifeom')
           6360 EXTENDED_ARG             6
           6362 LOAD_CONST            1640 ('zrtwkfvmrxgmebpc')
           6364 EXTENDED_ARG             6
           6366 LOAD_CONST            1641 ('esnlddvhmlycfnzm')
           6368 EXTENDED_ARG             6
           6370 LOAD_CONST            1642 ('ujmrrippyxxaitjd')
           6372 EXTENDED_ARG             6
           6374 LOAD_CONST            1643 ('cjqopvqjmwdwrhtc')
           6376 EXTENDED_ARG             6
           6378 LOAD_CONST            1644 ('axterdjcgvvkvjmt')
           6380 EXTENDED_ARG             6
           6382 LOAD_CONST            1645 ('wsfjhyhiwcskrnzl')
           6384 EXTENDED_ARG             6
           6386 LOAD_CONST            1646 ('excxprrgtvsdstkq')
           6388 EXTENDED_ARG             6
           6390 LOAD_CONST            1647 ('bqpvnpcbqbjeorfs')
           6392 EXTENDED_ARG             6
           6394 LOAD_CONST            1648 ('zgrbyxqcahdirxzz')
           6396 EXTENDED_ARG             6
           6398 LOAD_CONST            1649 ('ibruhcuhiwpsndjo')
           6400 EXTENDED_ARG             6
           6402 LOAD_CONST            1650 ('dmningijzetvgssq')
           6404 EXTENDED_ARG             6
           6406 LOAD_CONST            1651 ('vsbnskosiigyjwhd')
           6408 EXTENDED_ARG             6
           6410 LOAD_CONST            1652 ('gvbexrsmzefdfjra')
           6412 EXTENDED_ARG             6
           6414 LOAD_CONST            1653 ('rnjdwommvluzgmiw')
           6416 EXTENDED_ARG             6
           6418 LOAD_CONST            1654 ('qfnpnioafynmfnch')
           6420 EXTENDED_ARG             6
           6422 LOAD_CONST            1655 ('iutdykdyrnjbijim')
           6424 EXTENDED_ARG             6
           6426 LOAD_CONST            1656 ('yybpzynyyvqsibqw')
           6428 EXTENDED_ARG             6
           6430 LOAD_CONST            1657 ('ukcumxubdajklbow')
           6432 EXTENDED_ARG             6
           6434 LOAD_CONST            1658 ('qpfhjabesozcqxnt')
           6436 EXTENDED_ARG             6
           6438 LOAD_CONST            1659 ('ogpjowmcxjvltaei')
           6440 EXTENDED_ARG             6
           6442 LOAD_CONST            1660 ('nmmgxxpblhyvjcza')
           6444 EXTENDED_ARG             6
           6446 LOAD_CONST            1661 ('rsdicjpuitrhjhoo')
           6448 EXTENDED_ARG             6
           6450 LOAD_CONST            1662 ('rougghrsdcuhaxkb')
           6452 EXTENDED_ARG             6
           6454 LOAD_CONST            1663 ('ccoubobkldovhdha')
           6456 EXTENDED_ARG             6
           6458 LOAD_CONST            1664 ('heeysansiaiqecsy')
           6460 EXTENDED_ARG             6
           6462 LOAD_CONST            1665 ('txyzgixqzbqoyddo')
           6464 EXTENDED_ARG             6
           6466 LOAD_CONST            1666 ('zgonqkaonzusldmu')
           6468 EXTENDED_ARG             6
           6470 LOAD_CONST            1667 ('ksvocdxauzvzaqej')
           6472 EXTENDED_ARG             6
           6474 LOAD_CONST            1668 ('tthfhimluvparxna')
           6476 EXTENDED_ARG             6
           6478 LOAD_CONST            1669 ('jrfaqfteargbowaq')
           6480 EXTENDED_ARG             6
           6482 LOAD_CONST            1670 ('vwgdxfzukfkbwmoi')
           6484 EXTENDED_ARG             6
           6486 LOAD_CONST            1671 ('kxaxverroublhnkg')
           6488 EXTENDED_ARG             6
           6490 LOAD_CONST            1672 ('hxcyocruwhxerkwv')
           6492 EXTENDED_ARG             6
           6494 LOAD_CONST            1673 ('waaywxwtrwpnwcxe')
           6496 EXTENDED_ARG             6
           6498 LOAD_CONST            1674 ('kbrwbedcrxacnfzn')
           6500 EXTENDED_ARG             6
           6502 LOAD_CONST            1675 ('heqhjudnrfmpgffr')
           6504 EXTENDED_ARG             6
           6506 LOAD_CONST            1676 ('zoninmtmgfzwfivy')
           6508 EXTENDED_ARG             6
           6510 LOAD_CONST            1677 ('nhdjsbedakglczfb')
           6512 EXTENDED_ARG             6
           6514 LOAD_CONST            1678 ('eyklkfsriufgdeta')
           6516 EXTENDED_ARG             6
           6518 LOAD_CONST            1679 ('cdtcihvzlfrxcqkk')
           6520 EXTENDED_ARG             6
           6522 LOAD_CONST            1680 ('nszlmuisqibdhuij')
           6524 EXTENDED_ARG             6
           6526 LOAD_CONST            1681 ('frfwwwunnpwouryl')
           6528 EXTENDED_ARG             6
           6530 LOAD_CONST            1682 ('bahmwsfifpehpvlm')
           6532 EXTENDED_ARG             6
           6534 LOAD_CONST            1683 ('xinovuwjryvjderk')
           6536 EXTENDED_ARG             6
           6538 LOAD_CONST            1684 ('stdxirugdjwsxdrf')
           6540 EXTENDED_ARG             6
           6542 LOAD_CONST            1685 ('ukzsodimorlbassb')
           6544 EXTENDED_ARG             6
           6546 LOAD_CONST            1686 ('dcqdmnpirlwetexz')
           6548 EXTENDED_ARG             6
           6550 LOAD_CONST            1687 ('lnkkravbrdzuaixf')
           6552 EXTENDED_ARG             6
           6554 LOAD_CONST            1688 ('iqhikikqgoabcupoz')
           6556 EXTENDED_ARG             6
           6558 LOAD_CONST            1689 ('tqqnskydlxxyeloy')
           6560 EXTENDED_ARG             6
           6562 LOAD_CONST            1690 ('hoqhujloveotexob')
           6564 EXTENDED_ARG             6
           6566 LOAD_CONST            1691 ('tafrmbzoiiyxkrpv')
           6568 EXTENDED_ARG             6
           6570 LOAD_CONST            1692 ('gedftcwddbvqbcbp')
           6572 EXTENDED_ARG             6
           6574 LOAD_CONST            1693 ('tmlvgfxezfqhqlro')
           6576 EXTENDED_ARG             6
           6578 LOAD_CONST            1694 ('omkqddentowyusgs')
           6580 EXTENDED_ARG             6
           6582 LOAD_CONST            1695 ('uvmoywmfgcxprcob')
           6584 EXTENDED_ARG             6
           6586 LOAD_CONST            1696 ('wxaexnkxfscqpbvn')
           6588 EXTENDED_ARG             6
           6590 LOAD_CONST            1697 ('arouwkkwzmpxcraq')
           6592 EXTENDED_ARG             6
           6594 LOAD_CONST            1698 ('oshuiowfgoxvscum')
           6596 EXTENDED_ARG             6
           6598 LOAD_CONST            1699 ('wlcbjlvtpwbizxkk')
           6600 EXTENDED_ARG             6
           6602 LOAD_CONST            1700 ('pqdqfcardhablnlm')
           6604 EXTENDED_ARG             6
           6606 LOAD_CONST            1701 ('hncftotfykwkmcwc')
           6608 EXTENDED_ARG             6
           6610 LOAD_CONST            1702 ('ilbkfisyjvqmmjox')
           6612 EXTENDED_ARG             6
           6614 LOAD_CONST            1703 ('mjziuevwvgazkmrr')
           6616 EXTENDED_ARG             6
           6618 LOAD_CONST            1704 ('qxftpuleqzgeoxkn')
           6620 EXTENDED_ARG             6
           6622 LOAD_CONST            1705 ('qwfbcoulervauwzy')
           6624 EXTENDED_ARG             6
           6626 LOAD_CONST            1706 ('hzzahmyatnakmfkm')
           6628 EXTENDED_ARG             6
           6630 LOAD_CONST            1707 ('atlkeburbqttzgdv')
           6632 EXTENDED_ARG             6
           6634 LOAD_CONST            1708 ('chctjbylvaqivhnu')
           6636 EXTENDED_ARG             6
           6638 LOAD_CONST            1709 ('kljxzdlufmjsakrn')
           6640 EXTENDED_ARG             6
           6642 LOAD_CONST            1710 ('ldqznwrdmigxmplj')
           6644 EXTENDED_ARG             6
           6646 LOAD_CONST            1711 ('jnzsugujwghliiyj')
           6648 EXTENDED_ARG             6
           6650 LOAD_CONST            1712 ('davvfzptwjezrtut')
           6652 EXTENDED_ARG             6
           6654 LOAD_CONST            1713 ('ayvxlihyfxjghbnj')
           6656 EXTENDED_ARG             6
           6658 LOAD_CONST            1714 ('damnybtgbouyhgvm')
           6660 EXTENDED_ARG             6
           6662 LOAD_CONST            1715 ('xycclwykeleqgqbz')
           6664 EXTENDED_ARG             6
           6666 LOAD_CONST            1716 ('xcexkuimhauveeep')
           6668 EXTENDED_ARG             6
           6670 LOAD_CONST            1717 ('alawhglfqmrpujdu')
           6672 EXTENDED_ARG             6
           6674 LOAD_CONST            1718 ('ucqkzhnxzfmhrscm')
           6676 EXTENDED_ARG             6
           6678 LOAD_CONST            1719 ('giqfhrubpvulkbcz')
           6680 EXTENDED_ARG             6
           6682 LOAD_CONST            1720 ('ibjyvrczdfvorhxe')
           6684 EXTENDED_ARG             6
           6686 LOAD_CONST            1721 ('qbwwxgvtphqitwrc')
           6688 EXTENDED_ARG             6
           6690 LOAD_CONST            1722 ('nznctodxeivfdauc')
           6692 EXTENDED_ARG             6
           6694 LOAD_CONST            1723 ('gcelouuuaxwxmvsw')
           6696 EXTENDED_ARG             6
           6698 LOAD_CONST            1724 ('rqelrfgexnkdnazl')
           6700 EXTENDED_ARG             6
           6702 LOAD_CONST            1725 ('fbepvxtrhujvrdfc')
           6704 EXTENDED_ARG             6
           6706 LOAD_CONST            1726 ('iczbfakdstudncnv')
           6708 EXTENDED_ARG             6
           6710 LOAD_CONST            1727 ('qwyjcjokwchroxbr')
           6712 EXTENDED_ARG             6
           6714 LOAD_CONST            1728 ('ycjrzaetiivrrdkc')
           6716 EXTENDED_ARG             6
           6718 LOAD_CONST            1729 ('hjaflkntduxbssgu')
           6720 EXTENDED_ARG             6
           6722 LOAD_CONST            1730 ('rwfrleciyxwvxygj')
           6724 EXTENDED_ARG             6
           6726 LOAD_CONST            1731 ('pfkodbjvlrgvryzh')
           6728 EXTENDED_ARG             6
           6730 LOAD_CONST            1732 ('fyvawqjluonvjjxc')
           6732 EXTENDED_ARG             6
           6734 LOAD_CONST            1733 ('nzkedkvundnsfmnm')
           6736 EXTENDED_ARG             6
           6738 LOAD_CONST            1734 ('zkvlbpsldcyafkpj')
           6740 EXTENDED_ARG             6
           6742 LOAD_CONST            1735 ('hrnjhejkhdkcmnmh')
           6744 EXTENDED_ARG             6
           6746 LOAD_CONST            1736 ('sydwdkxfjjkvvbfk')
           6748 EXTENDED_ARG             6
           6750 LOAD_CONST            1737 ('ydznqbenlyrstgmu')
           6752 EXTENDED_ARG             6
           6754 LOAD_CONST            1738 ('katzotudzcpwwvkb')
           6756 EXTENDED_ARG             6
           6758 LOAD_CONST            1739 ('xucadxwemqvixtva')
           6760 EXTENDED_ARG             6
           6762 LOAD_CONST            1740 ('nnbzlmlmesntwwhh')
           6764 EXTENDED_ARG             6
           6766 LOAD_CONST            1741 ('sidmvrqryepebkda')
           6768 EXTENDED_ARG             6
           6770 LOAD_CONST            1742 ('zqlfnaleybermqpx')
           6772 EXTENDED_ARG             6
           6774 LOAD_CONST            1743 ('kduaxanohkcebsaj')
           6776 EXTENDED_ARG             6
           6778 LOAD_CONST            1744 ('jajuaudbrkkcnyyq')
           6780 EXTENDED_ARG             6
           6782 LOAD_CONST            1745 ('rhtefiqjirzhpjwt')
           6784 EXTENDED_ARG             6
           6786 LOAD_CONST            1746 ('tgbyhnyxxivxpebp')
           6788 EXTENDED_ARG             6
           6790 LOAD_CONST            1747 ('oqqwgmpqimqnjrxz')
           6792 EXTENDED_ARG             6
           6794 LOAD_CONST            1748 ('tptopmpejaaaxokz')
           6796 EXTENDED_ARG             6
           6798 LOAD_CONST            1749 ('rglhbkxoupbeqxhn')
           6800 EXTENDED_ARG             6
           6802 LOAD_CONST            1750 ('diannxikfirreuin')
           6804 EXTENDED_ARG             6
           6806 LOAD_CONST            1751 ('ilkjfpwdabcorejuk')
           6808 EXTENDED_ARG             6
           6810 LOAD_CONST            1752 ('tzygwhlicpqhsxsm')
           6812 EXTENDED_ARG             6
           6814 LOAD_CONST            1753 ('ednqyfigrhjjsixi')
           6816 EXTENDED_ARG             6
           6818 LOAD_CONST            1754 ('ichtvcqqxhzvwyrk')
           6820 EXTENDED_ARG             6
           6822 LOAD_CONST            1755 ('ckyoxfbufktqznpj')
           6824 EXTENDED_ARG             6
           6826 LOAD_CONST            1756 ('xoskspafepfgeeit')
           6828 EXTENDED_ARG             6
           6830 LOAD_CONST            1757 ('jcbtyhklimaasdfu')
           6832 EXTENDED_ARG             6
           6834 LOAD_CONST            1758 ('cfkabckzjghzapvxx')
           6836 EXTENDED_ARG             6
           6838 LOAD_CONST            1759 ('owdyarpowhkunwhy')
           6840 EXTENDED_ARG             6
           6842 LOAD_CONST            1760 ('etnyrgssgohswpva')
           6844 EXTENDED_ARG             6
           6846 LOAD_CONST            1761 ('ccdzytrxkxrfobiv')
           6848 EXTENDED_ARG             6
           6850 LOAD_CONST            1762 ('vxmwodlmkjmnanqf')
           6852 EXTENDED_ARG             6
           6854 LOAD_CONST            1763 ('lfoyuzoffzuzknom')
           6856 EXTENDED_ARG             6
           6858 LOAD_CONST            1764 ('avpouwwwczpcsixm')
           6860 EXTENDED_ARG             6
           6862 LOAD_CONST            1765 ('befuilgwreabcsjqn')
           6864 EXTENDED_ARG             6
           6866 LOAD_CONST            1766 ('wwlkjupnpinaskti')
           6868 EXTENDED_ARG             6
           6870 LOAD_CONST            1767 ('wuaufrnozwrcwrux')
           6872 EXTENDED_ARG             6
           6874 LOAD_CONST            1768 ('ddmlqscfylvvlqet')
           6876 EXTENDED_ARG             6
           6878 LOAD_CONST            1769 ('ngtehvarjqltinad')
           6880 EXTENDED_ARG             6
           6882 LOAD_CONST            1770 ('hxilufvmpbmybqse')
           6884 EXTENDED_ARG             6
           6886 LOAD_CONST            1771 ('sxckpnkpctadurmj')
           6888 EXTENDED_ARG             6
           6890 LOAD_CONST            1772 ('tkauepahazlgunce')
           6892 EXTENDED_ARG             6
           6894 LOAD_CONST            1773 ('wdnczbubbvaeugur')
           6896 EXTENDED_ARG             6
           6898 LOAD_CONST            1774 ('blbtvambkabhgfmt')
           6900 EXTENDED_ARG             6
           6902 LOAD_CONST            1775 ('hscywaqlqpzmajlw')
           6904 EXTENDED_ARG             6
           6906 LOAD_CONST            1776 ('kqbcyrflffoyrrde')
           6908 EXTENDED_ARG             6
           6910 LOAD_CONST            1777 ('swatgwoezppbhzrz')
           6912 EXTENDED_ARG             6
           6914 LOAD_CONST            1778 ('wncpezwknhwlkyfa')
           6916 EXTENDED_ARG             6
           6918 LOAD_CONST            1779 ('fxoalqugauheullc')
           6920 EXTENDED_ARG             6
           6922 LOAD_CONST            1780 ('yfejaqfwodcbvjxo')
           6924 EXTENDED_ARG             6
           6926 LOAD_CONST            1781 ('srdidycbfudekvry')
           6928 EXTENDED_ARG             6
           6930 LOAD_CONST            1782 ('wbmqrnpsbwvajyst')
           6932 EXTENDED_ARG             6
           6934 LOAD_CONST            1783 ('eojhwvsjkhruoihy')
           6936 EXTENDED_ARG             6
           6938 LOAD_CONST            1784 ('lebgsqpfytyfljzy')
           6940 EXTENDED_ARG             6
           6942 LOAD_CONST            1785 ('nlfrksicpahzoyzs')
           6944 EXTENDED_ARG             6
           6946 LOAD_CONST            1786 ('vwfuihhrcdfzahuq')
           6948 EXTENDED_ARG             6
           6950 LOAD_CONST            1787 ('zxossokxsiilrhwn')
           6952 EXTENDED_ARG             6
           6954 LOAD_CONST            1788 ('nnogzvnyavbajgxg')
           6956 EXTENDED_ARG             6
           6958 LOAD_CONST            1789 ('xudcsovkwdigfykp')
           6960 EXTENDED_ARG             6
           6962 LOAD_CONST            1790 ('oxnernpkebnwtzgk')
           6964 EXTENDED_ARG             6
           6966 LOAD_CONST            1791 ('lpkluymjfczcabbg')
           6968 EXTENDED_ARG             7
           6970 LOAD_CONST            1792 ('xwmoythsnnalagrd')
           6972 EXTENDED_ARG             7
           6974 LOAD_CONST            1793 ('bwxqduzhwponwuxh')
           6976 EXTENDED_ARG             7
           6978 LOAD_CONST            1794 ('tvqujorvigsrzqra')
           6980 EXTENDED_ARG             7
           6982 LOAD_CONST            1795 ('ruhirwfwnudvhndi')
           6984 EXTENDED_ARG             7
           6986 LOAD_CONST            1796 ('yigakwntqrddbxel')
           6988 EXTENDED_ARG             7
           6990 LOAD_CONST            1797 ('doyelkmwfiqrcvwf')
           6992 EXTENDED_ARG             7
           6994 LOAD_CONST            1798 ('nqepgxvwmpczbqmp')
           6996 EXTENDED_ARG             7
           6998 LOAD_CONST            1799 ('euwsrbwhhaosbuxv')
           7000 EXTENDED_ARG             7
           7002 LOAD_CONST            1800 ('qybvertwzftjmsbo')
           7004 EXTENDED_ARG             7
           7006 LOAD_CONST            1801 ('ovrxezhfnplztkrf')
           7008 EXTENDED_ARG             7
           7010 LOAD_CONST            1802 ('zhsklztsgdxqqlos')
           7012 EXTENDED_ARG             7
           7014 LOAD_CONST            1803 ('hjkalxuedegqevxf')
           7016 EXTENDED_ARG             7
           7018 LOAD_CONST            1804 ('acqcmxxnvxiyiarj')
           7020 EXTENDED_ARG             7
           7022 LOAD_CONST            1805 ('irfjxvnxvcwfggyf')
           7024 EXTENDED_ARG             7
           7026 LOAD_CONST            1806 ('ivjlvhotuhyjrbqi')
           7028 EXTENDED_ARG             7
           7030 LOAD_CONST            1807 ('ybowwazfbqnlxhix')
           7032 EXTENDED_ARG             7
           7034 LOAD_CONST            1808 ('rwldwkwiuokthyvd')
           7036 EXTENDED_ARG             7
           7038 LOAD_CONST            1809 ('emeoryhhzmchkcaf')
           7040 EXTENDED_ARG             7
           7042 LOAD_CONST            1810 ('wkjtfktltlxrpodu')
           7044 EXTENDED_ARG             7
           7046 LOAD_CONST            1811 ('zozxqufosbvhvzmk')
           7048 EXTENDED_ARG             7
           7050 LOAD_CONST            1812 ('kejjywawtflpnzxq')
           7052 EXTENDED_ARG             7
           7054 LOAD_CONST            1813 ('tgjqeqqyflstgyfn')
           7056 EXTENDED_ARG             7
           7058 LOAD_CONST            1814 ('edodalhdkbpbvbbi')
           7060 EXTENDED_ARG             7
           7062 LOAD_CONST            1815 ('svvbrdqtivcocuok')
           7064 EXTENDED_ARG             7
           7066 LOAD_CONST            1816 ('jqycfyojmcojaike')
           7068 EXTENDED_ARG             7
           7070 LOAD_CONST            1817 ('uysmgvolzqhvrjcg')
           7072 EXTENDED_ARG             7
           7074 LOAD_CONST            1818 ('jepqutdjnzdxpuis')
           7076 EXTENDED_ARG             7
           7078 LOAD_CONST            1819 ('htypdjotmvugsqrn')
           7080 EXTENDED_ARG             7
           7082 LOAD_CONST            1820 ('ruanlnsslyvcmloa')
           7084 EXTENDED_ARG             7
           7086 LOAD_CONST            1821 ('rmguapshfylrqcyw')
           7088 EXTENDED_ARG             7
           7090 LOAD_CONST            1822 ('idmrozfesprjyydi')
           7092 EXTENDED_ARG             7
           7094 LOAD_CONST            1823 ('igiijxxuaewkngez')
           7096 EXTENDED_ARG             7
           7098 LOAD_CONST            1824 ('mmfbpbxhjbbtaktl')
           7100 EXTENDED_ARG             7
           7102 LOAD_CONST            1825 ('wbryhbistnsnxcre')
           7104 EXTENDED_ARG             7
           7106 LOAD_CONST            1826 ('eyypsgultocxkddt')
           7108 EXTENDED_ARG             7
           7110 LOAD_CONST            1827 ('hmgsapmnlbhkldjy')
           7112 EXTENDED_ARG             7
           7114 LOAD_CONST            1828 ('srdiuczmorzzmqmx')
           7116 EXTENDED_ARG             7
           7118 LOAD_CONST            1829 ('jydlzvjtvssbiriv')
           7120 EXTENDED_ARG             7
           7122 LOAD_CONST            1830 ('xyxlubdngtpamnie')
           7124 EXTENDED_ARG             7
           7126 LOAD_CONST            1831 ('hzxhqmvdfeelavey')
           7128 EXTENDED_ARG             7
           7130 LOAD_CONST            1832 ('dnmkfxoqikbpnncm')
           7132 EXTENDED_ARG             7
           7134 LOAD_CONST            1833 ('uvykqjhcbjrkhwws')
           7136 EXTENDED_ARG             7
           7138 LOAD_CONST            1834 ('hcouhxnefskqtsmj')
           7140 EXTENDED_ARG             7
           7142 LOAD_CONST            1835 ('tlzdfixqvzmpnxey')
           7144 EXTENDED_ARG             7
           7146 LOAD_CONST            1836 ('bqthxadcjbuoihjb')
           7148 EXTENDED_ARG             7
           7150 LOAD_CONST            1837 ('amqcryxqrquugjds')
           7152 EXTENDED_ARG             7
           7154 LOAD_CONST            1838 ('kazopbofkzigbrjf')
           7156 EXTENDED_ARG             7
           7158 LOAD_CONST            1839 ('yoazjvgcjnuynogm')
           7160 EXTENDED_ARG             7
           7162 LOAD_CONST            1840 ('cekiuyvsxvnhllot')
           7164 EXTENDED_ARG             7
           7166 LOAD_CONST            1841 ('skaakenhygficler')
           7168 EXTENDED_ARG             7
           7170 LOAD_CONST            1842 ('vyyblxbztgjdxemi')
           7172 EXTENDED_ARG             7
           7174 LOAD_CONST            1843 ('cwijfnzpasohsysb')
           7176 EXTENDED_ARG             7
           7178 LOAD_CONST            1844 ('vxshtpkflepkegsv')
           7180 EXTENDED_ARG             7
           7182 LOAD_CONST            1845 ('dqlajjejvwkljffm')
           7184 EXTENDED_ARG             7
           7186 LOAD_CONST            1846 ('pdrurythrunegiyt')
           7188 EXTENDED_ARG             7
           7190 LOAD_CONST            1847 ('wyniiprlwdxayecx')
           7192 EXTENDED_ARG             7
           7194 LOAD_CONST            1848 ('onzimmmmwsczxrud')
           7196 EXTENDED_ARG             7
           7198 LOAD_CONST            1849 ('wahjycyykcusbzkh')
           7200 EXTENDED_ARG             7
           7202 LOAD_CONST            1850 ('pmxfomqplrchaeji')
           7204 EXTENDED_ARG             7
           7206 LOAD_CONST            1851 ('cuiofjxjmfwmwjpo')
           7208 EXTENDED_ARG             7
           7210 LOAD_CONST            1852 ('mqeyxhbjjhtyiqax')
           7212 EXTENDED_ARG             7
           7214 LOAD_CONST            1853 ('vxjtwryiiaiqmgxc')
           7216 EXTENDED_ARG             7
           7218 LOAD_CONST            1854 ('rpxhygecrrxsorep')
           7220 EXTENDED_ARG             7
           7222 LOAD_CONST            1855 ('pdhcrtkvutpxkjqk')
           7224 EXTENDED_ARG             7
           7226 LOAD_CONST            1856 ('xghqzhfjrcskksay')
           7228 EXTENDED_ARG             7
           7230 LOAD_CONST            1857 ('llatzvkvpehtkmlp')
           7232 EXTENDED_ARG             7
           7234 LOAD_CONST            1858 ('evcdafiqhelayolh')
           7236 EXTENDED_ARG             7
           7238 LOAD_CONST            1859 ('wnpjllgpnngclefg')
           7240 EXTENDED_ARG             7
           7242 LOAD_CONST            1860 ('cplkciggvoivrdrk')
           7244 EXTENDED_ARG             7
           7246 LOAD_CONST            1861 ('rwzojlohceoksqei')
           7248 EXTENDED_ARG             7
           7250 LOAD_CONST            1862 ('ibblbsqbtieahuip')
           7252 EXTENDED_ARG             7
           7254 LOAD_CONST            1863 ('rxymbuhpxlybbpwj')
           7256 EXTENDED_ARG             7
           7258 LOAD_CONST            1864 ('oufytsooclpjthdt')
           7260 EXTENDED_ARG             7
           7262 LOAD_CONST            1865 ('ladsdwyczkhlprsk')
           7264 EXTENDED_ARG             7
           7266 LOAD_CONST            1866 ('lqglakcncwvhbmdq')
           7268 EXTENDED_ARG             7
           7270 LOAD_CONST            1867 ('pvffqrafetpcnonv')
           7272 EXTENDED_ARG             7
           7274 LOAD_CONST            1868 ('ltxqocyoaqwqlclh')
           7276 EXTENDED_ARG             7
           7278 LOAD_CONST            1869 ('ujleyjgijrzxpohv')
           7280 EXTENDED_ARG             7
           7282 LOAD_CONST            1870 ('hdliszkijxjfdhuz')
           7284 EXTENDED_ARG             7
           7286 LOAD_CONST            1871 ('uerwlwcboltvibyv')
           7288 EXTENDED_ARG             7
           7290 LOAD_CONST            1872 ('frnvgotjrsmsvdrv')
           7292 EXTENDED_ARG             7
           7294 LOAD_CONST            1873 ('kprkmutaqpumileg')
           7296 EXTENDED_ARG             7
           7298 LOAD_CONST            1874 ('dyfntcyriixrbzpu')
           7300 EXTENDED_ARG             7
           7302 LOAD_CONST            1875 ('pljixloqwehtiyju')
           7304 EXTENDED_ARG             7
           7306 LOAD_CONST            1876 ('guvbkiuixwtllbyh')
           7308 EXTENDED_ARG             7
           7310 LOAD_CONST            1877 ('aywoiniduriovexc')
           7312 EXTENDED_ARG             7
           7314 LOAD_CONST            1878 ('xkhsubtnkyitnjuu')
           7316 EXTENDED_ARG             7
           7318 LOAD_CONST            1879 ('orgjwbnwirxnlvkv')
           7320 EXTENDED_ARG             7
           7322 LOAD_CONST            1880 ('tbnfpmbwrdvlcids')
           7324 EXTENDED_ARG             7
           7326 LOAD_CONST            1881 ('ljptwryckhaervnt')
           7328 EXTENDED_ARG             7
           7330 LOAD_CONST            1882 ('piklsbpqrpcwtkax')
           7332 EXTENDED_ARG             7
           7334 LOAD_CONST            1883 ('btjqiwzsjhtyrabp')
           7336 EXTENDED_ARG             7
           7338 LOAD_CONST            1884 ('xaqhoeyrofnixysd')
           7340 EXTENDED_ARG             7
           7342 LOAD_CONST            1885 ('ildloryxoleksykm')
           7344 EXTENDED_ARG             7
           7346 LOAD_CONST            1886 ('tpkrvszvlfvhpgua')
           7348 EXTENDED_ARG             7
           7350 LOAD_CONST            1887 ('uomslwptxjarrgtp')
           7352 EXTENDED_ARG             7
           7354 LOAD_CONST            1888 ('qfawaceubqhtfqia')
           7356 EXTENDED_ARG             7
           7358 LOAD_CONST            1889 ('xvsatjnexaphrcsq')
           7360 EXTENDED_ARG             7
           7362 LOAD_CONST            1890 ('chlowdcammoiqswp')
           7364 EXTENDED_ARG             7
           7366 LOAD_CONST            1891 ('vryqjuplbwlaomsw')
           7368 EXTENDED_ARG             7
           7370 LOAD_CONST            1892 ('zkndhkyqnmooseqy')
           7372 EXTENDED_ARG             7
           7374 LOAD_CONST            1893 ('oehmlodyfkbgwggc')
           7376 EXTENDED_ARG             7
           7378 LOAD_CONST            1894 ('ygicydiozmvrkjov')
           7380 EXTENDED_ARG             7
           7382 LOAD_CONST            1895 ('vffghaadldklcvpa')
           7384 EXTENDED_ARG             7
           7386 LOAD_CONST            1896 ('dudkmcpnwktzabcyc')
           7388 EXTENDED_ARG             7
           7390 LOAD_CONST            1897 ('cgpwhbxlqbydfial')
           7392 EXTENDED_ARG             7
           7394 LOAD_CONST            1898 ('xkeqyrbppiqzzdtc')
           7396 EXTENDED_ARG             7
           7398 LOAD_CONST            1899 ('aywomxmmicyapqry')
           7400 EXTENDED_ARG             7
           7402 LOAD_CONST            1900 ('qxrfswxmtgqwiaiu')
           7404 EXTENDED_ARG             7
           7406 LOAD_CONST            1901 ('ogesstqnbrqzcike')
           7408 EXTENDED_ARG             7
           7410 LOAD_CONST            1902 ('quvgbtgtjtgxrqez')
           7412 EXTENDED_ARG             7
           7414 LOAD_CONST            1903 ('ilrohxbbjzdyifwb')
           7416 EXTENDED_ARG             7
           7418 LOAD_CONST            1904 ('mwbgfsetpneteejs')
           7420 EXTENDED_ARG             7
           7422 LOAD_CONST            1905 ('awvqavqersnsgvym')
           7424 EXTENDED_ARG             7
           7426 LOAD_CONST            1906 ('lslutwvxqsgrasxf')
           7428 EXTENDED_ARG             7
           7430 LOAD_CONST            1907 ('hujsniqoktvleeph')
           7432 EXTENDED_ARG             7
           7434 LOAD_CONST            1908 ('tbibnfjtibcusfqc')
           7436 EXTENDED_ARG             7
           7438 LOAD_CONST            1909 ('jkeeyrhwuudkrzmx')
           7440 EXTENDED_ARG             7
           7442 LOAD_CONST            1910 ('rckpwpavcgvgmbqn')
           7444 EXTENDED_ARG             7
           7446 LOAD_CONST            1911 ('drzbjsuvjgfxgpzx')
           7448 EXTENDED_ARG             7
           7450 LOAD_CONST            1912 ('kmdsvposrrdokxzu')
           7452 EXTENDED_ARG             7
           7454 LOAD_CONST            1913 ('lapmakjdxbobqslx')
           7456 EXTENDED_ARG             7
           7458 LOAD_CONST            1914 ('awqhcznyrcbreinx')
           7460 EXTENDED_ARG             7
           7462 LOAD_CONST            1915 ('sgtrrbfxpgcdmlfi')
           7464 EXTENDED_ARG             7
           7466 LOAD_CONST            1916 ('hjvvuazaydvuqzfl')
           7468 EXTENDED_ARG             7
           7470 LOAD_CONST            1917 ('ukvueksttoovtqnx')
           7472 EXTENDED_ARG             7
           7474 LOAD_CONST            1918 ('fjcjtxrbzsrxelui')
           7476 EXTENDED_ARG             7
           7478 LOAD_CONST            1919 ('ynxnlswchgyljfah')
           7480 EXTENDED_ARG             7
           7482 LOAD_CONST            1920 ('ueznbslrhcswvlvg')
           7484 EXTENDED_ARG             7
           7486 LOAD_CONST            1921 ('ixvfnmhdbnowsido')
           7488 EXTENDED_ARG             7
           7490 LOAD_CONST            1922 ('tnvrbemiduyabcpgf')
           7492 EXTENDED_ARG             7
           7494 LOAD_CONST            1923 ('xicjxbvnripjquxk')
           7496 EXTENDED_ARG             7
           7498 LOAD_CONST            1924 ('pnguepiandvkkjgm')
           7500 EXTENDED_ARG             7
           7502 LOAD_CONST            1925 ('fmjuyijqtflklzrz')
           7504 EXTENDED_ARG             7
           7506 LOAD_CONST            1926 ('wowbwesqdjgbnfza')
           7508 EXTENDED_ARG             7
           7510 LOAD_CONST            1927 ('bzhqulhhfrmvlikt')
           7512 EXTENDED_ARG             7
           7514 LOAD_CONST            1928 ('xwwbxkpqwzuvbfcc')
           7516 EXTENDED_ARG             7
           7518 LOAD_CONST            1929 ('tzfeejglmxpjfiob')
           7520 EXTENDED_ARG             7
           7522 LOAD_CONST            1930 ('ttvlzzgyydwznuuj')
           7524 EXTENDED_ARG             7
           7526 LOAD_CONST            1931 ('zsaqdcbxiivqeibj')
           7528 EXTENDED_ARG             7
           7530 LOAD_CONST            1932 ('jqhivhimzrbhfjye')
           7532 EXTENDED_ARG             7
           7534 LOAD_CONST            1933 ('woxtmnynlehbynso')
           7536 EXTENDED_ARG             7
           7538 LOAD_CONST            1934 ('tweacunvvzvxvkhe')
           7540 EXTENDED_ARG             7
           7542 LOAD_CONST            1935 ('wvjiwrdllmbrzyzh')
           7544 EXTENDED_ARG             7
           7546 LOAD_CONST            1936 ('kpawpohuffukizip')
           7548 EXTENDED_ARG             7
           7550 LOAD_CONST            1937 ('culggzusblbzrbvp')
           7552 EXTENDED_ARG             7
           7554 LOAD_CONST            1938 ('rfiaujemuathqnrg')
           7556 EXTENDED_ARG             7
           7558 LOAD_CONST            1939 ('txcebmnimvozhnbq')
           7560 EXTENDED_ARG             7
           7562 LOAD_CONST            1940 ('lbpnqjkgkmqepuca')
           7564 EXTENDED_ARG             7
           7566 LOAD_CONST            1941 ('rqfueobyxicwpkao')
           7568 EXTENDED_ARG             7
           7570 LOAD_CONST            1942 ('rggegjcjqzhrkjqn')
           7572 EXTENDED_ARG             7
           7574 LOAD_CONST            1943 ('xbxlktpwwsergaut')
           7576 EXTENDED_ARG             7
           7578 LOAD_CONST            1944 ('lhowgnysedqhcquk')
           7580 EXTENDED_ARG             7
           7582 LOAD_CONST            1945 ('oqldregahyfprwsi')
           7584 EXTENDED_ARG             7
           7586 LOAD_CONST            1946 ('dizcwcthvgopgnwx')
           7588 EXTENDED_ARG             7
           7590 LOAD_CONST            1947 ('bzpodvsqzlmeakvy')
           7592 EXTENDED_ARG             7
           7594 LOAD_CONST            1948 ('vclpieckqkxhblhl')
           7596 EXTENDED_ARG             7
           7598 LOAD_CONST            1949 ('lnvngowxjpgdkwfv')
           7600 EXTENDED_ARG             7
           7602 LOAD_CONST            1950 ('yvkdxviywwowawba')
           7604 EXTENDED_ARG             7
           7606 LOAD_CONST            1951 ('zxymzgtfqsshclgz')
           7608 EXTENDED_ARG             7
           7610 LOAD_CONST            1952 ('boqkrbmnsxvbiema')
           7612 EXTENDED_ARG             7
           7614 LOAD_CONST            1953 ('hoeexawhwjrohbxe')
           7616 EXTENDED_ARG             7
           7618 LOAD_CONST            1954 ('luocnssrsnrlbmyi')
           7620 EXTENDED_ARG             7
           7622 LOAD_CONST            1955 ('tduuyggdvgbfgmhw')
           7624 EXTENDED_ARG             7
           7626 LOAD_CONST            1956 ('frvhgulszabsrunb')
           7628 EXTENDED_ARG             7
           7630 LOAD_CONST            1957 ('vcsontpzpacsgobo')
           7632 EXTENDED_ARG             7
           7634 LOAD_CONST            1958 ('kaiqymcnijuixgvp')
           7636 EXTENDED_ARG             7
           7638 LOAD_CONST            1959 ('vgfugfulxkppkurw')
           7640 EXTENDED_ARG             7
           7642 LOAD_CONST            1960 ('foudqjgejntrwhke')
           7644 EXTENDED_ARG             7
           7646 LOAD_CONST            1961 ('abldoxtbpltfnsni')
           7648 EXTENDED_ARG             7
           7650 LOAD_CONST            1962 ('kqxvgbgkkoakfeaj')
           7652 EXTENDED_ARG             7
           7654 LOAD_CONST            1963 ('rdkjzlwcpygzkshq')
           7656 EXTENDED_ARG             7
           7658 LOAD_CONST            1964 ('qfjxzlkyrpmuvlrf')
           7660 EXTENDED_ARG             7
           7662 LOAD_CONST            1965 ('depydkicbtuwrbuf')
           7664 EXTENDED_ARG             7
           7666 LOAD_CONST            1966 ('vmpfhqfgcyreyqdl')
           7668 EXTENDED_ARG             7
           7670 LOAD_CONST            1967 ('oneokdfkplafayzn')
           7672 EXTENDED_ARG             7
           7674 LOAD_CONST            1968 ('fjcerifwgajithlr')
           7676 EXTENDED_ARG             7
           7678 LOAD_CONST            1969 ('gtlxawvwmlmqsuuu')
           7680 EXTENDED_ARG             7
           7682 LOAD_CONST            1970 ('wgfxdchxqlzdxcpr')
           7684 EXTENDED_ARG             7
           7686 LOAD_CONST            1971 ('ajdrspwucswacivi')
           7688 EXTENDED_ARG             7
           7690 LOAD_CONST            1972 ('wjzhtgddolhaahmo')
           7692 EXTENDED_ARG             7
           7694 LOAD_CONST            1973 ('hbyrafvgohzefptw')
           7696 EXTENDED_ARG             7
           7698 LOAD_CONST            1974 ('roxblqysntdnkfqx')
           7700 EXTENDED_ARG             7
           7702 LOAD_CONST            1975 ('rmvrjdkeppblcmvy')
           7704 EXTENDED_ARG             7
           7706 LOAD_CONST            1976 ('xzgbkvnyxljluccp')
           7708 EXTENDED_ARG             7
           7710 LOAD_CONST            1977 ('dvvwfjxmydfdzqyt')
           7712 EXTENDED_ARG             7
           7714 LOAD_CONST            1978 ('kxxjltlgbaiguihx')
           7716 EXTENDED_ARG             7
           7718 LOAD_CONST            1979 ('rahukefeaibeekpq')
           7720 EXTENDED_ARG             7
           7722 LOAD_CONST            1980 ('spsdfgpofpoanurm')
           7724 EXTENDED_ARG             7
           7726 LOAD_CONST            1981 ('pjmewktbcytjsvrs')
           7728 EXTENDED_ARG             7
           7730 LOAD_CONST            1982 ('nhtbcrwqzoxbhkyi')
           7732 EXTENDED_ARG             7
           7734 LOAD_CONST            1983 ('eanjdepcqzqdeoea')
           7736 EXTENDED_ARG             7
           7738 LOAD_CONST            1984 ('ujhvaizclocaksng')
           7740 EXTENDED_ARG             7
           7742 LOAD_CONST            1985 ('tkucqzszyktwvyjq')
           7744 EXTENDED_ARG             7
           7746 LOAD_CONST            1986 ('dnummodkocgrdhbx')
           7748 EXTENDED_ARG             7
           7750 LOAD_CONST            1987 ('bzvvgfxvgzqjshji')
           7752 EXTENDED_ARG             7
           7754 LOAD_CONST            1988 ('ddctbuygjncstchf')
           7756 EXTENDED_ARG             7
           7758 LOAD_CONST            1989 ('mrpciqjmowzdjvsm')
           7760 EXTENDED_ARG             7
           7762 LOAD_CONST            1990 ('qhdgxhopljagfbfi')
           7764 EXTENDED_ARG             7
           7766 LOAD_CONST            1991 ('ksnimciprjexohfu')
           7768 EXTENDED_ARG             7
           7770 LOAD_CONST            1992 ('sdfgsfcwgaknzrqt')
           7772 EXTENDED_ARG             7
           7774 LOAD_CONST            1993 ('keiywmjuavometzf')
           7776 EXTENDED_ARG             7
           7778 LOAD_CONST            1994 ('pxdzshicopwmofxl')
           7780 EXTENDED_ARG             7
           7782 LOAD_CONST            1995 ('xdwlukdaxhwjojeq')
           7784 EXTENDED_ARG             7
           7786 LOAD_CONST            1996 ('krnlgjtxhnuntwsa')
           7788 EXTENDED_ARG             7
           7790 LOAD_CONST            1997 ('bpnrhdwfkagaubka')
           7792 EXTENDED_ARG             7
           7794 LOAD_CONST            1998 ('beoyleogpryyjcmv')
           7796 EXTENDED_ARG             7
           7798 LOAD_CONST            1999 ('rrhlmtgpyfszchsi')
           7800 EXTENDED_ARG             7
           7802 LOAD_CONST            2000 ('ozdknlljectjisdg')
           7804 EXTENDED_ARG             7
           7806 LOAD_CONST            2001 ('wdobdazbwjecqcep')
           7808 EXTENDED_ARG             7
           7810 LOAD_CONST            2002 ('jfxjpbzonkvxltib')
           7812 EXTENDED_ARG             7
           7814 LOAD_CONST            2003 ('fwcffctkbvpkgexm')
           7816 EXTENDED_ARG             7
           7818 LOAD_CONST            2004 ('gornbkdvwuqirrlk')
           7820 EXTENDED_ARG             7
           7822 LOAD_CONST            2005 ('yyiqngwrxevbwchf')
           7824 EXTENDED_ARG             7
           7826 LOAD_CONST            2006 ('ggyqhxvbjwyzuxwf')
           7828 EXTENDED_ARG             7
           7830 LOAD_CONST            2007 ('ixhwkhgotdmkamtj')
           7832 EXTENDED_ARG             7
           7834 LOAD_CONST            2008 ('dbqqdygrhtysgxgw')
           7836 EXTENDED_ARG             7
           7838 LOAD_CONST            2009 ('mzwmkjfknwfhulgv')
           7840 EXTENDED_ARG             7
           7842 LOAD_CONST            2010 ('xtngfkkjuaonbemi')
           7844 EXTENDED_ARG             7
           7846 LOAD_CONST            2011 ('vghhkblxwbijsqwi')
           7848 EXTENDED_ARG             7
           7850 LOAD_CONST            2012 ('fkfulljgmpkmvxwn')
           7852 EXTENDED_ARG             7
           7854 LOAD_CONST            2013 ('kqdckewxfcwyjkuo')
           7856 EXTENDED_ARG             7
           7858 LOAD_CONST            2014 ('msaxmgcjerovxgqo')
           7860 EXTENDED_ARG             7
           7862 LOAD_CONST            2015 ('bswhhcxiljhjeivr')
           7864 EXTENDED_ARG             7
           7866 LOAD_CONST            2016 ('lwllrzomgnjzjqxh')
           7868 EXTENDED_ARG             7
           7870 LOAD_CONST            2017 ('gugxbiwfpjbtscyw')
           7872 EXTENDED_ARG             7
           7874 LOAD_CONST            2018 ('mmqsxwrnsiprrmyv')
           7876 EXTENDED_ARG             7
           7878 LOAD_CONST            2019 ('pdjccwbewqxbhgzn')
           7880 EXTENDED_ARG             7
           7882 LOAD_CONST            2020 ('mshemwgzytwmqljx')
           7884 EXTENDED_ARG             7
           7886 LOAD_CONST            2021 ('moezekitiafkvsqr')
           7888 EXTENDED_ARG             7
           7890 LOAD_CONST            2022 ('edthrvvafeypjypw')
           7892 EXTENDED_ARG             7
           7894 LOAD_CONST            2023 ('qspowcqalsukqhhy')
           7896 EXTENDED_ARG             7
           7898 LOAD_CONST            2024 ('wasrmlhgjgalcbrb')
           7900 EXTENDED_ARG             7
           7902 LOAD_CONST            2025 ('dglyfamnfpqkmteh')
           7904 EXTENDED_ARG             7
           7906 LOAD_CONST            2026 ('xgpvsclrqskbjnao')
           7908 EXTENDED_ARG             7
           7910 LOAD_CONST            2027 ('iawgyqoqnmxmwtrk')
           7912 EXTENDED_ARG             3
           7914 BUILD_LIST            1000
           7916 CALL_FUNCTION            1
           7918 COMPARE_OP               2 (==)
           7920 EXTENDED_ARG            30
           7922 POP_JUMP_IF_TRUE      7928
           7924 LOAD_GLOBAL             19 (AssertionError)
           7926 RAISE_VARARGS            1

114     >> 7928 LOAD_NAME                5 (calc)
           7930 LOAD_NAME                8 (num1)
           7932 LOAD_NAME                9 (num2)
           7934 LOAD_NAME               10 (num3)
           7936 BUILD_LIST               3
           7938 CALL_FUNCTION            1
           7940 STORE_NAME              20 (s)
        >> 7942 LOAD_CONST               1 (None)
           7944 RETURN_VALUE

Disassembly of <code object func1 at 0x0000019D4A0797C0, file "<dis>", line 4>:
  5           0 LOAD_GLOBAL              0 (arr)
              2 LOAD_FAST                1 (i)
              4 LOAD_GLOBAL              1 (len)
              6 LOAD_FAST                0 (lss)
              8 CALL_FUNCTION            1
             10 BINARY_MULTIPLY
             12 LOAD_FAST                2 (j)
             14 BINARY_ADD
             16 BINARY_SUBSCR
             18 LOAD_CONST               1 (-1)
             20 COMPARE_OP               3 (!=)
             22 POP_JUMP_IF_FALSE       44

  6          24 LOAD_GLOBAL              0 (arr)
             26 LOAD_FAST                1 (i)
             28 LOAD_GLOBAL              1 (len)
             30 LOAD_FAST                0 (lss)
             32 CALL_FUNCTION            1
             34 BINARY_MULTIPLY
             36 LOAD_FAST                2 (j)
             38 BINARY_ADD
             40 BINARY_SUBSCR
             42 RETURN_VALUE

  8     >>   44 LOAD_GLOBAL              2 (list)
             46 LOAD_FAST                0 (lss)
             48 LOAD_FAST                1 (i)
             50 BINARY_SUBSCR
             52 CALL_FUNCTION            1
             54 LOAD_GLOBAL              2 (list)
             56 LOAD_FAST                0 (lss)
             58 LOAD_FAST                2 (j)
             60 BINARY_SUBSCR
             62 CALL_FUNCTION            1
             64 ROT_TWO
             66 STORE_FAST               3 (s1)
             68 STORE_FAST               4 (s2)

  9          70 LOAD_GLOBAL              1 (len)
             72 LOAD_FAST                3 (s1)
             74 CALL_FUNCTION            1
             76 LOAD_GLOBAL              1 (len)
             78 LOAD_FAST                4 (s2)
             80 CALL_FUNCTION            1
             82 ROT_TWO
             84 STORE_FAST               5 (l1)
             86 STORE_FAST               6 (l2)

 11          88 LOAD_CONST               2 (True)
             90 STORE_FAST               7 (flag)

 12          92 LOAD_CONST               3 (0)
             94 STORE_FAST               8 (n)

 13          96 LOAD_FAST                5 (l1)
             98 LOAD_FAST                6 (l2)
            100 BINARY_SUBTRACT
            102 LOAD_CONST               4 (1)
            104 COMPARE_OP               2 (==)
            106 POP_JUMP_IF_FALSE      216

 14         108 LOAD_GLOBAL              3 (range)
            110 LOAD_FAST                5 (l1)
            112 CALL_FUNCTION            1
            114 GET_ITER
        >>  116 FOR_ITER                96 (to 214)
            118 STORE_FAST               9 (m)

 15         120 LOAD_FAST                3 (s1)
            122 LOAD_FAST                9 (m)
            124 BINARY_SUBSCR
            126 LOAD_FAST                4 (s2)
            128 LOAD_FAST                8 (n)
            130 BINARY_SUBSCR
            132 COMPARE_OP               3 (!=)
            134 POP_JUMP_IF_FALSE      192

 16         136 LOAD_FAST                7 (flag)
            138 POP_JUMP_IF_FALSE      146

 17         140 LOAD_CONST               5 (False)
            142 STORE_FAST               7 (flag)
            144 JUMP_ABSOLUTE          212

 19     >>  146 LOAD_CONST               3 (0)
            148 LOAD_GLOBAL              0 (arr)
            150 LOAD_FAST                1 (i)
            152 LOAD_GLOBAL              1 (len)
            154 LOAD_FAST                0 (lss)
            156 CALL_FUNCTION            1
            158 BINARY_MULTIPLY
            160 LOAD_FAST                2 (j)
            162 BINARY_ADD
            164 STORE_SUBSCR

 20         166 LOAD_GLOBAL              0 (arr)
            168 LOAD_FAST                1 (i)
            170 LOAD_GLOBAL              1 (len)
            172 LOAD_FAST                0 (lss)
            174 CALL_FUNCTION            1
            176 BINARY_MULTIPLY
            178 LOAD_FAST                2 (j)
            180 BINARY_ADD
            182 BINARY_SUBSCR
            184 ROT_TWO
            186 POP_TOP
            188 RETURN_VALUE
            190 JUMP_ABSOLUTE          116

 22     >>  192 LOAD_FAST                8 (n)
            194 LOAD_CONST               4 (1)
            196 INPLACE_ADD
            198 STORE_FAST               8 (n)

 23         200 LOAD_FAST                8 (n)
            202 LOAD_FAST                6 (l2)
            204 COMPARE_OP               2 (==)
            206 POP_JUMP_IF_FALSE      116

 24         208 POP_TOP
            210 JUMP_ABSOLUTE          214
        >>  212 JUMP_ABSOLUTE          116
        >>  214 JUMP_FORWARD            40 (to 256)

 26     >>  216 LOAD_CONST               3 (0)
            218 LOAD_GLOBAL              0 (arr)
            220 LOAD_FAST                1 (i)
            222 LOAD_GLOBAL              1 (len)
            224 LOAD_FAST                0 (lss)
            226 CALL_FUNCTION            1
            228 BINARY_MULTIPLY
            230 LOAD_FAST                2 (j)
            232 BINARY_ADD
            234 STORE_SUBSCR

 27         236 LOAD_GLOBAL              0 (arr)
            238 LOAD_FAST                1 (i)
            240 LOAD_GLOBAL              1 (len)
            242 LOAD_FAST                0 (lss)
            244 CALL_FUNCTION            1
            246 BINARY_MULTIPLY
            248 LOAD_FAST                2 (j)
            250 BINARY_ADD
            252 BINARY_SUBSCR
            254 RETURN_VALUE

 29     >>  256 LOAD_CONST               4 (1)
            258 LOAD_GLOBAL              0 (arr)
            260 LOAD_FAST                1 (i)
            262 LOAD_GLOBAL              1 (len)
            264 LOAD_FAST                0 (lss)
            266 CALL_FUNCTION            1
            268 BINARY_MULTIPLY
            270 LOAD_FAST                2 (j)
            272 BINARY_ADD
            274 STORE_SUBSCR

 30         276 LOAD_CONST               4 (1)
            278 RETURN_VALUE

Disassembly of <code object abc at 0x0000019D4A079870, file "<dis>", line 33>:
 34           0 LOAD_GLOBAL              0 (abcarray)
              2 LOAD_FAST                1 (i)
              4 BINARY_SUBSCR
              6 LOAD_CONST               1 (0)
              8 COMPARE_OP               4 (>)
             10 POP_JUMP_IF_FALSE       20

 35          12 LOAD_GLOBAL              0 (abcarray)
             14 LOAD_FAST                1 (i)
             16 BINARY_SUBSCR
             18 RETURN_VALUE

 37     >>   20 LOAD_CONST               2 (1)
             22 STORE_FAST               2 (m)

 38          24 LOAD_GLOBAL              1 (enumerate)
             26 LOAD_FAST                0 (lss)
             28 CALL_FUNCTION            1
             30 GET_ITER
        >>   32 FOR_ITER                44 (to 78)
             34 UNPACK_SEQUENCE          2
             36 STORE_FAST               3 (index)
             38 STORE_FAST               4 (word)

 41          40 LOAD_GLOBAL              2 (func1)
             42 LOAD_FAST                0 (lss)
             44 LOAD_FAST                1 (i)
             46 LOAD_FAST                3 (index)
             48 CALL_FUNCTION            3
             50 LOAD_CONST               2 (1)
             52 COMPARE_OP               2 (==)
             54 POP_JUMP_IF_FALSE       32

 42          56 LOAD_GLOBAL              3 (max)
             58 LOAD_FAST                2 (m)
             60 LOAD_GLOBAL              4 (abc)
             62 LOAD_FAST                0 (lss)
             64 LOAD_FAST                3 (index)
             66 CALL_FUNCTION            2
             68 LOAD_CONST               2 (1)
             70 BINARY_ADD
             72 CALL_FUNCTION            2
             74 STORE_FAST               2 (m)
             76 JUMP_ABSOLUTE           32

 44     >>   78 LOAD_FAST                2 (m)
             80 LOAD_GLOBAL              0 (abcarray)
             82 LOAD_FAST                1 (i)
             84 STORE_SUBSCR

 45          86 LOAD_FAST                2 (m)
             88 RETURN_VALUE

Disassembly of <code object solution at 0x0000019D4A079920, file "<dis>", line 48>:
 50           0 LOAD_CONST               1 (-1)
              2 BUILD_LIST               1
              4 LOAD_GLOBAL              0 (len)
              6 LOAD_FAST                0 (lss)
              8 CALL_FUNCTION            1
             10 BINARY_MULTIPLY
             12 STORE_GLOBAL             1 (abcarray)

 52          14 LOAD_CONST               1 (-1)
             16 BUILD_LIST               1
             18 LOAD_GLOBAL              0 (len)
             20 LOAD_FAST                0 (lss)
             22 CALL_FUNCTION            1
             24 LOAD_GLOBAL              0 (len)
             26 LOAD_FAST                0 (lss)
             28 CALL_FUNCTION            1
             30 BINARY_MULTIPLY
             32 BINARY_MULTIPLY
             34 STORE_GLOBAL             2 (arr)

 54          36 LOAD_CONST               2 (1)
             38 STORE_FAST               1 (ans)

 55          40 LOAD_GLOBAL              3 (range)
             42 LOAD_GLOBAL              0 (len)
             44 LOAD_FAST                0 (lss)
             46 CALL_FUNCTION            1
             48 CALL_FUNCTION            1
             50 GET_ITER
        >>   52 FOR_ITER                20 (to 74)
             54 STORE_FAST               2 (i)

 56          56 LOAD_GLOBAL              4 (max)
             58 LOAD_FAST                1 (ans)
             60 LOAD_GLOBAL              5 (abc)
             62 LOAD_FAST                0 (lss)
             64 LOAD_FAST                2 (i)
             66 CALL_FUNCTION            2
             68 CALL_FUNCTION            2
             70 STORE_FAST               1 (ans)
             72 JUMP_ABSOLUTE           52

 57     >>   74 LOAD_FAST                1 (ans)
             76 RETURN_VALUE

Disassembly of <code object func2 at 0x0000019D4A0799D0, file "<dis>", line 60>:
 61           0 LOAD_CONST               1 ((1, 1))
              2 UNPACK_SEQUENCE          2
              4 STORE_FAST               1 (a)
              6 STORE_FAST               2 (b)

 62           8 LOAD_GLOBAL              0 (range)
             10 LOAD_FAST                0 (n)
             12 LOAD_CONST               2 (1)
             14 BINARY_SUBTRACT
             16 CALL_FUNCTION            1
             18 GET_ITER
        >>   20 FOR_ITER                18 (to 40)
             22 STORE_FAST               3 (i)

 63          24 LOAD_FAST                2 (b)
             26 LOAD_FAST                1 (a)
             28 LOAD_FAST                2 (b)
             30 BINARY_ADD
             32 ROT_TWO
             34 STORE_FAST               1 (a)
             36 STORE_FAST               2 (b)
             38 JUMP_ABSOLUTE           20

 64     >>   40 LOAD_FAST                1 (a)
             42 RETURN_VALUE

Disassembly of <code object calc at 0x0000019D4A079B30, file "<dis>", line 67>:
 68           0 LOAD_FAST                0 (nums)
              2 LOAD_CONST               1 (0)
              4 BINARY_SUBSCR
              6 LOAD_FAST                0 (nums)
              8 LOAD_CONST               2 (1)
             10 BINARY_SUBSCR
             12 LOAD_FAST                0 (nums)
             14 LOAD_CONST               3 (2)
             16 BINARY_SUBSCR
             18 ROT_THREE
             20 ROT_TWO
             22 STORE_FAST               1 (num1)
             24 STORE_FAST               2 (num2)
             26 STORE_FAST               3 (num3)

 69          28 LOAD_CONST               4 (2023)
             30 LOAD_FAST                1 (num1)
             32 LOAD_CONST               5 (15)
             34 BINARY_AND
             36 BINARY_ADD
             38 LOAD_FAST                1 (num1)
             40 LOAD_CONST               6 (240)
             42 BINARY_AND
             44 BINARY_SUBTRACT
             46 STORE_FAST               1 (num1)

 70          48 LOAD_GLOBAL              0 (func2)
             50 LOAD_FAST                2 (num2)
             52 LOAD_CONST               7 (7)
             54 BINARY_ADD
             56 CALL_FUNCTION            1
             58 STORE_FAST               2 (num2)

 71          60 LOAD_GLOBAL              1 (random)
             62 LOAD_METHOD              2 (seed)
             64 LOAD_FAST                3 (num3)
             66 CALL_METHOD              1
             68 POP_TOP

 72          70 LOAD_FAST                1 (num1)
             72 FORMAT_VALUE             0
             74 LOAD_FAST                2 (num2)
             76 FORMAT_VALUE             0
             78 LOAD_FAST                3 (num3)
             80 FORMAT_VALUE             0
             82 LOAD_GLOBAL              1 (random)
             84 LOAD_METHOD              3 (gauss)
             86 LOAD_FAST                2 (num2)
             88 LOAD_CONST               8 (0.2)
             90 CALL_METHOD              2
             92 FORMAT_VALUE             0
             94 BUILD_STRING             4
             96 STORE_FAST               4 (flag)

 73          98 LOAD_FAST                4 (flag)
            100 LOAD_METHOD              4 (replace)
            102 LOAD_CONST               9 ('.')
            104 LOAD_CONST              10 ('x')
            106 CALL_METHOD              2
            108 STORE_FAST               4 (flag)

 74         110 LOAD_GLOBAL              5 (print)
            112 LOAD_CONST              11 ('flag=')
            114 LOAD_FAST                4 (flag)
            116 CALL_FUNCTION            2
            118 POP_TOP

 75         120 LOAD_FAST                4 (flag)
            122 RETURN_VALUE

Disassembly of <code object encode at 0x0000019D4A079BE0, file "<dis>", line 78>:
 79           0 BUILD_LIST               0
              2 STORE_FAST               1 (ret)

 80           4 LOAD_GLOBAL              0 (list)
              6 LOAD_FAST                0 (s)
              8 CALL_FUNCTION            1
             10 STORE_FAST               2 (ls)

 81          12 LOAD_GLOBAL              1 (range)
             14 LOAD_CONST               1 (0)
             16 LOAD_GLOBAL              2 (len)
             18 LOAD_FAST                2 (ls)
             20 CALL_FUNCTION            1
             22 LOAD_CONST               2 (2)
             24 CALL_FUNCTION            3
             26 GET_ITER
        >>   28 FOR_ITER                90 (to 120)
             30 STORE_FAST               3 (i)

 82          32 LOAD_GLOBAL              3 (ord)
             34 LOAD_FAST                2 (ls)
             36 LOAD_FAST                3 (i)
             38 BINARY_SUBSCR
             40 CALL_FUNCTION            1
             42 STORE_FAST               4 (num1)

 83          44 LOAD_GLOBAL              3 (ord)
             46 LOAD_FAST                2 (ls)
             48 LOAD_FAST                3 (i)
             50 LOAD_CONST               3 (1)
             52 BINARY_ADD
             54 BINARY_SUBSCR
             56 CALL_FUNCTION            1
             58 STORE_FAST               5 (num2)

 84          60 LOAD_FAST                4 (num1)
             62 LOAD_CONST               4 (248)
             64 BINARY_AND
             66 LOAD_CONST               5 (3)
             68 BINARY_RSHIFT
             70 STORE_FAST               6 (numa)

 85          72 LOAD_FAST                4 (num1)
             74 LOAD_CONST               6 (7)
             76 BINARY_AND
             78 LOAD_CONST               5 (3)
             80 BINARY_LSHIFT
             82 LOAD_FAST                5 (num2)
             84 LOAD_CONST               7 (240)
             86 BINARY_AND
             88 LOAD_CONST               8 (4)
             90 BINARY_RSHIFT
             92 BINARY_OR
             94 STORE_FAST               7 (numb)

 86          96 LOAD_FAST                5 (num2)
             98 LOAD_CONST               9 (15)
            100 BINARY_AND
            102 STORE_FAST               8 (numc)

 87         104 LOAD_FAST                1 (ret)
            106 LOAD_FAST                6 (numa)
            108 LOAD_FAST                7 (numb)
            110 LOAD_FAST                8 (numc)
            112 BUILD_LIST               3
            114 BINARY_ADD
            116 STORE_FAST               1 (ret)
            118 JUMP_ABSOLUTE           28

 88     >>  120 LOAD_FAST                1 (ret)
            122 RETURN_VALUE
